Workbook

Sheet Read Me & Sources
A1: Cross-hedging castor meal with NCDEX castor seed futures: Read Me & Sources
A3: ASSIGNMENT
A4: Hedge a castor meal price exposure (Asset A) with NCDEX castor seed futures (Asset B), because no castor meal futures contract exists. Use about three years of daily data; estimate the optimal hedge; measure in-sample hedge effectiveness; test it out of sample; deal with futures roll and data problems using the two course papers.
A6: DATA SOURCES
A7: Item | B7: Publisher | C7: Source | D7: Field used | E7: Unit
A8: Asset A: castor meal spot | B8: The Solvent Extractors' Association of India (SEA) | C8: https://seaofindia.com/seaquotes/ (one page per day; URLs in Spot Data) | D8: Castormeal Ext (FOR) (Bulk) (Ex-Kandla) | E8: Rs/MT
A9: Asset B: castor seed futures | B9: National Commodity & Derivatives Exchange (NCDEX) | C9: https://www.ncdex.com/markets/bhavcopy (daily ZIP, FO_DDMMYY_FINAL.csv) | D9: CASTOR contracts: close, volume, open interest, expiry | E9: Rs/quintal; MT
A10: CASTOR contract rules | B10: NCDEX | C10: https://www.ncdex.com/public/uploads/downloads/Contract%20Specifications%20Castor%20Futures%20Contract_31082026_1788157717.pdf | D10: Expiry 20th (or previous trading day); compulsory delivery; tender period last 3 trading days
A11: Pre-expiry margin (context) | B11: NCCL (NCDEX clearing) | C11: https://www.ncdex.com/public/uploads/circulars/Pre_Expiry_Margin_Castor_04082022_1659619001.pdf | D11: Margin over last 7 trading days (2022 circular)
A12: Method papers | B12: Course material | C12: paper_1.pdf: Continuous Contracts Explained; paper_2.pdf: Buyukkara, Kucukozmen & Uysal (2022), Borsa Istanbul Review 22-1, 92-102
A14: SAMPLE COVERAGE (live formulas)
A15: Spot quotes used: first / last / count | C15: =TEXT(_xlfn.MINIFS('Spot Data'!$A$5:$A$651,'Spot Data'!$H$5:$H$651,"YES"),"dd mmm yyyy")&" to "&TEXT(_xlfn.MAXIFS('Spot Data'!$A$5:$A$651,'Spot Data'!$H$5:$H$651,"YES"),"dd mmm yyyy")&" ("&COUNTIF('Spot Data'!$H$5:$H$651,"YES")&" quotes)" -> 25 Sep 2023 to 28 Sep 2026 (546 quotes)
A16: Futures trading days: first / last / count | C16: =TEXT(MIN('Roll Schedule'!A47:A790),"dd mmm yyyy")&" to "&TEXT(MAX('Roll Schedule'!A47:A790),"dd mmm yyyy")&" ("&COUNT('Roll Schedule'!A47:A790)&" days)" -> 25 Sep 2023 to 28 Sep 2026 (744 days)
A17: Common price dates (NCDEX trading day with a used SEA quote) | C17: =TEXT(_xlfn.MINIFS('Spot Data'!$A$5:$A$651,'Spot Data'!$H$5:$H$651,"YES",'Spot Data'!$I$5:$I$651,TRUE()),"dd mmm yyyy")&" to "&TEXT(_xlfn.MAXIFS('Spot Data'!$A$5:$A$651,'Spot Data'!$H$5:$H$651,"YES",'Spot Data'!$I$5:$I$651,TRUE()),"dd mmm yyyy")&" ("&COUNTIFS('Spot Data'!$H$5:$H$651,"YES",'Spot Data'!$I$5:$I$651,TRUE())&" dates)" -> 25 Sep 2023 to 28 Sep 2026 (535 dates)
A18: Return dates: first / last / count | C18: =TEXT(MIN('Daily Analysis'!A5:A500),"dd mmm yyyy")&" to "&TEXT(MAX('Daily Analysis'!A5:A500),"dd mmm yyyy")&" ("&COUNT('Daily Analysis'!H5:H500)&" returns)" -> 26 Sep 2023 to 28 Sep 2026 (496 returns)
A19: In-sample returns | C19: =TEXT('Results & Charts'!D18,"dd mmm yyyy")&" to "&TEXT('Results & Charts'!E18,"dd mmm yyyy")&" ("&'Results & Charts'!F18&")" -> 26 Sep 2023 to 26 Sep 2025 (275)
A20: Out-of-sample returns | C20: =TEXT('Results & Charts'!D19,"dd mmm yyyy")&" to "&TEXT('Results & Charts'!E19,"dd mmm yyyy")&" ("&'Results & Charts'!F19&")" -> 01 Oct 2025 to 28 Sep 2026 (221)
A21: Calendar coverage is three full years of returns (26 Sep 2023 to 28 Sep 2026), BUT SEA published no castor meal quote from 27 Apr 2024 to 3 Dec 2024 (castor meal marked NQ May-Sep 2024; almost no posts Oct-Nov 2024). No returns exist for that gap; nothing is filled. SEA quotes on non-NCDEX days are listed but not used.
A23: METHOD AND ITS BASIS
A24: Step | B24: What is done | C24: Basis | D24: Classification | E24: Where
A25: Contracts kept separate | B25: Every CASTOR contract kept by expiry; continuous series built by an explicit rule | C25: CCE p.1 | D25: Prescribed in paper | E25: Futures Data, Roll Schedule
A26: Roll signal | B26: Next-month open interest larger than held month's | C26: CCE p.2 ('volume and/or open interest') | D26: Prescribed (OI chosen over volume: adaptation) | E26: Roll Schedule E-H
A27: Execution timing | B27: Signal read from the day's published file, acted on at the next close | C27: Not specified in either paper | D27: Project adaptation (removes look-ahead) | E27: Roll Schedule C
A28: Backstop | B28: Forced roll when 7 NCDEX trading days remain | C28: CCE p.1-2 notice-day argument; NCDEX tender period; NCCL pre-expiry margin | D28: Project adaptation | E28: Roll Schedule G4
A29: Roll gap and back-adjustment | B29: Gap = new close - old close on roll day; back-adjusted = stitched + later gaps | C29: CCE p.7-8 | D29: Prescribed in paper | E29: Roll Schedule J-N
A30: Hedge returns | B30: LN return of the contract actually held, never across two contracts | C30: BKU eq. (1)-(2); CCE p.9 'trading reality' | D30: Prescribed returns, applied per held contract (adaptation) | E30: Roll Schedule O; Daily Analysis I
A31: OLS hedge ratio | B31: SLOPE of rA on rF, in-sample only | C31: BKU eq. (3), p.96 | D31: Prescribed | E31: Results Table 1
A32: Naive hedge | B32: h = 1 | C32: BKU p.95 | D32: Prescribed | E32: Results Table 2
A33: Dynamic hedge | B33: Diagonal VECH GARCH(1,1), h_t = H12/H22 | C33: BKU eq. (4)-(8), p.96 | D33: Prescribed (estimated in-sample, fixed out-of-sample: adaptation) | E33: Results Table 4
A34: Hedge effectiveness | B34: 1 - Var(hedged)/Var(unhedged) | C34: BKU eq. (11)-(13), p.97 | D34: Prescribed (eq. 10 printed sign inconsistent with eq. 12; eq. 12 used) | E34: Results Table 2
A35: Out-of-sample test | B35: Chronological split at 30 Sep 2025 | C35: Assignment brief (paper uses sub-periods, not out-of-sample) | D35: Additional to papers | E35: Results Table 2
... A37: Roll comparison | B37: Five rules on identical dates | C37: CCE p.2 (compare roll schedules) | D37: Prescribed idea; rules are adaptations | E37: Results Table 6
A39: CCE = Continuous Contracts Explained (paper_1.pdf, PDF page numbers). BKU = Buyukkara, Kucukozmen & Uysal (2022) (journal page numbers).
A41: DEFINITIONS AND TREATMENT OF DATA
A42: - Return pair: two consecutive NCDEX trading days, both with a used SEA quote. Weekends and holidays are skipped naturally (a Monday return spans Friday-Monday).
A43: - Missing SEA quote (NQ, row absent, excluded post): no return is formed for the pairs touching that date. Nothing is interpolated or carried forward.
A44: - Unchanged SEA quote: a genuine zero return; kept.
A45: - SEA quote on a non-NCDEX day: listed in Spot Data; not used.
A46: - Futures price: NCDEX closing price. Settlement price is absent from files before 8 Jul 2024, so close is used throughout.
A47: - Colour key: blue = source value or Python output; black = formula; green = link; yellow = input.
A49: KEY ASSUMPTIONS AND LIMITATIONS: see 'Results & Charts' (bottom) and the separate results_and_limitations.md.
A50: Supporting files (not needed to audit the workbook): full paper-method matrix, audit and change log, Python scripts, raw exchange ZIPs and SEA pages.

Sheet Spot Data
A1: Spot Data: castor meal quotes published by The Solvent Extractors' Association of India (SEA). NOT NCDEX data.
A2: Quote: 'Castormeal Ext (FOR) (Bulk) (Ex-Kandla)', Rs per metric tonne. One SEA post per day; every post in the window is listed, including excluded ones. Values unchanged from the source.
A4: Quote date | B4: Post title | C4: Published (IST) | D4: Castor meal cell as published | E4: Price (Rs/MT) | F4: Date rule | G4: Status | H4: Used in analysis | I4: NCDEX trading day? | J4: Live check | K4: Source URL
A5: 45194 | B5: 25th September 23 | C5: 2023-09-25T17:32:41 | D5: Rs./ MT 9575 | E5: 9575 | F5: A_title | G5: OK | H5: =IF(G5="OK","YES","no") -> YES | I5: =COUNTIF('Roll Schedule'!$A$47:$A$790,A5)>0 -> TRUE | J5: fetched 29 Sep 2026 (new post) | K5: https://seaofindia.com/seaquotes/25th-september-23/
A6: 45195 | B6: 26th September 23 | C6: 2023-09-26T17:23:30 | D6: Rs./ MT 9500 | E6: 9500 | F6: A_title | G6: OK | H6: =IF(G6="OK","YES","no") -> YES | I6: =COUNTIF('Roll Schedule'!$A$47:$A$790,A6)>0 -> TRUE | J6: fetched 29 Sep 2026 (new post) | K6: https://seaofindia.com/seaquotes/26th-september-23/
A7: 45196 | B7: 28th September 2023 | C7: 2023-09-27T16:59:38 | D7: Rs./ MT 9450 | E7: 9450 | F7: B_pub_title_implausible | G7: EXCLUDED: uncertain publication date | H7: =IF(G7="OK","YES","no") -> no | I7: =COUNTIF('Roll Schedule'!$A$47:$A$790,A7)>0 -> TRUE | J7: fetched 29 Sep 2026 (new post) | K7: https://seaofindia.com/seaquotes/28th-september-2023/
A8: 45198 | B8: 29th September 23 | C8: 2023-09-29T17:34:34 | D8: Rs./ MT 9450 | E8: 9450 | F8: A_title | G8: OK | H8: =IF(G8="OK","YES","no") -> YES | I8: =COUNTIF('Roll Schedule'!$A$47:$A$790,A8)>0 -> TRUE | J8: fetched 29 Sep 2026 (new post) | K8: https://seaofindia.com/seaquotes/29th-september-23/
A9: 45202 | B9: 3rd October 23 | C9: 2023-10-03T17:25:44 | D9: Rs./ MT 9350 | E9: 9350 | F9: A_title | G9: OK | H9: =IF(G9="OK","YES","no") -> YES | I9: =COUNTIF('Roll Schedule'!$A$47:$A$790,A9)>0 -> TRUE | J9: matches live page 29 Sep 2026 | K9: https://seaofindia.com/seaquotes/3rd-october-23/
A10: 45203 | B10: 4th October 23 | C10: 2023-10-04T17:33:09 | D10: Rs./ MT 9150 | E10: 9150 | F10: A_title | G10: OK | H10: =IF(G10="OK","YES","no") -> YES | I10: =COUNTIF('Roll Schedule'!$A$47:$A$790,A10)>0 -> TRUE | J10: matches live page 29 Sep 2026 | K10: https://seaofindia.com/seaquotes/4th-october-23/
A11: 45204 | B11: 5th October 23 | C11: 2023-10-05T17:17:31 | D11: Rs./ MT 9000 | E11: 9000 | F11: A_title | G11: OK | H11: =IF(G11="OK","YES","no") -> YES | I11: =COUNTIF('Roll Schedule'!$A$47:$A$790,A11)>0 -> TRUE | J11: matches live page 29 Sep 2026 | K11: https://seaofindia.com/seaquotes/5th-october-23/
A12: 45205 | B12: 6th October 23 | C12: 2023-10-06T17:43:33 | D12: Rs./ MT 8950 | E12: 8950 | F12: A_title | G12: OK | H12: =IF(G12="OK","YES","no") -> YES | I12: =COUNTIF('Roll Schedule'!$A$47:$A$790,A12)>0 -> TRUE | J12: matches live page 29 Sep 2026 | K12: https://seaofindia.com/seaquotes/6th-october-23/
A13: 45208 | B13: 9th October 23 | C13: 2023-10-09T17:28:05 | D13: Rs./ MT 8875 | E13: 8875 | F13: A_title | G13: OK | H13: =IF(G13="OK","YES","no") -> YES | I13: =COUNTIF('Roll Schedule'!$A$47:$A$790,A13)>0 -> TRUE | J13: matches live page 29 Sep 2026 | K13: https://seaofindia.com/seaquotes/9th-october-23/
A14: 45209 | B14: 10th October 23 | C14: 2023-10-10T17:25:14 | D14: Rs./ MT 8950 | E14: 8950 | F14: A_title | G14: OK | H14: =IF(G14="OK","YES","no") -> YES | I14: =COUNTIF('Roll Schedule'!$A$47:$A$790,A14)>0 -> TRUE | J14: matches live page 29 Sep 2026 | K14: https://seaofindia.com/seaquotes/10th-october-23/
A15: 45210 | B15: 11th October 23 | C15: 2023-10-11T17:25:49 | D15: Rs./ MT 8800 | E15: 8800 | F15: A_title | G15: OK | H15: =IF(G15="OK","YES","no") -> YES | I15: =COUNTIF('Roll Schedule'!$A$47:$A$790,A15)>0 -> TRUE | J15: matches live page 29 Sep 2026 | K15: https://seaofindia.com/seaquotes/11th-october-23/
A16: 45211 | B16: 12th October 23 | C16: 2023-10-12T17:35:08 | D16: Rs./ MT 8700 | E16: 8700 | F16: A_title | G16: OK | H16: =IF(G16="OK","YES","no") -> YES | I16: =COUNTIF('Roll Schedule'!$A$47:$A$790,A16)>0 -> TRUE | J16: matches live page 29 Sep 2026 | K16: https://seaofindia.com/seaquotes/12th-october-23/
... A29: 45232 | B29: 2nd Nov 23 | C29: 2023-11-02T17:33:07 | D29: Rs./ MT 7800 | E29: 7800 | F29: A_title | G29: OK | H29: =IF(G29="OK","YES","no") -> YES | I29: =COUNTIF('Roll Schedule'!$A$47:$A$790,A29)>0 -> TRUE | J29: matches live page 29 Sep 2026 | K29: https://seaofindia.com/seaquotes/2nd-nov-23/
A30: 45233 | C30: 2023-11-03T17:26:11 | D30: Rs./ M T 7950 | E30: 7950 | F30: D_pub_no_usable_title | G30: EXCLUDED: uncertain publication date | H30: =IF(G30="OK","YES","no") -> no | I30: =COUNTIF('Roll Schedule'!$A$47:$A$790,A30)>0 -> TRUE | J30: matches live page 29 Sep 2026 | K30: https://seaofindia.com/seaquotes/11726-2/
A31: 45237 | B31: 7th November 23 | C31: 2023-11-07T17:19:39 | D31: Rs./ MT 7950 | E31: 7950 | F31: A_title | G31: OK | H31: =IF(G31="OK","YES","no") -> YES | I31: =COUNTIF('Roll Schedule'!$A$47:$A$790,A31)>0 -> TRUE | J31: matches live page 29 Sep 2026 | K31: https://seaofindia.com/seaquotes/7th-november-23/
A32: 45239 | B32: 9th November 23 | C32: 2023-11-09T17:19:49 | D32: Rs./ MT 7950 | E32: 7950 | F32: A_title | G32: OK | H32: =IF(G32="OK","YES","no") -> YES | I32: =COUNTIF('Roll Schedule'!$A$47:$A$790,A32)>0 -> TRUE | J32: matches live page 29 Sep 2026 | K32: https://seaofindia.com/seaquotes/9th-november-23/
A33: 45240 | C33: 2023-11-10T17:30:39 | D33: Rs./ MT 7950 | E33: 7950 | F33: D_pub_no_usable_title | G33: EXCLUDED: uncertain publication date | H33: =IF(G33="OK","YES","no") -> no | I33: =COUNTIF('Roll Schedule'!$A$47:$A$790,A33)>0 -> TRUE | J33: matches live page 29 Sep 2026 | K33: https://seaofindia.com/seaquotes/11740-2/
A34: 45246 | B34: 16th November 23 | C34: 2023-11-16T17:31:27 | D34: Rs./ MT NQ | F34: A_title | G34: NQ (not quoted by SEA) | H34: =IF(G34="OK","YES","no") -> no | I34: =COUNTIF('Roll Schedule'!$A$47:$A$790,A34)>0 -> TRUE | J34: matches live page 29 Sep 2026 | K34: https://seaofindia.com/seaquotes/16th-november-23/
A35: 45247 | B35: 17th November 23 | C35: 2023-11-17T17:47:56 | D35: Rs./ MT NQ | F35: A_title | G35: NQ (not quoted by SEA) | H35: =IF(G35="OK","YES","no") -> no | I35: =COUNTIF('Roll Schedule'!$A$47:$A$790,A35)>0 -> TRUE | J35: matches live page 29 Sep 2026 | K35: https://seaofindia.com/seaquotes/17th-november-23/
A36: 45247 | B36: 17th November 23 | C36: 2023-11-17T17:49:15 | D36: Rs./ MT NQ | F36: A_title | G36: EXCLUDED: duplicate post (identical values, earlier post kept) | H36: =IF(G36="OK","YES","no") -> no | I36: =COUNTIF('Roll Schedule'!$A$47:$A$790,A36)>0 -> TRUE | J36: matches live page 29 Sep 2026 | K36: https://seaofindia.com/seaquotes/17th-november-23-2/
A37: 45250 | B37: 20th November 23 | C37: 2023-11-20T17:54:16 | D37: Rs./ MT 7950 | E37: 7950 | F37: A_title | G37: OK | H37: =IF(G37="OK","YES","no") -> YES | I37: =COUNTIF('Roll Schedule'!$A$47:$A$790,A37)>0 -> TRUE | J37: matches live page 29 Sep 2026 | K37: https://seaofindia.com/seaquotes/20th-november-23/
A38: 45251 | B38: 21st November 23 | C38: 2023-11-21T17:25:15 | D38: Rs./ MT 8400 | E38: 8400 | F38: A_title | G38: OK | H38: =IF(G38="OK","YES","no") -> YES | I38: =COUNTIF('Roll Schedule'!$A$47:$A$790,A38)>0 -> TRUE | J38: matches live page 29 Sep 2026 | K38: https://seaofindia.com/seaquotes/21st-november-23/
A39: 45252 | B39: 22nd November 23 | C39: 2023-11-22T17:26:44 | D39: Rs./ MT 8700 | E39: 8700 | F39: A_title | G39: OK | H39: =IF(G39="OK","YES","no") -> YES | I39: =COUNTIF('Roll Schedule'!$A$47:$A$790,A39)>0 -> TRUE | J39: matches live page 29 Sep 2026 | K39: https://seaofindia.com/seaquotes/22nd-november-23/
A40: 45253 | B40: 23rd November 23 | C40: 2023-11-23T17:33:47 | D40: Rs./ MT 8950 | E40: 8950 | F40: A_title | G40: OK | H40: =IF(G40="OK","YES","no") -> YES | I40: =COUNTIF('Roll Schedule'!$A$47:$A$790,A40)>0 -> TRUE | J40: matches live page 29 Sep 2026 | K40: https://seaofindia.com/seaquotes/23rd-november-23/
A41: 45254 | B41: 24thNovember 23 | C41: 2023-11-24T17:54:15 | D41: Rs./ MT 8900 | E41: 8900 | F41: A_title | G41: OK | H41: =IF(G41="OK","YES","no") -> YES | I41: =COUNTIF('Roll Schedule'!$A$47:$A$790,A41)>0 -> TRUE | J41: matches live page 29 Sep 2026 | K41: https://seaofindia.com/seaquotes/24thnovember-23/
A42: 45258 | B42: 28th November 23 | C42: 2023-11-28T17:00:57 | D42: Rs./ MT 9050 | E42: 9050 | F42: A_title | G42: OK | H42: =IF(G42="OK","YES","no") -> YES | I42: =COUNTIF('Roll Schedule'!$A$47:$A$790,A42)>0 -> TRUE | J42: matches live page 29 Sep 2026 | K42: https://seaofindia.com/seaquotes/28th-november-23/
A43: 45259 | B43: 29th Novembr 2023 | C43: 2023-11-29T17:15:46 | D43: Rs./ MT 9000 | E43: 9000 | F43: A_title | G43: OK | H43: =IF(G43="OK","YES","no") -> YES | I43: =COUNTIF('Roll Schedule'!$A$47:$A$790,A43)>0 -> TRUE | J43: matches live page 29 Sep 2026 | K43: https://seaofindia.com/seaquotes/29th-novembr-2023/
A44: 45260 | B44: 30th Nov 23 | C44: 2023-11-30T17:28:18 | D44: Rs./ MT 8900 | E44: 8900 | F44: A_title | G44: OK | H44: =IF(G44="OK","YES","no") -> YES | I44: =COUNTIF('Roll Schedule'!$A$47:$A$790,A44)>0 -> TRUE | J44: matches live page 29 Sep 2026 | K44: https://seaofindia.com/seaquotes/30th-nov-23/
A45: 45261 | B45: 1st Dec 23 | C45: 2023-12-01T17:54:57 | D45: Rs./ MT 8850 | E45: 8850 | F45: A_title | G45: OK | H45: =IF(G45="OK","YES","no") -> YES | I45: =COUNTIF('Roll Schedule'!$A$47:$A$790,A45)>0 -> TRUE | J45: matches live page 29 Sep 2026 | K45: https://seaofindia.com/seaquotes/1st-dec-23/
A46: 45264 | B46: 4th Dec 23 | C46: 2023-12-04T17:40:01 | D46: Rs./ MT 8750 | E46: 8750 | F46: A_title | G46: OK | H46: =IF(G46="OK","YES","no") -> YES | I46: =COUNTIF('Roll Schedule'!$A$47:$A$790,A46)>0 -> TRUE | J46: matches live page 29 Sep 2026 | K46: https://seaofindia.com/seaquotes/4th-dec-23-2/
A47: 45266 | B47: 6th Dec 23 | C47: 2023-12-06T17:35:23 | D47: Rs./ MT 8850 | E47: 8850 | F47: A_title | G47: OK | H47: =IF(G47="OK","YES","no") -> YES | I47: =COUNTIF('Roll Schedule'!$A$47:$A$790,A47)>0 -> TRUE | J47: matches live page 29 Sep 2026 | K47: https://seaofindia.com/seaquotes/6th-dec-23/
A48: 45267 | B48: 7th Dec 23 | C48: 2023-12-07T17:42:02 | D48: Rs./ MT 8650 | E48: 8650 | F48: A_title | G48: OK | H48: =IF(G48="OK","YES","no") -> YES | I48: =COUNTIF('Roll Schedule'!$A$47:$A$790,A48)>0 -> TRUE | J48: matches live page 29 Sep 2026 | K48: https://seaofindia.com/seaquotes/7th-dec-23/
... A124: 45411 | B124: 29th Jan 24 | C124: 2024-04-29T17:24:33 | D124: Rs./MT 6050 | E124: 6050 | F124: B_pub_title_implausible | G124: EXCLUDED: uncertain publication date | H124: =IF(G124="OK","YES","no") -> no | I124: =COUNTIF('Roll Schedule'!$A$47:$A$790,A124)>0 -> TRUE | J124: matches live page 29 Sep 2026 | K124: https://seaofindia.com/seaquotes/29th-jan-24-2/
A125: 45412 | B125: 30th April 24 | C125: 2024-04-30T16:55:28 | D125: (row absent) | F125: A_title | G125: NQ (not quoted by SEA) | H125: =IF(G125="OK","YES","no") -> no | I125: =COUNTIF('Roll Schedule'!$A$47:$A$790,A125)>0 -> TRUE | J125: matches live page 29 Sep 2026 | K125: https://seaofindia.com/seaquotes/30th-april-24/
A126: 45414 | B126: 2nd May 24 | C126: 2024-05-02T17:03:58 | D126: (row absent) | F126: A_title | G126: NQ (not quoted by SEA) | H126: =IF(G126="OK","YES","no") -> no | I126: =COUNTIF('Roll Schedule'!$A$47:$A$790,A126)>0 -> TRUE | J126: matches live page 29 Sep 2026 | K126: https://seaofindia.com/seaquotes/2nd-may-24/
A127: 45415 | B127: 3rd May 24 | C127: 2024-05-03T18:08:31 | D127: (row absent) | F127: A_title | G127: NQ (not quoted by SEA) | H127: =IF(G127="OK","YES","no") -> no | I127: =COUNTIF('Roll Schedule'!$A$47:$A$790,A127)>0 -> TRUE | J127: matches live page 29 Sep 2026 | K127: https://seaofindia.com/seaquotes/3rd-may-24/
A128: 45418 | B128: 6th May 24 | C128: 2024-05-06T17:11:21 | D128: (row absent) | F128: A_title | G128: NQ (not quoted by SEA) | H128: =IF(G128="OK","YES","no") -> no | I128: =COUNTIF('Roll Schedule'!$A$47:$A$790,A128)>0 -> TRUE | J128: matches live page 29 Sep 2026 | K128: https://seaofindia.com/seaquotes/6th-may-24/
A129: 45420 | B129: 8th May 24 | C129: 2024-05-08T17:23:21 | D129: (row absent) | F129: A_title | G129: NQ (not quoted by SEA) | H129: =IF(G129="OK","YES","no") -> no | I129: =COUNTIF('Roll Schedule'!$A$47:$A$790,A129)>0 -> TRUE | J129: matches live page 29 Sep 2026 | K129: https://seaofindia.com/seaquotes/8th-may-24/
A130: 45421 | B130: 9th May 24 | C130: 2024-05-09T17:46:24 | D130: (row absent) | F130: A_title | G130: NQ (not quoted by SEA) | H130: =IF(G130="OK","YES","no") -> no | I130: =COUNTIF('Roll Schedule'!$A$47:$A$790,A130)>0 -> TRUE | J130: matches live page 29 Sep 2026 | K130: https://seaofindia.com/seaquotes/9th-may-24/
A131: 45422 | B131: 13th May 24 | C131: 2024-05-10T17:57:44 | D131: (row absent) | F131: B_pub_title_implausible | G131: EXCLUDED: uncertain publication date | H131: =IF(G131="OK","YES","no") -> no | I131: =COUNTIF('Roll Schedule'!$A$47:$A$790,A131)>0 -> TRUE | J131: matches live page 29 Sep 2026 | K131: https://seaofindia.com/seaquotes/10th-may-24/
A132: 45425 | B132: 13th May 24 | C132: 2024-05-13T17:22:23 | D132: (row absent) | F132: A_title | G132: NQ (not quoted by SEA) | H132: =IF(G132="OK","YES","no") -> no | I132: =COUNTIF('Roll Schedule'!$A$47:$A$790,A132)>0 -> TRUE | J132: matches live page 29 Sep 2026 | K132: https://seaofindia.com/seaquotes/13th-may-24/
A133: 45426 | B133: 14th May 24 | C133: 2024-05-14T17:57:09 | D133: (row absent) | F133: A_title | G133: NQ (not quoted by SEA) | H133: =IF(G133="OK","YES","no") -> no | I133: =COUNTIF('Roll Schedule'!$A$47:$A$790,A133)>0 -> TRUE | J133: matches live page 29 Sep 2026 | K133: https://seaofindia.com/seaquotes/14th-may-24/
A134: 45427 | B134: 15th May 24 | C134: 2024-05-15T17:21:00 | D134: (row absent) | F134: A_title | G134: NQ (not quoted by SEA) | H134: =IF(G134="OK","YES","no") -> no | I134: =COUNTIF('Roll Schedule'!$A$47:$A$790,A134)>0 -> TRUE | J134: matches live page 29 Sep 2026 | K134: https://seaofindia.com/seaquotes/15th-may-24/
A135: 45428 | B135: 16th May 24 | C135: 2024-05-16T17:15:37 | D135: (row absent) | F135: A_title | G135: NQ (not quoted by SEA) | H135: =IF(G135="OK","YES","no") -> no | I135: =COUNTIF('Roll Schedule'!$A$47:$A$790,A135)>0 -> TRUE | J135: matches live page 29 Sep 2026 | K135: https://seaofindia.com/seaquotes/16th-may-24/
A136: 45463 | B136: 20th June 24 | C136: 2024-06-20T05:00:34 | D136: (row absent) | F136: A_title | G136: EXCLUDED: uncertain publication date | H136: =IF(G136="OK","YES","no") -> no | I136: =COUNTIF('Roll Schedule'!$A$47:$A$790,A136)>0 -> TRUE | J136: matches live page 29 Sep 2026 | K136: https://seaofindia.com/seaquotes/21st-may-24/
... A197: 45560 | B197: 25th Sept. 24 | C197: 2024-09-25T17:41:11 | D197: (row absent) | F197: A_title | G197: NQ (not quoted by SEA) | H197: =IF(G197="OK","YES","no") -> no | I197: =COUNTIF('Roll Schedule'!$A$47:$A$790,A197)>0 -> TRUE | J197: matches live page 29 Sep 2026 | K197: https://seaofindia.com/seaquotes/25th-sept-24/
A198: 45562 | C198: 2024-09-27T18:07:34 | D198: (row absent) | F198: D_pub_no_usable_title | G198: EXCLUDED: uncertain publication date | H198: =IF(G198="OK","YES","no") -> no | I198: =COUNTIF('Roll Schedule'!$A$47:$A$790,A198)>0 -> TRUE | J198: matches live page 29 Sep 2026 | K198: https://seaofindia.com/seaquotes/13016-2/
A199: 45566 | B199: 4th Nov2024 | C199: 2024-10-01T18:05:12 | D199: (row absent) | F199: B_pub_title_implausible | G199: NQ (not quoted by SEA) | H199: =IF(G199="OK","YES","no") -> no | I199: =COUNTIF('Roll Schedule'!$A$47:$A$790,A199)>0 -> TRUE | J199: matches live page 29 Sep 2026 | K199: https://seaofindia.com/seaquotes/1sr-oct-2024/
A200: 45601 | B200: 2nd December | C200: 2024-11-05T17:51:20 | D200: (row absent) | F200: D_pub_no_usable_title | G200: EXCLUDED: uncertain publication date | H200: =IF(G200="OK","YES","no") -> no | I200: =COUNTIF('Roll Schedule'!$A$47:$A$790,A200)>0 -> TRUE | J200: matches live page 29 Sep 2026 | K200: https://seaofindia.com/seaquotes/4th-november/
A201: 45629 | B201: 3rd December 2024 | C201: 2024-12-03T09:46:51 | D201: (row absent) | F201: A_title | G201: NQ (not quoted by SEA) | H201: =IF(G201="OK","YES","no") -> no | I201: =COUNTIF('Roll Schedule'!$A$47:$A$790,A201)>0 -> TRUE | J201: matches live page 29 Sep 2026 | K201: https://seaofindia.com/seaquotes/december-2024/
A202: 45629 | B202: 3rd Dec 2024 | C202: 2024-12-04T10:26:52 | D202: Rs./MT 6950 | E202: 6950 | F202: A_title | G202: EXCLUDED: duplicate post (identical values, earlier post kept) | H202: =IF(G202="OK","YES","no") -> no | I202: =COUNTIF('Roll Schedule'!$A$47:$A$790,A202)>0 -> TRUE | J202: matches live page 29 Sep 2026 | K202: https://seaofindia.com/seaquotes/3rd-dec-2024/
A203: 45630 | B203: 4th Dec 2024 | C203: 2024-12-04T17:26:22 | D203: Rs./MT 6800 | E203: 6800 | F203: A_title | G203: OK | H203: =IF(G203="OK","YES","no") -> YES | I203: =COUNTIF('Roll Schedule'!$A$47:$A$790,A203)>0 -> TRUE | J203: matches live page 29 Sep 2026 | K203: https://seaofindia.com/seaquotes/4th-dec-2024/
A204: 45631 | B204: 5th Dec 2024 | C204: 2024-12-05T17:19:13 | D204: Rs./MT 6750 | E204: 6750 | F204: A_title | G204: OK | H204: =IF(G204="OK","YES","no") -> YES | I204: =COUNTIF('Roll Schedule'!$A$47:$A$790,A204)>0 -> TRUE | J204: matches live page 29 Sep 2026 | K204: https://seaofindia.com/seaquotes/5th-dec-2024/
A205: 45632 | B205: 6th Dec 24 | C205: 2024-12-06T17:38:55 | D205: Rs./MT 6650 | E205: 6650 | F205: A_title | G205: OK | H205: =IF(G205="OK","YES","no") -> YES | I205: =COUNTIF('Roll Schedule'!$A$47:$A$790,A205)>0 -> TRUE | J205: matches live page 29 Sep 2026 | K205: https://seaofindia.com/seaquotes/6th-dec-24/
A206: 45635 | B206: 9th Dec 2024 | C206: 2024-12-09T17:49:40 | D206: Rs./MT 6650 | E206: 6650 | F206: A_title | G206: OK | H206: =IF(G206="OK","YES","no") -> YES | I206: =COUNTIF('Roll Schedule'!$A$47:$A$790,A206)>0 -> TRUE | J206: matches live page 29 Sep 2026 | K206: https://seaofindia.com/seaquotes/9th-dec-24/
A207: 45636 | B207: 10th Dec 2024 | C207: 2024-12-10T17:26:35 | D207: Rs./MT 6650 | E207: 6650 | F207: A_title | G207: OK | H207: =IF(G207="OK","YES","no") -> YES | I207: =COUNTIF('Roll Schedule'!$A$47:$A$790,A207)>0 -> TRUE | J207: matches live page 29 Sep 2026 | K207: https://seaofindia.com/seaquotes/10-dec-2024/
A208: 45637 | B208: 11th Dec 2024 | C208: 2024-12-11T17:48:00 | D208: Rs./MT 6750 | E208: 6750 | F208: A_title | G208: OK | H208: =IF(G208="OK","YES","no") -> YES | I208: =COUNTIF('Roll Schedule'!$A$47:$A$790,A208)>0 -> TRUE | J208: matches live page 29 Sep 2026 | K208: https://seaofindia.com/seaquotes/11-dec-2024/
A209: 45638 | B209: 12th Dec 2024 | C209: 2024-12-12T17:24:00 | D209: Rs./MT 6700 | E209: 6700 | F209: A_title | G209: OK | H209: =IF(G209="OK","YES","no") -> YES | I209: =COUNTIF('Roll Schedule'!$A$47:$A$790,A209)>0 -> TRUE | J209: matches live page 29 Sep 2026 | K209: https://seaofindia.com/seaquotes/12th-dec-2024/
A210: 45639 | B210: 13th Dec 2024 | C210: 2024-12-13T17:53:39 | D210: Rs./MT 6700 | E210: 6700 | F210: A_title | G210: OK | H210: =IF(G210="OK","YES","no") -> YES | I210: =COUNTIF('Roll Schedule'!$A$47:$A$790,A210)>0 -> TRUE | J210: matches live page 29 Sep 2026 | K210: https://seaofindia.com/seaquotes/13th-dec-2024/
A211: 45642 | B211: 16th Dec 2024 | C211: 2024-12-16T17:50:11 | D211: Rs./MT 6650 | E211: 6650 | F211: A_title | G211: OK | H211: =IF(G211="OK","YES","no") -> YES | I211: =COUNTIF('Roll Schedule'!$A$47:$A$790,A211)>0 -> TRUE | J211: matches live page 29 Sep 2026 | K211: https://seaofindia.com/seaquotes/16t-dec-2024/
A212: 45643 | B212: 17th Dec 2024 | C212: 2024-12-17T17:34:02 | D212: Rs./MT 6600 | E212: 6600 | F212: A_title | G212: OK | H212: =IF(G212="OK","YES","no") -> YES | I212: =COUNTIF('Roll Schedule'!$A$47:$A$790,A212)>0 -> TRUE | J212: matches live page 29 Sep 2026 | K212: https://seaofindia.com/seaquotes/17th-dec-2024/
A213: 45644 | B213: 18th Dec 2024 | C213: 2024-12-18T17:40:32 | D213: Rs./MT 6600 | E213: 6600 | F213: A_title | G213: OK | H213: =IF(G213="OK","YES","no") -> YES | I213: =COUNTIF('Roll Schedule'!$A$47:$A$790,A213)>0 -> TRUE | J213: matches live page 29 Sep 2026 | K213: https://seaofindia.com/seaquotes/18th-dec-2024/
... A231: 45670 | B231: 13th Jan 2025 | C231: 2025-01-13T17:32:21 | D231: Rs./MT 6650 | E231: 6650 | F231: A_title | G231: OK | H231: =IF(G231="OK","YES","no") -> YES | I231: =COUNTIF('Roll Schedule'!$A$47:$A$790,A231)>0 -> TRUE | J231: matches live page 29 Sep 2026 | K231: https://seaofindia.com/seaquotes/13th-jan-2025/
A232: 45671 | B232: 14th Jan 2025 | C232: 2025-01-14T17:14:08 | D232: Rs./MT NQ | F232: A_title | G232: NQ (not quoted by SEA) | H232: =IF(G232="OK","YES","no") -> no | I232: =COUNTIF('Roll Schedule'!$A$47:$A$790,A232)>0 -> TRUE | J232: matches live page 29 Sep 2026 | K232: https://seaofindia.com/seaquotes/14th-jan-2025/
A233: 45672 | B233: 15th Jan 2025 | C233: 2025-01-15T17:40:17 | D233: Rs./MT 6800 | E233: 6800 | F233: A_title | G233: OK | H233: =IF(G233="OK","YES","no") -> YES | I233: =COUNTIF('Roll Schedule'!$A$47:$A$790,A233)>0 -> TRUE | J233: matches live page 29 Sep 2026 | K233: https://seaofindia.com/seaquotes/15th-jan-2025/
A234: 45673 | B234: 16th Jan 2025 | C234: 2025-01-16T17:50:16 | D234: Rs./MT 6750 | E234: 6750 | F234: A_title | G234: OK | H234: =IF(G234="OK","YES","no") -> YES | I234: =COUNTIF('Roll Schedule'!$A$47:$A$790,A234)>0 -> TRUE | J234: matches live page 29 Sep 2026 | K234: https://seaofindia.com/seaquotes/16th-jan-2025/
A235: 45674 | B235: 17th Jan 2025 | C235: 2025-01-17T17:29:01 | D235: Rs./MT 6750 | E235: 6750 | F235: A_title | G235: OK | H235: =IF(G235="OK","YES","no") -> YES | I235: =COUNTIF('Roll Schedule'!$A$47:$A$790,A235)>0 -> TRUE | J235: matches live page 29 Sep 2026 | K235: https://seaofindia.com/seaquotes/17th-jan-2025/
A236: 45677 | B236: 20th Jan 2025 | C236: 2025-01-20T17:48:42 | D236: Rs./MT 6850 | E236: 6850 | F236: A_title | G236: OK | H236: =IF(G236="OK","YES","no") -> YES | I236: =COUNTIF('Roll Schedule'!$A$47:$A$790,A236)>0 -> TRUE | J236: matches live page 29 Sep 2026 | K236: https://seaofindia.com/seaquotes/20th-jan-2025/
A237: 45678 | B237: 21st Jan 2025 | C237: 2025-01-21T17:36:48 | D237: Rs./MT 6900 | E237: 6900 | F237: A_title | G237: OK | H237: =IF(G237="OK","YES","no") -> YES | I237: =COUNTIF('Roll Schedule'!$A$47:$A$790,A237)>0 -> TRUE | J237: matches live page 29 Sep 2026 | K237: https://seaofindia.com/seaquotes/21st-jan-2025/
A238: 45679 | B238: 22nd Jan 2025 | C238: 2025-01-22T17:30:18 | D238: Rs./MT 7000 | E238: 7000 | F238: A_title | G238: OK | H238: =IF(G238="OK","YES","no") -> YES | I238: =COUNTIF('Roll Schedule'!$A$47:$A$790,A238)>0 -> TRUE | J238: matches live page 29 Sep 2026 | K238: https://seaofindia.com/seaquotes/22nd-jan-2025/
A239: 45680 | B239: 23rd Jan 2025 | C239: 2025-01-23T17:47:41 | D239: Rs./MT 7050 | E239: 7050 | F239: A_title | G239: OK | H239: =IF(G239="OK","YES","no") -> YES | I239: =COUNTIF('Roll Schedule'!$A$47:$A$790,A239)>0 -> TRUE | J239: matches live page 29 Sep 2026 | K239: https://seaofindia.com/seaquotes/23rd-jan-2025/
A240: 45681 | B240: 24th Jan 2025 | C240: 2025-01-24T17:48:25 | D240: Rs./MT 7050 | E240: 7050 | F240: A_title | G240: OK | H240: =IF(G240="OK","YES","no") -> YES | I240: =COUNTIF('Roll Schedule'!$A$47:$A$790,A240)>0 -> TRUE | J240: matches live page 29 Sep 2026 | K240: https://seaofindia.com/seaquotes/24th-jan-2025/
A241: 45684 | B241: 27th Jan 2025 | C241: 2025-01-27T17:38:53 | D241: Rs./MT 7100 | E241: 7100 | F241: A_title | G241: OK | H241: =IF(G241="OK","YES","no") -> YES | I241: =COUNTIF('Roll Schedule'!$A$47:$A$790,A241)>0 -> TRUE | J241: matches live page 29 Sep 2026 | K241: https://seaofindia.com/seaquotes/27th-jan-2025/
A242: 45685 | B242: 28th Jan 2025 | C242: 2025-01-28T17:03:50 | D242: Rs./MT 7250 | E242: 7250 | F242: A_title | G242: OK | H242: =IF(G242="OK","YES","no") -> YES | I242: =COUNTIF('Roll Schedule'!$A$47:$A$790,A242)>0 -> TRUE | J242: matches live page 29 Sep 2026 | K242: https://seaofindia.com/seaquotes/28th-jan-2025/
A243: 45686 | B243: 29th Jan 2025 | C243: 2025-01-29T17:43:36 | D243: Rs./MT 7150 | E243: 7150 | F243: A_title | G243: OK | H243: =IF(G243="OK","YES","no") -> YES | I243: =COUNTIF('Roll Schedule'!$A$47:$A$790,A243)>0 -> TRUE | J243: matches live page 29 Sep 2026 | K243: https://seaofindia.com/seaquotes/29th-jan-2025/
A244: 45687 | B244: 30th Jan 2025 | C244: 2025-01-30T17:26:54 | D244: Rs./MT 7300 | E244: 7300 | F244: A_title | G244: OK | H244: =IF(G244="OK","YES","no") -> YES | I244: =COUNTIF('Roll Schedule'!$A$47:$A$790,A244)>0 -> TRUE | J244: matches live page 29 Sep 2026 | K244: https://seaofindia.com/seaquotes/30th-jan-2025/
... A288: 45755 | B288: 8th Apr 25 | C288: 2025-04-08T17:58:46 | D288: Rs./MT 6500 | E288: 6500 | F288: A_title | G288: OK | H288: =IF(G288="OK","YES","no") -> YES | I288: =COUNTIF('Roll Schedule'!$A$47:$A$790,A288)>0 -> TRUE | J288: matches live page 29 Sep 2026 | K288: https://seaofindia.com/seaquotes/8th-apr-25/
A289: 45756 | B289: 10th Apr 25 | C289: 2025-04-09T17:44:28 | D289: Rs./MT NQ | F289: B_pub_title_implausible | G289: EXCLUDED: uncertain publication date | H289: =IF(G289="OK","YES","no") -> no | I289: =COUNTIF('Roll Schedule'!$A$47:$A$790,A289)>0 -> TRUE | J289: matches live page 29 Sep 2026 | K289: https://seaofindia.com/seaquotes/9th-apr-25/
A290: 45756 | B290: 9th Apr 25 | C290: 2025-04-10T17:37:46 | D290: Rs./MT 6500 | E290: 6500 | F290: A_title | G290: EXCLUDED: duplicate post (identical values, earlier post kept) | H290: =IF(G290="OK","YES","no") -> no | I290: =COUNTIF('Roll Schedule'!$A$47:$A$790,A290)>0 -> TRUE | J290: matches live page 29 Sep 2026 | K290: https://seaofindia.com/seaquotes/10th-apr-25/
A291: 45758 | B291: 11th Apr 25 | C291: 2025-04-11T17:55:22 | D291: Rs./MT 6850 | E291: 6850 | F291: A_title | G291: OK | H291: =IF(G291="OK","YES","no") -> YES | I291: =COUNTIF('Roll Schedule'!$A$47:$A$790,A291)>0 -> TRUE | J291: matches live page 29 Sep 2026 | K291: https://seaofindia.com/seaquotes/11th-apr-25/
A292: 45761 | B292: 14th Apr 25 | C292: 2025-04-23T17:38:50 | D292: Rs./MT 6600 | E292: 6600 | F292: A_title | G292: OK | H292: =IF(G292="OK","YES","no") -> YES | I292: =COUNTIF('Roll Schedule'!$A$47:$A$790,A292)>0 -> FALSE | J292: matches live page 29 Sep 2026 | K292: https://seaofindia.com/seaquotes/14th-apr-25/
A293: 45762 | B293: 15th Apr 25 | C293: 2025-04-23T17:45:06 | D293: Rs./MT 6450 | E293: 6450 | F293: A_title | G293: OK | H293: =IF(G293="OK","YES","no") -> YES | I293: =COUNTIF('Roll Schedule'!$A$47:$A$790,A293)>0 -> TRUE | J293: matches live page 29 Sep 2026 | K293: https://seaofindia.com/seaquotes/15th-apr-25/
A294: 45763 | B294: 16th Apr 25 | C294: 2025-04-16T17:44:05 | D294: Rs./MT 6500 | E294: 6500 | F294: A_title | G294: OK | H294: =IF(G294="OK","YES","no") -> YES | I294: =COUNTIF('Roll Schedule'!$A$47:$A$790,A294)>0 -> TRUE | J294: matches live page 29 Sep 2026 | K294: https://seaofindia.com/seaquotes/16th-apr-25/
A295: 45764 | B295: 17th Apr 25 | C295: 2025-04-17T17:48:15 | D295: Rs./MT 6600 | E295: 6600 | F295: A_title | G295: OK | H295: =IF(G295="OK","YES","no") -> YES | I295: =COUNTIF('Roll Schedule'!$A$47:$A$790,A295)>0 -> TRUE | J295: matches live page 29 Sep 2026 | K295: https://seaofindia.com/seaquotes/17th-apr-25/
A296: 45765 | B296: 18th Apr 25 | C296: 2025-04-21T10:13:24 | D296: Rs./MT 6600 | E296: 6600 | F296: A_title | G296: OK | H296: =IF(G296="OK","YES","no") -> YES | I296: =COUNTIF('Roll Schedule'!$A$47:$A$790,A296)>0 -> FALSE | J296: matches live page 29 Sep 2026 | K296: https://seaofindia.com/seaquotes/18th-apr-25/
A297: 45768 | B297: 21st Apr 25 | C297: 2025-04-21T17:48:15 | D297: Rs./MT 6550 | E297: 6550 | F297: A_title | G297: OK | H297: =IF(G297="OK","YES","no") -> YES | I297: =COUNTIF('Roll Schedule'!$A$47:$A$790,A297)>0 -> TRUE | J297: matches live page 29 Sep 2026 | K297: https://seaofindia.com/seaquotes/21st-apr-25/
A298: 45769 | B298: 22nd Apr 25 | C298: 2025-04-22T17:49:05 | D298: Rs./MT 6400 | E298: 6400 | F298: A_title | G298: OK | H298: =IF(G298="OK","YES","no") -> YES | I298: =COUNTIF('Roll Schedule'!$A$47:$A$790,A298)>0 -> TRUE | J298: matches live page 29 Sep 2026 | K298: https://seaofindia.com/seaquotes/22nd-apr-25/
A299: 45770 | B299: 23rd Apr 25 | C299: 2025-04-23T18:00:12 | D299: Rs./MT 6450 | E299: 6450 | F299: A_title | G299: OK | H299: =IF(G299="OK","YES","no") -> YES | I299: =COUNTIF('Roll Schedule'!$A$47:$A$790,A299)>0 -> TRUE | J299: matches live page 29 Sep 2026 | K299: https://seaofindia.com/seaquotes/23rd-apr-25/
A300: 45771 | B300: 24th Apr 25 | C300: 2025-04-24T17:29:36 | D300: Rs./MT 6450 | E300: 6450 | F300: A_title | G300: OK | H300: =IF(G300="OK","YES","no") -> YES | I300: =COUNTIF('Roll Schedule'!$A$47:$A$790,A300)>0 -> TRUE | J300: matches live page 29 Sep 2026 | K300: https://seaofindia.com/seaquotes/24th-apr-25/
A301: 45772 | B301: 25th Apr 25 | C301: 2025-04-25T17:32:46 | D301: Rs./MT 6500 | E301: 6500 | F301: A_title | G301: OK | H301: =IF(G301="OK","YES","no") -> YES | I301: =COUNTIF('Roll Schedule'!$A$47:$A$790,A301)>0 -> TRUE | J301: matches live page 29 Sep 2026 | K301: https://seaofindia.com/seaquotes/25th-apr-25/
... A418: 45947 | B418: 17th Oct 25 | C418: 2025-10-17T17:59:52 | D418: Rs./MT 8550 | E418: 8550 | F418: A_title | G418: OK | H418: =IF(G418="OK","YES","no") -> YES | I418: =COUNTIF('Roll Schedule'!$A$47:$A$790,A418)>0 -> TRUE | J418: matches live page 29 Sep 2026 | K418: https://seaofindia.com/seaquotes/17th-oct-25/
A419: 45950 | B419: 20th Oct 25 | C419: 2025-10-20T17:38:19 | D419: Rs./MT NQ | F419: A_title | G419: NQ (not quoted by SEA) | H419: =IF(G419="OK","YES","no") -> no | I419: =COUNTIF('Roll Schedule'!$A$47:$A$790,A419)>0 -> TRUE | J419: matches live page 29 Sep 2026 | K419: https://seaofindia.com/seaquotes/20th-oct-25/
A420: 45953 | B420: 23rd Oct 25 | C420: 2025-10-24T10:14:38 | D420: Rs./MT NQ | F420: A_title | G420: NQ (not quoted by SEA) | H420: =IF(G420="OK","YES","no") -> no | I420: =COUNTIF('Roll Schedule'!$A$47:$A$790,A420)>0 -> TRUE | J420: matches live page 29 Sep 2026 | K420: https://seaofindia.com/seaquotes/23rd-oct-25/
A421: 45954 | B421: 24th Oct 25 | C421: 2025-10-27T10:39:39 | D421: Rs./MT NQ | F421: A_title | G421: NQ (not quoted by SEA) | H421: =IF(G421="OK","YES","no") -> no | I421: =COUNTIF('Roll Schedule'!$A$47:$A$790,A421)>0 -> TRUE | J421: matches live page 29 Sep 2026 | K421: https://seaofindia.com/seaquotes/24th-oct-25/
A422: 45957 | B422: 27th Oct 25 | C422: 2025-10-27T17:46:36 | D422: Rs./MT 8500 | E422: 8500 | F422: A_title | G422: OK | H422: =IF(G422="OK","YES","no") -> YES | I422: =COUNTIF('Roll Schedule'!$A$47:$A$790,A422)>0 -> TRUE | J422: matches live page 29 Sep 2026 | K422: https://seaofindia.com/seaquotes/27th-oct-25/
A423: 45958 | B423: 28th Oct 25 | C423: 2025-10-29T10:30:12 | D423: Rs./MT 8450 | E423: 8450 | F423: A_title | G423: OK | H423: =IF(G423="OK","YES","no") -> YES | I423: =COUNTIF('Roll Schedule'!$A$47:$A$790,A423)>0 -> TRUE | J423: matches live page 29 Sep 2026 | K423: https://seaofindia.com/seaquotes/28th-oct-25/
A424: 45959 | B424: 29th Oct 25 | C424: 2025-10-29T17:48:18 | D424: Rs./MT 8450 | E424: 8450 | F424: A_title | G424: OK | H424: =IF(G424="OK","YES","no") -> YES | I424: =COUNTIF('Roll Schedule'!$A$47:$A$790,A424)>0 -> TRUE | J424: matches live page 29 Sep 2026 | K424: https://seaofindia.com/seaquotes/29th-oct-25/
...

Sheet Futures Data
A1: Futures Data: NCDEX castor seed futures (symbol CASTOR), every contract on every trading day. Source: NCDEX daily final bhavcopy.
A2: File FO_DDMMYY_FINAL.csv in each daily ZIP from https://www.ncdex.com/markets/bhavcopy, rows with Instrument Type FUTCOM. Close in Rs per quintal; volume and open interest in MT. Values unchanged.
A4: Trade date | B4: Contract expiry | C4: Close (Rs/qtl) | D4: Volume (MT) | E4: Open interest (MT) | F4: Price unit | G4: Delivery centre | H4: Source file
A5: 45194 | B5: 45219 | C5: 6176 | D5: 6820 | E5: 27755 | F5: RS/QUINTAL | G5: DEESA | H5: ncdex_bhavcopy_20230925.zip::FO_250923_FINAL.csv
A6: 45194 | B6: 45250 | C6: 6234 | D6: 3660 | E6: 10270 | F6: RS/QUINTAL | G6: DEESA | H6: ncdex_bhavcopy_20230925.zip::FO_250923_FINAL.csv
A7: 45194 | B7: 45280 | C7: 6292 | D7: 0 | E7: 120 | F7: RS/QUINTAL | G7: DEESA | H7: ncdex_bhavcopy_20230925.zip::FO_250923_FINAL.csv
A8: 45194 | B8: 45310 | C8: 6350 | D8: 0 | E8: 0 | F8: RS/QUINTAL | G8: DEESA | H8: ncdex_bhavcopy_20230925.zip::FO_250923_FINAL.csv
A9: 45195 | B9: 45219 | C9: 6155 | D9: 4340 | E9: 26860 | F9: RS/QUINTAL | G9: DEESA | H9: ncdex_bhavcopy_20230926.zip::FO_260923_FINAL.csv
A10: 45195 | B10: 45250 | C10: 6225 | D10: 2400 | E10: 11415 | F10: RS/QUINTAL | G10: DEESA | H10: ncdex_bhavcopy_20230926.zip::FO_260923_FINAL.csv
A11: 45195 | B11: 45280 | C11: 6295 | D11: 0 | E11: 120 | F11: RS/QUINTAL | G11: DEESA | H11: ncdex_bhavcopy_20230926.zip::FO_260923_FINAL.csv
A12: 45195 | B12: 45310 | C12: 6365 | D12: 0 | E12: 0 | F12: RS/QUINTAL | G12: DEESA | H12: ncdex_bhavcopy_20230926.zip::FO_260923_FINAL.csv
A13: 45196 | B13: 45219 | C13: 6164 | D13: 8775 | E13: 23975 | F13: RS/QUINTAL | G13: DEESA | H13: ncdex_bhavcopy_20230927.zip::FO_270923_FINAL.csv
A14: 45196 | B14: 45250 | C14: 6232 | D14: 5465 | E14: 15220 | F14: RS/QUINTAL | G14: DEESA | H14: ncdex_bhavcopy_20230927.zip::FO_270923_FINAL.csv
A15: 45196 | B15: 45280 | C15: 6300 | D15: 40 | E15: 125 | F15: RS/QUINTAL | G15: DEESA | H15: ncdex_bhavcopy_20230927.zip::FO_270923_FINAL.csv
A16: 45196 | B16: 45310 | C16: 6368 | D16: 0 | E16: 0 | F16: RS/QUINTAL | G16: DEESA | H16: ncdex_bhavcopy_20230927.zip::FO_270923_FINAL.csv
... A3471: 46293 | B3471: 46407 | C3471: 8105 | D3471: 0 | E3471: 0 | F3471: RS/QUINTAL | G3471: DEESA | H3471: ncdex_bhavcopy_20260928.zip::FO_280926_FINAL.csv

Sheet Roll Schedule
A1: Roll Schedule: which CASTOR contract is held each day, and every roll
A2: Rule: switch to the next contract at the close of day t if EITHER (a) at the close of day t-1 the next contract's open interest was larger than the held contract's (read from the published t-1 file, so acted on one day later) OR (b) only the backstop number of NCDEX trading days remain to the held contract's expiry (a calendar rule known in advance).
A3: Basis: Continuous Contracts Explained p.2 (rolling on open interest) and p.1 (avoid the delivery/notice period); NCDEX CASTOR specification (tender period = last 3 trading days). The one-day lag and the backstop are project adaptations.
A4: Backstop: trading days left at which the switch is forced | G4: 7
A5: Last trading day in the data | G5: =MAX(A47:A790) -> 46293
A7: Roll # | B7: Signal observed at close of | C7: Switch at close of | D7: Reason | E7: Old contract (expiry) | F7: New contract (expiry) | G7: Trading days left on old at switch | H7: OI old contract (MT) at signal date (backstop: switch date) | I7: OI new contract (MT), same date | J7: Old close at switch (Rs/qtl) | K7: New close at switch (Rs/qtl) | L7: Roll gap (new - old) | M7: Gap % | N7: First return on new contract
A8: 1 | B8: =IF(H52,A52,A53) -> 45202 | C8: =A53 -> 45203 | D8: =IF(H52,"OI signal: next-month OI > held OI at previous close","Calendar backstop: "&D53&" trading days left") -> OI signal: next-month OI > held OI at previous close | E8: =B53 -> 45219 | F8: =C53 -> 45250 | G8: =D53 -> 12 | H8: =IF(H52,E52,SUMIFS('Futures Data'!$E$5:$E$3471,'Futures Data'!$A$5:$A$3471,A53,'Futures Data'!$B$5:$B$3471,B53)) -> 18280 | I8: =IF(H52,G52,E53) -> 19645 | J8: =J53 -> 6135 | K8: =K53 -> 6193 | L8: =L53 -> 58 | M8: =L53/J53 -> 0.0094539527 | N8: =A54 -> 45204
A9: 2 | B9: =IF(H77,A77,A78) -> 45239 | C9: =A78 -> 45239 | D9: =IF(H77,"OI signal: next-month OI > held OI at previous close","Calendar backstop: "&D78&" trading days left") -> Calendar backstop: 7 trading days left | E9: =B78 -> 45250 | F9: =C78 -> 45280 | G9: =D78 -> 7 | H9: =IF(H77,E77,SUMIFS('Futures Data'!$E$5:$E$3471,'Futures Data'!$A$5:$A$3471,A78,'Futures Data'!$B$5:$B$3471,B78)) -> 20495 | I9: =IF(H77,G77,E78) -> 15600 | J9: =J78 -> 5953 | K9: =K78 -> 5873 | L9: =L78 -> -80 | M9: =L78/J78 -> -0.013438602 | N9: =A79 -> 45240
A10: 3 | B10: =IF(H94,A94,A95) -> 45264 | C10: =A95 -> 45265 | D10: =IF(H94,"OI signal: next-month OI > held OI at previous close","Calendar backstop: "&D95&" trading days left") -> OI signal: next-month OI > held OI at previous close | E10: =B95 -> 45280 | F10: =C95 -> 45310 | G10: =D95 -> 11 | H10: =IF(H94,E94,SUMIFS('Futures Data'!$E$5:$E$3471,'Futures Data'!$A$5:$A$3471,A95,'Futures Data'!$B$5:$B$3471,B95)) -> 10310 | I10: =IF(H94,G94,E95) -> 12010 | J10: =J95 -> 5880 | K10: =K95 -> 5925 | L10: =L95 -> 45 | M10: =L95/J95 -> 0.0076530612 | N10: =A96 -> 45266
A11: 4 | B11: =IF(H113,A113,A114) -> 45292 | C11: =A114 -> 45293 | D11: =IF(H113,"OI signal: next-month OI > held OI at previous close","Calendar backstop: "&D114&" trading days left") -> OI signal: next-month OI > held OI at previous close | E11: =B114 -> 45310 | F11: =C114 -> 45342 | G11: =D114 -> 13 | H11: =IF(H113,E113,SUMIFS('Futures Data'!$E$5:$E$3471,'Futures Data'!$A$5:$A$3471,A114,'Futures Data'!$B$5:$B$3471,B114)) -> 14005 | I11: =IF(H113,G113,E114) -> 16060 | J11: =J114 -> 5670 | K11: =K114 -> 5708 | L11: =L114 -> 38 | M11: =L114/J114 -> 0.00670194 | N11: =A115 -> 45294
A12: 5 | B12: =IF(H139,A139,A140) -> 45330 | C12: =A140 -> 45331 | D12: =IF(H139,"OI signal: next-month OI > held OI at previous close","Calendar backstop: "&D140&" trading days left") -> OI signal: next-month OI > held OI at previous close | E12: =B140 -> 45342 | F12: =C140 -> 45371 | G12: =D140 -> 7 | H12: =IF(H139,E139,SUMIFS('Futures Data'!$E$5:$E$3471,'Futures Data'!$A$5:$A$3471,A140,'Futures Data'!$B$5:$B$3471,B140)) -> 14835 | I12: =IF(H139,G139,E140) -> 15515 | J12: =J140 -> 5773 | K12: =K140 -> 5610 | L12: =L140 -> -163 | M12: =L140/J140 -> -0.028234887 | N12: =A141 -> 45334
A13: 6 | B13: =IF(H147,A147,A148) -> 45342 | C13: =A148 -> 45343 | D13: =IF(H147,"OI signal: next-month OI > held OI at previous close","Calendar backstop: "&D148&" trading days left") -> OI signal: next-month OI > held OI at previous close | E13: =B148 -> 45371 | F13: =C148 -> 45401 | G13: =D148 -> 19 | H13: =IF(H147,E147,SUMIFS('Futures Data'!$E$5:$E$3471,'Futures Data'!$A$5:$A$3471,A148,'Futures Data'!$B$5:$B$3471,B148)) -> 18545 | I13: =IF(H147,G147,E148) -> 21670 | J13: =J148 -> 5759 | K13: =K148 -> 5840 | L13: =L148 -> 81 | M13: =L148/J148 -> 0.014064942 | N13: =A149 -> 45344
A14: 7 | B14: =IF(H177,A177,A178) -> 45390 | C14: =A178 -> 45390 | D14: =IF(H177,"OI signal: next-month OI > held OI at previous close","Calendar backstop: "&D178&" trading days left") -> Calendar backstop: 7 trading days left | E14: =B178 -> 45401 | F14: =C178 -> 45432 | G14: =D178 -> 7 | H14: =IF(H177,E177,SUMIFS('Futures Data'!$E$5:$E$3471,'Futures Data'!$A$5:$A$3471,A178,'Futures Data'!$B$5:$B$3471,B178)) -> 23950 | I14: =IF(H177,G177,E178) -> 11970 | J14: =J178 -> 5931 | K14: =K178 -> 5895 | L14: =L178 -> -36 | M14: =L178/J178 -> -0.0060698027 | N14: =A179 -> 45391
A15: 8 | B15: =IF(H194,A194,A195) -> 45415 | C15: =A195 -> 45418 | D15: =IF(H194,"OI signal: next-month OI > held OI at previous close","Calendar backstop: "&D195&" trading days left") -> OI signal: next-month OI > held OI at previous close | E15: =B195 -> 45432 | F15: =C195 -> 45463 | G15: =D195 -> 9 | H15: =IF(H194,E194,SUMIFS('Futures Data'!$E$5:$E$3471,'Futures Data'!$A$5:$A$3471,A195,'Futures Data'!$B$5:$B$3471,B195)) -> 13380 | I15: =IF(H194,G194,E195) -> 15675 | J15: =J195 -> 5590 | K15: =K195 -> 5674 | L15: =L195 -> 84 | M15: =L195/J195 -> 0.015026834 | N15: =A196 -> 45419
A16: 9 | B16: =IF(H215,A215,A216) -> 45447 | C16: =A216 -> 45448 | D16: =IF(H215,"OI signal: next-month OI > held OI at previous close","Calendar backstop: "&D216&" trading days left") -> OI signal: next-month OI > held OI at previous close | E16: =B216 -> 45463 | F16: =C216 -> 45492 | G16: =D216 -> 10 | H16: =IF(H215,E215,SUMIFS('Futures Data'!$E$5:$E$3471,'Futures Data'!$A$5:$A$3471,A216,'Futures Data'!$B$5:$B$3471,B216)) -> 16785 | I16: =IF(H215,G215,E216) -> 18175 | J16: =J216 -> 5700 | K16: =K216 -> 5775 | L16: =L216 -> 75 | M16: =L216/J216 -> 0.013157895 | N16: =A217 -> 45449
A17: 10 | B17: =IF(H236,A236,A237) -> 45477 | C17: =A237 -> 45478 | D17: =IF(H236,"OI signal: next-month OI > held OI at previous close","Calendar backstop: "&D237&" trading days left") -> OI signal: next-month OI > held OI at previous close | E17: =B237 -> 45492 | F17: =C237 -> 45524 | G17: =D237 -> 9 | H17: =IF(H236,E236,SUMIFS('Futures Data'!$E$5:$E$3471,'Futures Data'!$A$5:$A$3471,A237,'Futures Data'!$B$5:$B$3471,B237)) -> 17945 | I17: =IF(H236,G236,E237) -> 20205 | J17: =J237 -> 5896 | K17: =K237 -> 5976 | L17: =L237 -> 80 | M17: =L237/J237 -> 0.013568521 | N17: =A238 -> 45481
A18: 11 | B18: =IF(H256,A256,A257) -> 45506 | C18: =A257 -> 45509 | D18: =IF(H256,"OI signal: next-month OI > held OI at previous close","Calendar backstop: "&D257&" trading days left") -> OI signal: next-month OI > held OI at previous close | E18: =B257 -> 45524 | F18: =C257 -> 45555 | G18: =D257 -> 10 | H18: =IF(H256,E256,SUMIFS('Futures Data'!$E$5:$E$3471,'Futures Data'!$A$5:$A$3471,A257,'Futures Data'!$B$5:$B$3471,B257)) -> 22955 | I18: =IF(H256,G256,E257) -> 24380 | J18: =J257 -> 6193 | K18: =K257 -> 6260 | L18: =L257 -> 67 | M18: =L257/J257 -> 0.010818666 | N18: =A258 -> 45510
A19: 12 | B19: =IF(H278,A278,A279) -> 45539 | C19: =A279 -> 45540 | D19: =IF(H278,"OI signal: next-month OI > held OI at previous close","Calendar backstop: "&D279&" trading days left") -> OI signal: next-month OI > held OI at previous close | E19: =B279 -> 45555 | F19: =C279 -> 45583 | G19: =D279 -> 11 | H19: =IF(H278,E278,SUMIFS('Futures Data'!$E$5:$E$3471,'Futures Data'!$A$5:$A$3471,A279,'Futures Data'!$B$5:$B$3471,B279)) -> 17915 | I19: =IF(H278,G278,E279) -> 23995 | J19: =J279 -> 6108 | K19: =K279 -> 6193 | L19: =L279 -> 85 | M19: =L279/J279 -> 0.013916176 | N19: =A280 -> 45541
A20: 13 | B20: =IF(H298,A298,A299) -> 45568 | C20: =A299 -> 45569 | D20: =IF(H298,"OI signal: next-month OI > held OI at previous close","Calendar backstop: "&D299&" trading days left") -> OI signal: next-month OI > held OI at previous close | E20: =B299 -> 45583 | F20: =C299 -> 45616 | G20: =D299 -> 10 | H20: =IF(H298,E298,SUMIFS('Futures Data'!$E$5:$E$3471,'Futures Data'!$A$5:$A$3471,A299,'Futures Data'!$B$5:$B$3471,B299)) -> 22525 | I20: =IF(H298,G298,E299) -> 28215 | J20: =J299 -> 6819 | K20: =K299 -> 6889 | L20: =L299 -> 70 | M20: =L299/J299 -> 0.010265435 | N20: =A300 -> 45572
A21: 14 | B21: =IF(H317,A317,A318) -> 45595 | C21: =A318 -> 45596 | D21: =IF(H317,"OI signal: next-month OI > held OI at previous close","Calendar backstop: "&D318&" trading days left") -> OI signal: next-month OI > held OI at previous close | E21: =B318 -> 45616 | F21: =C318 -> 45646 | G21: =D318 -> 12 | H21: =IF(H317,E317,SUMIFS('Futures Data'!$E$5:$E$3471,'Futures Data'!$A$5:$A$3471,A318,'Futures Data'!$B$5:$B$3471,B318)) -> 18835 | I21: =IF(H317,G317,E318) -> 20575 | J21: =J318 -> 6603 | K21: =K318 -> 6724 | L21: =L318 -> 121 | M21: =L318/J318 -> 0.018325004 | N21: =A319 -> 45597
A22: 15 | B22: =IF(H343,A343,A344) -> 45635 | C22: =A344 -> 45636 | D22: =IF(H343,"OI signal: next-month OI > held OI at previous close","Calendar backstop: "&D344&" trading days left") -> OI signal: next-month OI > held OI at previous close | E22: =B344 -> 45646 | F22: =C344 -> 45677 | G22: =D344 -> 8 | H22: =IF(H343,E343,SUMIFS('Futures Data'!$E$5:$E$3471,'Futures Data'!$A$5:$A$3471,A344,'Futures Data'!$B$5:$B$3471,B344)) -> 13170 | I22: =IF(H343,G343,E344) -> 16915 | J22: =J344 -> 6294 | K22: =K344 -> 6368 | L22: =L344 -> 74 | M22: =L344/J344 -> 0.011757229 | N22: =A345 -> 45637
A23: 16 | B23: =IF(H364,A364,A365) -> 45665 | C23: =A365 -> 45666 | D23: =IF(H364,"OI signal: next-month OI > held OI at previous close","Calendar backstop: "&D365&" trading days left") -> OI signal: next-month OI > held OI at previous close | E23: =B365 -> 45677 | F23: =C365 -> 45708 | G23: =D365 -> 7 | H23: =IF(H364,E364,SUMIFS('Futures Data'!$E$5:$E$3471,'Futures Data'!$A$5:$A$3471,A365,'Futures Data'!$B$5:$B$3471,B365)) -> 13065 | I23: =IF(H364,G364,E365) -> 13230 | J23: =J365 -> 6318 | K23: =K365 -> 6368 | L23: =L365 -> 50 | M23: =L365/J365 -> 0.0079138968 | N23: =A366 -> 45667
A24: 17 | B24: =IF(H388,A388,A389) -> 45698 | C24: =A389 -> 45699 | D24: =IF(H388,"OI signal: next-month OI > held OI at previous close","Calendar backstop: "&D389&" trading days left") -> OI signal: next-month OI > held OI at previous close | E24: =B389 -> 45708 | F24: =C389 -> 45736 | G24: =D389 -> 7 | H24: =IF(H388,E388,SUMIFS('Futures Data'!$E$5:$E$3471,'Futures Data'!$A$5:$A$3471,A389,'Futures Data'!$B$5:$B$3471,B389)) -> 15180 | I24: =IF(H388,G388,E389) -> 16360 | J24: =J389 -> 6543 | K24: =K389 -> 6290 | L24: =L389 -> -253 | M24: =L389/J389 -> -0.038667278 | N24: =A390 -> 45700
A25: 18 | B25: =IF(H406,A406,A407) -> 45726 | C25: =A407 -> 45726 | D25: =IF(H406,"OI signal: next-month OI > held OI at previous close","Calendar backstop: "&D407&" trading days left") -> Calendar backstop: 7 trading days left | E25: =B407 -> 45736 | F25: =C407 -> 45764 | G25: =D407 -> 7 | H25: =IF(H406,E406,SUMIFS('Futures Data'!$E$5:$E$3471,'Futures Data'!$A$5:$A$3471,A407,'Futures Data'!$B$5:$B$3471,B407)) -> 20320 | I25: =IF(H406,G406,E407) -> 13095 | J25: =J407 -> 6256 | K25: =K407 -> 6264 | L25: =L407 -> 8 | M25: =L407/J407 -> 0.0012787724 | N25: =A408 -> 45727
A26: 19 | B26: =IF(H417,A417,A418) -> 45741 | C26: =A418 -> 45742 | D26: =IF(H417,"OI signal: next-month OI > held OI at previous close","Calendar backstop: "&D418&" trading days left") -> OI signal: next-month OI > held OI at previous close | E26: =B418 -> 45764 | F26: =C418 -> 45797 | G26: =D418 -> 13 | H26: =IF(H417,E417,SUMIFS('Futures Data'!$E$5:$E$3471,'Futures Data'!$A$5:$A$3471,A418,'Futures Data'!$B$5:$B$3471,B418)) -> 13800 | I26: =IF(H417,G417,E418) -> 14885 | J26: =J418 -> 6272 | K26: =K418 -> 6340 | L26: =L418 -> 68 | M26: =L418/J418 -> 0.010841837 | N26: =A419 -> 45743
A27: 20 | B27: =IF(H437,A437,A438) -> 45775 | C27: =A438 -> 45776 | D27: =IF(H437,"OI signal: next-month OI > held OI at previous close","Calendar backstop: "&D438&" trading days left") -> OI signal: next-month OI > held OI at previous close | E27: =B438 -> 45797 | F27: =C438 -> 45828 | G27: =D438 -> 14 | H27: =IF(H437,E437,SUMIFS('Futures Data'!$E$5:$E$3471,'Futures Data'!$A$5:$A$3471,A438,'Futures Data'!$B$5:$B$3471,B438)) -> 17560 | I27: =IF(H437,G437,E438) -> 18605 | J27: =J438 -> 6261 | K27: =K438 -> 6326 | L27: =L438 -> 65 | M27: =L438/J438 -> 0.010381728 | N27: =A439 -> 45777
A28: 21 | B28: =IF(H462,A462,A463) -> 45811 | C28: =A463 -> 45812 | D28: =IF(H462,"OI signal: next-month OI > held OI at previous close","Calendar backstop: "&D463&" trading days left") -> OI signal: next-month OI > held OI at previous close | E28: =B463 -> 45828 | F28: =C463 -> 45856 | G28: =D463 -> 12 | H28: =IF(H462,E462,SUMIFS('Futures Data'!$E$5:$E$3471,'Futures Data'!$A$5:$A$3471,A463,'Futures Data'!$B$5:$B$3471,B463)) -> 18280 | I28: =IF(H462,G462,E463) -> 19515 | J28: =J463 -> 6392 | K28: =K463 -> 6470 | L28: =L463 -> 78 | M28: =L463/J463 -> 0.012202753 | N28: =A464 -> 45813
A29: 22 | B29: =IF(H482,A482,A483) -> 45839 | C29: =A483 -> 45840 | D29: =IF(H482,"OI signal: next-month OI > held OI at previous close","Calendar backstop: "&D483&" trading days left") -> OI signal: next-month OI > held OI at previous close | E29: =B483 -> 45856 | F29: =C483 -> 45889 | G29: =D483 -> 12 | H29: =IF(H482,E482,SUMIFS('Futures Data'!$E$5:$E$3471,'Futures Data'!$A$5:$A$3471,A483,'Futures Data'!$B$5:$B$3471,B483)) -> 21870 | I29: =IF(H482,G482,E483) -> 23290 | J29: =J483 -> 6898 | K29: =K483 -> 6974 | L29: =L483 -> 76 | M29: =L483/J483 -> 0.011017686 | N29: =A484 -> 45841
A30: 23 | B30: =IF(H508,A508,A509) -> 45875 | C30: =A509 -> 45876 | D30: =IF(H508,"OI signal: next-month OI > held OI at previous close","Calendar backstop: "&D509&" trading days left") -> OI signal: next-month OI > held OI at previous close | E30: =B509 -> 45889 | F30: =C509 -> 45919 | G30: =D509 -> 8 | H30: =IF(H508,E508,SUMIFS('Futures Data'!$E$5:$E$3471,'Futures Data'!$A$5:$A$3471,A509,'Futures Data'!$B$5:$B$3471,B509)) -> 21840 | I30: =IF(H508,G508,E509) -> 22505 | J30: =J509 -> 6638 | K30: =K509 -> 6704 | L30: =L509 -> 66 | M30: =L509/J509 -> 0.0099427538 | N30: =A510 -> 45877
A31: 24 | B31: =IF(H526,A526,A527) -> 45903 | C31: =A527 -> 45904 | D31: =IF(H526,"OI signal: next-month OI > held OI at previous close","Calendar backstop: "&D527&" trading days left") -> OI signal: next-month OI > held OI at previous close | E31: =B527 -> 45919 | F31: =C527 -> 45950 | G31: =D527 -> 11 | H31: =IF(H526,E526,SUMIFS('Futures Data'!$E$5:$E$3471,'Futures Data'!$A$5:$A$3471,A527,'Futures Data'!$B$5:$B$3471,B527)) -> 18165 | I31: =IF(H526,G526,E527) -> 18950 | J31: =J527 -> 6622 | K31: =K527 -> 6685 | L31: =L527 -> 63 | M31: =L527/J527 -> 0.0095137421 | N31: =A528 -> 45905
A32: 25 | B32: =IF(H546,A546,A547) -> 45931 | C32: =A547 -> 45933 | D32: =IF(H546,"OI signal: next-month OI > held OI at previous close","Calendar backstop: "&D547&" trading days left") -> OI signal: next-month OI > held OI at previous close | E32: =B547 -> 45950 | F32: =C547 -> 45981 | G32: =D547 -> 11 | H32: =IF(H546,E546,SUMIFS('Futures Data'!$E$5:$E$3471,'Futures Data'!$A$5:$A$3471,A547,'Futures Data'!$B$5:$B$3471,B547)) -> 17630 | I32: =IF(H546,G546,E547) -> 19320 | J32: =J547 -> 6466 | K32: =K547 -> 6542 | L32: =L547 -> 76 | M32: =L547/J547 -> 0.011753789 | N32: =A548 -> 45936
A33: 26 | B33: =IF(H569,A569,A570) -> 45967 | C33: =A570 -> 45968 | D33: =IF(H569,"OI signal: next-month OI > held OI at previous close","Calendar backstop: "&D570&" trading days left") -> OI signal: next-month OI > held OI at previous close | E33: =B570 -> 45981 | F33: =C570 -> 46010 | G33: =D570 -> 9 | H33: =IF(H569,E569,SUMIFS('Futures Data'!$E$5:$E$3471,'Futures Data'!$A$5:$A$3471,A570,'Futures Data'!$B$5:$B$3471,B570)) -> 18525 | I33: =IF(H569,G569,E570) -> 19865 | J33: =J570 -> 6758 | K33: =K570 -> 6829 | L33: =L570 -> 71 | M33: =L570/J570 -> 0.010506067 | N33: =A571 -> 45971
A34: 27 | B34: =IF(H590,A590,A591) -> 45996 | C34: =A591 -> 45999 | D34: =IF(H590,"OI signal: next-month OI > held OI at previous close","Calendar backstop: "&D591&" trading days left") -> OI signal: next-month OI > held OI at previous close | E34: =B591 -> 46010 | F34: =C591 -> 46042 | G34: =D591 -> 9 | H34: =IF(H590,E590,SUMIFS('Futures Data'!$E$5:$E$3471,'Futures Data'!$A$5:$A$3471,A591,'Futures Data'!$B$5:$B$3471,B591)) -> 13785 | I34: =IF(H590,G590,E591) -> 15585 | J34: =J591 -> 6958 | K34: =K591 -> 6984 | L34: =L591 -> 26 | M34: =L591/J591 -> 0.0037367059 | N34: =A592 -> 46000
A35: 28 | B35: =IF(H612,A612,A613) -> 46030 | C35: =A613 -> 46030 | D35: =IF(H612,"OI signal: next-month OI > held OI at previous close","Calendar backstop: "&D613&" trading days left") -> Calendar backstop: 7 trading days left | E35: =B613 -> 46042 | F35: =C613 -> 46073 | G35: =D613 -> 7 | H35: =IF(H612,E612,SUMIFS('Futures Data'!$E$5:$E$3471,'Futures Data'!$A$5:$A$3471,A613,'Futures Data'!$B$5:$B$3471,B613)) -> 12415 | I35: =IF(H612,G612,E613) -> 14460 | J35: =J613 -> 6618 | K35: =K613 -> 6667 | L35: =L613 -> 49 | M35: =L613/J613 -> 0.0074040496 | N35: =A614 -> 46031
A36: 29 | B36: =IF(H635,A635,A636) -> 46063 | C36: =A636 -> 46064 | D36: =IF(H635,"OI signal: next-month OI > held OI at previous close","Calendar backstop: "&D636&" trading days left") -> OI signal: next-month OI > held OI at previous close | E36: =B636 -> 46073 | F36: =C636 -> 46101 | G36: =D636 -> 7 | H36: =IF(H635,E635,SUMIFS('Futures Data'!$E$5:$E$3471,'Futures Data'!$A$5:$A$3471,A636,'Futures Data'!$B$5:$B$3471,B636)) -> 14365 | I36: =IF(H635,G635,E636) -> 15970 | J36: =J636 -> 6388 | K36: =K636 -> 6445 | L36: =L636 -> 57 | M36: =L636/J636 -> 0.0089229806 | N36: =A637 -> 46065
A37: 30 | B37: =IF(H651,A651,A652) -> 46086 | C37: =A652 -> 46087 | D37: =IF(H651,"OI signal: next-month OI > held OI at previous close","Calendar backstop: "&D652&" trading days left") -> OI signal: next-month OI > held OI at previous close | E37: =B652 -> 46101 | F37: =C652 -> 46132 | G37: =D652 -> 10 | H37: =IF(H651,E651,SUMIFS('Futures Data'!$E$5:$E$3471,'Futures Data'!$A$5:$A$3471,A652,'Futures Data'!$B$5:$B$3471,B652)) -> 14625 | I37: =IF(H651,G651,E652) -> 15370 | J37: =J652 -> 6277 | K37: =K652 -> 6322 | L37: =L652 -> 45 | M37: =L652/J652 -> 0.0071690298 | N37: =A653 -> 46090
A38: 31 | B38: =IF(H671,A671,A672) -> 46119 | C38: =A672 -> 46120 | D38: =IF(H671,"OI signal: next-month OI > held OI at previous close","Calendar backstop: "&D672&" trading days left") -> OI signal: next-month OI > held OI at previous close | E38: =B672 -> 46132 | F38: =C672 -> 46162 | G38: =D672 -> 7 | H38: =IF(H671,E671,SUMIFS('Futures Data'!$E$5:$E$3471,'Futures Data'!$A$5:$A$3471,A672,'Futures Data'!$B$5:$B$3471,B672)) -> 14985 | I38: =IF(H671,G671,E672) -> 16660 | J38: =J672 -> 6375 | K38: =K672 -> 6441 | L38: =L672 -> 66 | M38: =L672/J672 -> 0.010352941 | N38: =A673 -> 46121
A39: 32 | B39: =IF(H690,A690,A691) -> 46148 | C39: =A691 -> 46149 | D39: =IF(H690,"OI signal: next-month OI > held OI at previous close","Calendar backstop: "&D691&" trading days left") -> OI signal: next-month OI > held OI at previous close | E39: =B691 -> 46162 | F39: =C691 -> 46192 | G39: =D691 -> 9 | H39: =IF(H690,E690,SUMIFS('Futures Data'!$E$5:$E$3471,'Futures Data'!$A$5:$A$3471,A691,'Futures Data'!$B$5:$B$3471,B691)) -> 14275 | I39: =IF(H690,G690,E691) -> 17020 | J39: =J691 -> 6501 | K39: =K691 -> 6592 | L39: =L691 -> 91 | M39: =L691/J691 -> 0.013997846 | N39: =A692 -> 46150
A40: 33 | B40: =IF(H713,A713,A714) -> 46182 | C40: =A714 -> 46183 | D40: =IF(H713,"OI signal: next-month OI > held OI at previous close","Calendar backstop: "&D714&" trading days left") -> OI signal: next-month OI > held OI at previous close | E40: =B714 -> 46192 | F40: =C714 -> 46223 | G40: =D714 -> 7 | H40: =IF(H713,E713,SUMIFS('Futures Data'!$E$5:$E$3471,'Futures Data'!$A$5:$A$3471,A714,'Futures Data'!$B$5:$B$3471,B714)) -> 15780 | I40: =IF(H713,G713,E714) -> 17960 | J40: =J714 -> 6549 | K40: =K714 -> 6656 | L40: =L714 -> 107 | M40: =L714/J714 -> 0.016338372 | N40: =A715 -> 46184
A41: 34 | B41: =IF(H731,A731,A732) -> 46209 | C41: =A732 -> 46210 | D41: =IF(H731,"OI signal: next-month OI > held OI at previous close","Calendar backstop: "&D732&" trading days left") -> OI signal: next-month OI > held OI at previous close | E41: =B732 -> 46223 | F41: =C732 -> 46254 | G41: =D732 -> 9 | H41: =IF(H731,E731,SUMIFS('Futures Data'!$E$5:$E$3471,'Futures Data'!$A$5:$A$3471,A732,'Futures Data'!$B$5:$B$3471,B732)) -> 20145 | I41: =IF(H731,G731,E732) -> 21375 | J41: =J732 -> 7042 | K41: =K732 -> 7125 | L41: =L732 -> 83 | M41: =L732/J732 -> 0.011786424 | N41: =A733 -> 46211
A42: 35 | B42: =IF(H753,A753,A754) -> 46239 | C42: =A754 -> 46240 | D42: =IF(H753,"OI signal: next-month OI > held OI at previous close","Calendar backstop: "&D754&" trading days left") -> OI signal: next-month OI > held OI at previous close | E42: =B754 -> 46254 | F42: =C754 -> 46283 | G42: =D754 -> 10 | H42: =IF(H753,E753,SUMIFS('Futures Data'!$E$5:$E$3471,'Futures Data'!$A$5:$A$3471,A754,'Futures Data'!$B$5:$B$3471,B754)) -> 17430 | I42: =IF(H753,G753,E754) -> 24265 | J42: =J754 -> 7131 | K42: =K754 -> 7212 | L42: =L754 -> 81 | M42: =L754/J754 -> 0.011358856 | N42: =A755 -> 46241
A43: 36 | B43: =IF(H773,A773,A774) -> 46267 | C43: =A774 -> 46268 | D43: =IF(H773,"OI signal: next-month OI > held OI at previous close","Calendar backstop: "&D774&" trading days left") -> OI signal: next-month OI > held OI at previous close | E43: =B774 -> 46283 | F43: =C774 -> 46311 | G43: =D774 -> 10 | H43: =IF(H773,E773,SUMIFS('Futures Data'!$E$5:$E$3471,'Futures Data'!$A$5:$A$3471,A774,'Futures Data'!$B$5:$B$3471,B774)) -> 22360 | I43: =IF(H773,G773,E774) -> 22665 | J43: =J774 -> 7542 | K43: =K774 -> 7659 | L43: =L774 -> 117 | M43: =L774/J774 -> 0.015513126 | N43: =A775 -> 46269
A44: Rolls counted in daily table: | D44: =COUNTIF(I47:I790,TRUE()) -> 36
A45: Daily contract selection and continuous series (one row per NCDEX trading day)
A46: Date t | B46: Held over (t-1,t]: contract used for day-t return | C46: Held at close t (after any switch) | D46: Trading days left on B after t | E46: OI of C at t (MT) | F46: Next contract after C | G46: OI of next contract at t (MT) | H46: OI signal at close t (G > E) | I46: Roll at close t | J46: Stitched price: close of B at t (Rs/qtl) | K46: Close of C at t | L46: Roll gap = K - J | M46: Sum of roll gaps on or after t | N46: Back-adjusted price = J + M | O46: Futures return = LN(J_t / K_t-1) | P46: LN change of back-adjusted series | Q46: Volume of B at t (MT) | R46: Python: held at close | S46: Excel = Python | T46: Return uses one contract
A47: 45194 | B47: =_xlfn.MINIFS('Futures Data'!$B$5:$B$3471,'Futures Data'!$A$5:$A$3471,A47,'Futures Data'!$B$5:$B$3471,">="&A47) -> 45219 | C47: =IF(D47<=$G$4,_xlfn.MINIFS('Futures Data'!$B$5:$B$3471,'Futures Data'!$A$5:$A$3471,A47,'Futures Data'!$B$5:$B$3471,">"&B47),B47) -> 45219 | D47: =COUNTIFS($A$47:$A$790,">"&A47,$A$47:$A$790,"<="&B47)+IF(B47>$G$5,NETWORKDAYS($G$5+1,B47),0) -> 18 | E47: =SUMIFS('Futures Data'!$E$5:$E$3471,'Futures Data'!$A$5:$A$3471,A47,'Futures Data'!$B$5:$B$3471,C47) -> 27755 | F47: =_xlfn.MINIFS('Futures Data'!$B$5:$B$3471,'Futures Data'!$A$5:$A$3471,A47,'Futures Data'!$B$5:$B$3471,">"&C47) -> 45250 | G47: =SUMIFS('Futures Data'!$E$5:$E$3471,'Futures Data'!$A$5:$A$3471,A47,'Futures Data'!$B$5:$B$3471,F47) -> 10270 | H47: =G47>E47 -> FALSE | I47: =C47<>B47 -> FALSE | J47: =SUMIFS('Futures Data'!$C$5:$C$3471,'Futures Data'!$A$5:$A$3471,A47,'Futures Data'!$B$5:$B$3471,B47) -> 6176 | K47: =SUMIFS('Futures Data'!$C$5:$C$3471,'Futures Data'!$A$5:$A$3471,A47,'Futures Data'!$B$5:$B$3471,C47) -> 6176 | L47: =K47-J47 -> 0 | M47: =M48+L47 -> 1689 | N47: =J47+M47 -> 7865 | Q47: =SUMIFS('Futures Data'!$D$5:$D$3471,'Futures Data'!$A$5:$A$3471,A47,'Futures Data'!$B$5:$B$3471,B47) -> 6820 | R47: 45219 | S47: =C47=R47 -> TRUE
A48: 45195 | B48: =C47 -> 45219 | C48: =IF(OR(H47,D48<=$G$4),_xlfn.MINIFS('Futures Data'!$B$5:$B$3471,'Futures Data'!$A$5:$A$3471,A48,'Futures Data'!$B$5:$B$3471,">"&B48),B48) -> 45219 | D48: =COUNTIFS($A$47:$A$790,">"&A48,$A$47:$A$790,"<="&B48)+IF(B48>$G$5,NETWORKDAYS($G$5+1,B48),0) -> 17 | E48: =SUMIFS('Futures Data'!$E$5:$E$3471,'Futures Data'!$A$5:$A$3471,A48,'Futures Data'!$B$5:$B$3471,C48) -> 26860 | F48: =_xlfn.MINIFS('Futures Data'!$B$5:$B$3471,'Futures Data'!$A$5:$A$3471,A48,'Futures Data'!$B$5:$B$3471,">"&C48) -> 45250 | G48: =SUMIFS('Futures Data'!$E$5:$E$3471,'Futures Data'!$A$5:$A$3471,A48,'Futures Data'!$B$5:$B$3471,F48) -> 11415 | H48: =G48>E48 -> FALSE | I48: =C48<>B48 -> FALSE | J48: =SUMIFS('Futures Data'!$C$5:$C$3471,'Futures Data'!$A$5:$A$3471,A48,'Futures Data'!$B$5:$B$3471,B48) -> 6155 | K48: =SUMIFS('Futures Data'!$C$5:$C$3471,'Futures Data'!$A$5:$A$3471,A48,'Futures Data'!$B$5:$B$3471,C48) -> 6155 | L48: =K48-J48 -> 0 | M48: =M49+L48 -> 1689 | N48: =J48+M48 -> 7844 | O48: =LN(J48/K47) -> -0.0034060531 | P48: =LN(N48/N47) -> -0.0026736282 | Q48: =SUMIFS('Futures Data'!$D$5:$D$3471,'Futures Data'!$A$5:$A$3471,A48,'Futures Data'!$B$5:$B$3471,B48) -> 4340 | R48: 45219 | S48: =C48=R48 -> TRUE | T48: =ABS(O48-LN(J48/SUMIFS('Futures Data'!$C$5:$C$3471,'Futures Data'!$A$5:$A$3471,A47,'Futures Data'!$B$5:$B$3471,B48)))<0.000000001 -> TRUE
A49: 45196 | B49: =C48 -> 45219 | C49: =IF(OR(H48,D49<=$G$4),_xlfn.MINIFS('Futures Data'!$B$5:$B$3471,'Futures Data'!$A$5:$A$3471,A49,'Futures Data'!$B$5:$B$3471,">"&B49),B49) -> 45219 | D49: =COUNTIFS($A$47:$A$790,">"&A49,$A$47:$A$790,"<="&B49)+IF(B49>$G$5,NETWORKDAYS($G$5+1,B49),0) -> 16 | E49: =SUMIFS('Futures Data'!$E$5:$E$3471,'Futures Data'!$A$5:$A$3471,A49,'Futures Data'!$B$5:$B$3471,C49) -> 23975 | F49: =_xlfn.MINIFS('Futures Data'!$B$5:$B$3471,'Futures Data'!$A$5:$A$3471,A49,'Futures Data'!$B$5:$B$3471,">"&C49) -> 45250 | G49: =SUMIFS('Futures Data'!$E$5:$E$3471,'Futures Data'!$A$5:$A$3471,A49,'Futures Data'!$B$5:$B$3471,F49) -> 15220 | H49: =G49>E49 -> FALSE | I49: =C49<>B49 -> FALSE | J49: =SUMIFS('Futures Data'!$C$5:$C$3471,'Futures Data'!$A$5:$A$3471,A49,'Futures Data'!$B$5:$B$3471,B49) -> 6164 | K49: =SUMIFS('Futures Data'!$C$5:$C$3471,'Futures Data'!$A$5:$A$3471,A49,'Futures Data'!$B$5:$B$3471,C49) -> 6164 | L49: =K49-J49 -> 0 | M49: =M50+L49 -> 1689 | N49: =J49+M49 -> 7853 | O49: =LN(J49/K48) -> 0.0014611578 | P49: =LN(N49/N48) -> 0.0011467161 | Q49: =SUMIFS('Futures Data'!$D$5:$D$3471,'Futures Data'!$A$5:$A$3471,A49,'Futures Data'!$B$5:$B$3471,B49) -> 8775 | R49: 45219 | S49: =C49=R49 -> TRUE | T49: =ABS(O49-LN(J49/SUMIFS('Futures Data'!$C$5:$C$3471,'Futures Data'!$A$5:$A$3471,A48,'Futures Data'!$B$5:$B$3471,B49)))<0.000000001 -> TRUE
A50: 45197 | B50: =C49 -> 45219 | C50: =IF(OR(H49,D50<=$G$4),_xlfn.MINIFS('Futures Data'!$B$5:$B$3471,'Futures Data'!$A$5:$A$3471,A50,'Futures Data'!$B$5:$B$3471,">"&B50),B50) -> 45219 | D50: =COUNTIFS($A$47:$A$790,">"&A50,$A$47:$A$790,"<="&B50)+IF(B50>$G$5,NETWORKDAYS($G$5+1,B50),0) -> 15 | E50: =SUMIFS('Futures Data'!$E$5:$E$3471,'Futures Data'!$A$5:$A$3471,A50,'Futures Data'!$B$5:$B$3471,C50) -> 22905 | F50: =_xlfn.MINIFS('Futures Data'!$B$5:$B$3471,'Futures Data'!$A$5:$A$3471,A50,'Futures Data'!$B$5:$B$3471,">"&C50) -> 45250 | G50: =SUMIFS('Futures Data'!$E$5:$E$3471,'Futures Data'!$A$5:$A$3471,A50,'Futures Data'!$B$5:$B$3471,F50) -> 17070 | H50: =G50>E50 -> FALSE | I50: =C50<>B50 -> FALSE | J50: =SUMIFS('Futures Data'!$C$5:$C$3471,'Futures Data'!$A$5:$A$3471,A50,'Futures Data'!$B$5:$B$3471,B50) -> 6215 | K50: =SUMIFS('Futures Data'!$C$5:$C$3471,'Futures Data'!$A$5:$A$3471,A50,'Futures Data'!$B$5:$B$3471,C50) -> 6215 | L50: =K50-J50 -> 0 | M50: =M51+L50 -> 1689 | N50: =J50+M50 -> 7904 | O50: =LN(J50/K49) -> 0.0082398075 | P50: =LN(N50/N49) -> 0.0064733361 | Q50: =SUMIFS('Futures Data'!$D$5:$D$3471,'Futures Data'!$A$5:$A$3471,A50,'Futures Data'!$B$5:$B$3471,B50) -> 5835 | R50: 45219 | S50: =C50=R50 -> TRUE | T50: =ABS(O50-LN(J50/SUMIFS('Futures Data'!$C$5:$C$3471,'Futures Data'!$A$5:$A$3471,A49,'Futures Data'!$B$5:$B$3471,B50)))<0.000000001 -> TRUE
A51: 45198 | B51: =C50 -> 45219 | C51: =IF(OR(H50,D51<=$G$4),_xlfn.MINIFS('Futures Data'!$B$5:$B$3471,'Futures Data'!$A$5:$A$3471,A51,'Futures Data'!$B$5:$B$3471,">"&B51),B51) -> 45219 | D51: =COUNTIFS($A$47:$A$790,">"&A51,$A$47:$A$790,"<="&B51)+IF(B51>$G$5,NETWORKDAYS($G$5+1,B51),0) -> 14 | E51: =SUMIFS('Futures Data'!$E$5:$E$3471,'Futures Data'!$A$5:$A$3471,A51,'Futures Data'!$B$5:$B$3471,C51) -> 18665 | F51: =_xlfn.MINIFS('Futures Data'!$B$5:$B$3471,'Futures Data'!$A$5:$A$3471,A51,'Futures Data'!$B$5:$B$3471,">"&C51) -> 45250 | G51: =SUMIFS('Futures Data'!$E$5:$E$3471,'Futures Data'!$A$5:$A$3471,A51,'Futures Data'!$B$5:$B$3471,F51) -> 18145 | H51: =G51>E51 -> FALSE | I51: =C51<>B51 -> FALSE | J51: =SUMIFS('Futures Data'!$C$5:$C$3471,'Futures Data'!$A$5:$A$3471,A51,'Futures Data'!$B$5:$B$3471,B51) -> 6137 | K51: =SUMIFS('Futures Data'!$C$5:$C$3471,'Futures Data'!$A$5:$A$3471,A51,'Futures Data'!$B$5:$B$3471,C51) -> 6137 | L51: =K51-J51 -> 0 | M51: =M52+L51 -> 1689 | N51: =J51+M51 -> 7826 | O51: =LN(J51/K50) -> -0.012629702 | P51: =LN(N51/N50) -> -0.0099174367 | Q51: =SUMIFS('Futures Data'!$D$5:$D$3471,'Futures Data'!$A$5:$A$3471,A51,'Futures Data'!$B$5:$B$3471,B51) -> 9415 | R51: 45219 | S51: =C51=R51 -> TRUE | T51: =ABS(O51-LN(J51/SUMIFS('Futures Data'!$C$5:$C$3471,'Futures Data'!$A$5:$A$3471,A50,'Futures Data'!$B$5:$B$3471,B51)))<0.000000001 -> TRUE
A52: 45202 | B52: =C51 -> 45219 | C52: =IF(OR(H51,D52<=$G$4),_xlfn.MINIFS('Futures Data'!$B$5:$B$3471,'Futures Data'!$A$5:$A$3471,A52,'Futures Data'!$B$5:$B$3471,">"&B52),B52) -> 45219 | D52: =COUNTIFS($A$47:$A$790,">"&A52,$A$47:$A$790,"<="&B52)+IF(B52>$G$5,NETWORKDAYS($G$5+1,B52),0) -> 13 | E52: =SUMIFS('Futures Data'!$E$5:$E$3471,'Futures Data'!$A$5:$A$3471,A52,'Futures Data'!$B$5:$B$3471,C52) -> 18280 | F52: =_xlfn.MINIFS('Futures Data'!$B$5:$B$3471,'Futures Data'!$A$5:$A$3471,A52,'Futures Data'!$B$5:$B$3471,">"&C52) -> 45250 | G52: =SUMIFS('Futures Data'!$E$5:$E$3471,'Futures Data'!$A$5:$A$3471,A52,'Futures Data'!$B$5:$B$3471,F52) -> 19645 | H52: =G52>E52 -> TRUE | I52: =C52<>B52 -> FALSE | J52: =SUMIFS('Futures Data'!$C$5:$C$3471,'Futures Data'!$A$5:$A$3471,A52,'Futures Data'!$B$5:$B$3471,B52) -> 6101 | K52: =SUMIFS('Futures Data'!$C$5:$C$3471,'Futures Data'!$A$5:$A$3471,A52,'Futures Data'!$B$5:$B$3471,C52) -> 6101 | L52: =K52-J52 -> 0 | M52: =M53+L52 -> 1689 | N52: =J52+M52 -> 7790 | O52: =LN(J52/K51) -> -0.0058833312 | P52: =LN(N52/N51) -> -0.0046106639 | Q52: =SUMIFS('Futures Data'!$D$5:$D$3471,'Futures Data'!$A$5:$A$3471,A52,'Futures Data'!$B$5:$B$3471,B52) -> 4630 | R52: 45219 | S52: =C52=R52 -> TRUE | T52: =ABS(O52-LN(J52/SUMIFS('Futures Data'!$C$5:$C$3471,'Futures Data'!$A$5:$A$3471,A51,'Futures Data'!$B$5:$B$3471,B52)))<0.000000001 -> TRUE
A53: 45203 | B53: =C52 -> 45219 | C53: =IF(OR(H52,D53<=$G$4),_xlfn.MINIFS('Futures Data'!$B$5:$B$3471,'Futures Data'!$A$5:$A$3471,A53,'Futures Data'!$B$5:$B$3471,">"&B53),B53) -> 45250 | D53: =COUNTIFS($A$47:$A$790,">"&A53,$A$47:$A$790,"<="&B53)+IF(B53>$G$5,NETWORKDAYS($G$5+1,B53),0) -> 12 | E53: =SUMIFS('Futures Data'!$E$5:$E$3471,'Futures Data'!$A$5:$A$3471,A53,'Futures Data'!$B$5:$B$3471,C53) -> 21280 | F53: =_xlfn.MINIFS('Futures Data'!$B$5:$B$3471,'Futures Data'!$A$5:$A$3471,A53,'Futures Data'!$B$5:$B$3471,">"&C53) -> 45280 | G53: =SUMIFS('Futures Data'!$E$5:$E$3471,'Futures Data'!$A$5:$A$3471,A53,'Futures Data'!$B$5:$B$3471,F53) -> 270 | H53: =G53>E53 -> FALSE | I53: =C53<>B53 -> TRUE | J53: =SUMIFS('Futures Data'!$C$5:$C$3471,'Futures Data'!$A$5:$A$3471,A53,'Futures Data'!$B$5:$B$3471,B53) -> 6135 | K53: =SUMIFS('Futures Data'!$C$5:$C$3471,'Futures Data'!$A$5:$A$3471,A53,'Futures Data'!$B$5:$B$3471,C53) -> 6193 | L53: =K53-J53 -> 58 | M53: =M54+L53 -> 1689 | N53: =J53+M53 -> 7824 | O53: =LN(J53/K52) -> 0.005557386 | P53: =LN(N53/N52) -> 0.0043550728 | Q53: =SUMIFS('Futures Data'!$D$5:$D$3471,'Futures Data'!$A$5:$A$3471,A53,'Futures Data'!$B$5:$B$3471,B53) -> 5905 | R53: 45250 | S53: =C53=R53 -> TRUE | T53: =ABS(O53-LN(J53/SUMIFS('Futures Data'!$C$5:$C$3471,'Futures Data'!$A$5:$A$3471,A52,'Futures Data'!$B$5:$B$3471,B53)))<0.000000001 -> TRUE
A54: 45204 | B54: =C53 -> 45250 | C54: =IF(OR(H53,D54<=$G$4),_xlfn.MINIFS('Futures Data'!$B$5:$B$3471,'Futures Data'!$A$5:$A$3471,A54,'Futures Data'!$B$5:$B$3471,">"&B54),B54) -> 45250 | D54: =COUNTIFS($A$47:$A$790,">"&A54,$A$47:$A$790,"<="&B54)+IF(B54>$G$5,NETWORKDAYS($G$5+1,B54),0) -> 31 | E54: =SUMIFS('Futures Data'!$E$5:$E$3471,'Futures Data'!$A$5:$A$3471,A54,'Futures Data'!$B$5:$B$3471,C54) -> 22020 | F54: =_xlfn.MINIFS('Futures Data'!$B$5:$B$3471,'Futures Data'!$A$5:$A$3471,A54,'Futures Data'!$B$5:$B$3471,">"&C54) -> 45280 | G54: =SUMIFS('Futures Data'!$E$5:$E$3471,'Futures Data'!$A$5:$A$3471,A54,'Futures Data'!$B$5:$B$3471,F54) -> 320 | H54: =G54>E54 -> FALSE | I54: =C54<>B54 -> FALSE | J54: =SUMIFS('Futures Data'!$C$5:$C$3471,'Futures Data'!$A$5:$A$3471,A54,'Futures Data'!$B$5:$B$3471,B54) -> 6175 | K54: =SUMIFS('Futures Data'!$C$5:$C$3471,'Futures Data'!$A$5:$A$3471,A54,'Futures Data'!$B$5:$B$3471,C54) -> 6175 | L54: =K54-J54 -> 0 | M54: =M55+L54 -> 1631 | N54: =J54+M54 -> 7806 | O54: =LN(J54/K53) -> -0.0029107394 | P54: =LN(N54/N53) -> -0.002303264 | Q54: =SUMIFS('Futures Data'!$D$5:$D$3471,'Futures Data'!$A$5:$A$3471,A54,'Futures Data'!$B$5:$B$3471,B54) -> 4065 | R54: 45250 | S54: =C54=R54 -> TRUE | T54: =ABS(O54-LN(J54/SUMIFS('Futures Data'!$C$5:$C$3471,'Futures Data'!$A$5:$A$3471,A53,'Futures Data'!$B$5:$B$3471,B54)))<0.000000001 -> TRUE
A55: 45205 | B55: =C54 -> 45250 | C55: =IF(OR(H54,D55<=$G$4),_xlfn.MINIFS('Futures Data'!$B$5:$B$3471,'Futures Data'!$A$5:$A$3471,A55,'Futures Data'!$B$5:$B$3471,">"&B55),B55) -> 45250 | D55: =COUNTIFS($A$47:$A$790,">"&A55,$A$47:$A$790,"<="&B55)+IF(B55>$G$5,NETWORKDAYS($G$5+1,B55),0) -> 30 | E55: =SUMIFS('Futures Data'!$E$5:$E$3471,'Futures Data'!$A$5:$A$3471,A55,'Futures Data'!$B$5:$B$3471,C55) -> 22755 | F55: =_xlfn.MINIFS('Futures Data'!$B$5:$B$3471,'Futures Data'!$A$5:$A$3471,A55,'Futures Data'!$B$5:$B$3471,">"&C55) -> 45280 | G55: =SUMIFS('Futures Data'!$E$5:$E$3471,'Futures Data'!$A$5:$A$3471,A55,'Futures Data'!$B$5:$B$3471,F55) -> 395 | H55: =G55>E55 -> FALSE | I55: =C55<>B55 -> FALSE | J55: =SUMIFS('Futures Data'!$C$5:$C$3471,'Futures Data'!$A$5:$A$3471,A55,'Futures Data'!$B$5:$B$3471,B55) -> 6162 | K55: =SUMIFS('Futures Data'!$C$5:$C$3471,'Futures Data'!$A$5:$A$3471,A55,'Futures Data'!$B$5:$B$3471,C55) -> 6162 | L55: =K55-J55 -> 0 | M55: =M56+L55 -> 1631 | N55: =J55+M55 -> 7793 | O55: =LN(J55/K54) -> -0.0021074823 | P55: =LN(N55/N54) -> -0.0016667739 | Q55: =SUMIFS('Futures Data'!$D$5:$D$3471,'Futures Data'!$A$5:$A$3471,A55,'Futures Data'!$B$5:$B$3471,B55) -> 6585 | R55: 45250 | S55: =C55=R55 -> TRUE | T55: =ABS(O55-LN(J55/SUMIFS('Futures Data'!$C$5:$C$3471,'Futures Data'!$A$5:$A$3471,A54,'Futures Data'!$B$5:$B$3471,B55)))<0.000000001 -> TRUE
A56: 45208 | B56: =C55 -> 45250 | C56: =IF(OR(H55,D56<=$G$4),_xlfn.MINIFS('Futures Data'!$B$5:$B$3471,'Futures Data'!$A$5:$A$3471,A56,'Futures Data'!$B$5:$B$3471,">"&B56),B56) -> 45250 | D56: =COUNTIFS($A$47:$A$790,">"&A56,$A$47:$A$790,"<="&B56)+IF(B56>$G$5,NETWORKDAYS($G$5+1,B56),0) -> 29 | E56: =SUMIFS('Futures Data'!$E$5:$E$3471,'Futures Data'!$A$5:$A$3471,A56,'Futures Data'!$B$5:$B$3471,C56) -> 24230 | F56: =_xlfn.MINIFS('Futures Data'!$B$5:$B$3471,'Futures Data'!$A$5:$A$3471,A56,'Futures Data'!$B$5:$B$3471,">"&C56) -> 45280 | G56: =SUMIFS('Futures Data'!$E$5:$E$3471,'Futures Data'!$A$5:$A$3471,A56,'Futures Data'!$B$5:$B$3471,F56) -> 395 | H56: =G56>E56 -> FALSE | I56: =C56<>B56 -> FALSE | J56: =SUMIFS('Futures Data'!$C$5:$C$3471,'Futures Data'!$A$5:$A$3471,A56,'Futures Data'!$B$5:$B$3471,B56) -> 6115 | K56: =SUMIFS('Futures Data'!$C$5:$C$3471,'Futures Data'!$A$5:$A$3471,A56,'Futures Data'!$B$5:$B$3471,C56) -> 6115 | L56: =K56-J56 -> 0 | M56: =M57+L56 -> 1631 | N56: =J56+M56 -> 7746 | O56: =LN(J56/K55) -> -0.007656631 | P56: =LN(N56/N55) -> -0.0060493138 | Q56: =SUMIFS('Futures Data'!$D$5:$D$3471,'Futures Data'!$A$5:$A$3471,A56,'Futures Data'!$B$5:$B$3471,B56) -> 5345 | R56: 45250 | S56: =C56=R56 -> TRUE | T56: =ABS(O56-LN(J56/SUMIFS('Futures Data'!$C$5:$C$3471,'Futures Data'!$A$5:$A$3471,A55,'Futures Data'!$B$5:$B$3471,B56)))<0.000000001 -> TRUE
A57: 45209 | B57: =C56 -> 45250 | C57: =IF(OR(H56,D57<=$G$4),_xlfn.MINIFS('Futures Data'!$B$5:$B$3471,'Futures Data'!$A$5:$A$3471,A57,'Futures Data'!$B$5:$B$3471,">"&B57),B57) -> 45250 | D57: =COUNTIFS($A$47:$A$790,">"&A57,$A$47:$A$790,"<="&B57)+IF(B57>$G$5,NETWORKDAYS($G$5+1,B57),0) -> 28 | E57: =SUMIFS('Futures Data'!$E$5:$E$3471,'Futures Data'!$A$5:$A$3471,A57,'Futures Data'!$B$5:$B$3471,C57) -> 25170 | F57: =_xlfn.MINIFS('Futures Data'!$B$5:$B$3471,'Futures Data'!$A$5:$A$3471,A57,'Futures Data'!$B$5:$B$3471,">"&C57) -> 45280 | G57: =SUMIFS('Futures Data'!$E$5:$E$3471,'Futures Data'!$A$5:$A$3471,A57,'Futures Data'!$B$5:$B$3471,F57) -> 395 | H57: =G57>E57 -> FALSE | I57: =C57<>B57 -> FALSE | J57: =SUMIFS('Futures Data'!$C$5:$C$3471,'Futures Data'!$A$5:$A$3471,A57,'Futures Data'!$B$5:$B$3471,B57) -> 6124 | K57: =SUMIFS('Futures Data'!$C$5:$C$3471,'Futures Data'!$A$5:$A$3471,A57,'Futures Data'!$B$5:$B$3471,C57) -> 6124 | L57: =K57-J57 -> 0 | M57: =M58+L57 -> 1631 | N57: =J57+M57 -> 7755 | O57: =LN(J57/K56) -> 0.0014707087 | P57: =LN(N57/N56) -> 0.0011612155 | Q57: =SUMIFS('Futures Data'!$D$5:$D$3471,'Futures Data'!$A$5:$A$3471,A57,'Futures Data'!$B$5:$B$3471,B57) -> 5300 | R57: 45250 | S57: =C57=R57 -> TRUE | T57: =ABS(O57-LN(J57/SUMIFS('Futures Data'!$C$5:$C$3471,'Futures Data'!$A$5:$A$3471,A56,'Futures Data'!$B$5:$B$3471,B57)))<0.000000001 -> TRUE
A58: 45210 | B58: =C57 -> 45250 | C58: =IF(OR(H57,D58<=$G$4),_xlfn.MINIFS('Futures Data'!$B$5:$B$3471,'Futures Data'!$A$5:$A$3471,A58,'Futures Data'!$B$5:$B$3471,">"&B58),B58) -> 45250 | D58: =COUNTIFS($A$47:$A$790,">"&A58,$A$47:$A$790,"<="&B58)+IF(B58>$G$5,NETWORKDAYS($G$5+1,B58),0) -> 27 | E58: =SUMIFS('Futures Data'!$E$5:$E$3471,'Futures Data'!$A$5:$A$3471,A58,'Futures Data'!$B$5:$B$3471,C58) -> 27150 | F58: =_xlfn.MINIFS('Futures Data'!$B$5:$B$3471,'Futures Data'!$A$5:$A$3471,A58,'Futures Data'!$B$5:$B$3471,">"&C58) -> 45280 | G58: =SUMIFS('Futures Data'!$E$5:$E$3471,'Futures Data'!$A$5:$A$3471,A58,'Futures Data'!$B$5:$B$3471,F58) -> 855 | H58: =G58>E58 -> FALSE | I58: =C58<>B58 -> FALSE | J58: =SUMIFS('Futures Data'!$C$5:$C$3471,'Futures Data'!$A$5:$A$3471,A58,'Futures Data'!$B$5:$B$3471,B58) -> 6072 | K58: =SUMIFS('Futures Data'!$C$5:$C$3471,'Futures Data'!$A$5:$A$3471,A58,'Futures Data'!$B$5:$B$3471,C58) -> 6072 | L58: =K58-J58 -> 0 | M58: =M59+L58 -> 1631 | N58: =J58+M58 -> 7703 | O58: =LN(J58/K57) -> -0.0085274377 | P58: =LN(N58/N57) -> -0.0067279333 | Q58: =SUMIFS('Futures Data'!$D$5:$D$3471,'Futures Data'!$A$5:$A$3471,A58,'Futures Data'!$B$5:$B$3471,B58) -> 10215 | R58: 45250 | S58: =C58=R58 -> TRUE | T58: =ABS(O58-LN(J58/SUMIFS('Futures Data'!$C$5:$C$3471,'Futures Data'!$A$5:$A$3471,A57,'Futures Data'!$B$5:$B$3471,B58)))<0.000000001 -> TRUE
A59: 45211 | B59: =C58 -> 45250 | C59: =IF(OR(H58,D59<=$G$4),_xlfn.MINIFS('Futures Data'!$B$5:$B$3471,'Futures Data'!$A$5:$A$3471,A59,'Futures Data'!$B$5:$B$3471,">"&B59),B59) -> 45250 | D59: =COUNTIFS($A$47:$A$790,">"&A59,$A$47:$A$790,"<="&B59)+IF(B59>$G$5,NETWORKDAYS($G$5+1,B59),0) -> 26 | E59: =SUMIFS('Futures Data'!$E$5:$E$3471,'Futures Data'!$A$5:$A$3471,A59,'Futures Data'!$B$5:$B$3471,C59) -> 28035 | F59: =_xlfn.MINIFS('Futures Data'!$B$5:$B$3471,'Futures Data'!$A$5:$A$3471,A59,'Futures Data'!$B$5:$B$3471,">"&C59) -> 45280 | G59: =SUMIFS('Futures Data'!$E$5:$E$3471,'Futures Data'!$A$5:$A$3471,A59,'Futures Data'!$B$5:$B$3471,F59) -> 1230 | H59: =G59>E59 -> FALSE | I59: =C59<>B59 -> FALSE | J59: =SUMIFS('Futures Data'!$C$5:$C$3471,'Futures Data'!$A$5:$A$3471,A59,'Futures Data'!$B$5:$B$3471,B59) -> 6034 | K59: =SUMIFS('Futures Data'!$C$5:$C$3471,'Futures Data'!$A$5:$A$3471,A59,'Futures Data'!$B$5:$B$3471,C59) -> 6034 | L59: =K59-J59 -> 0 | M59: =M60+L59 -> 1631 | N59: =J59+M59 -> 7665 | O59: =LN(J59/K58) -> -0.0062778994 | P59: =LN(N59/N58) -> -0.004945351 | Q59: =SUMIFS('Futures Data'!$D$5:$D$3471,'Futures Data'!$A$5:$A$3471,A59,'Futures Data'!$B$5:$B$3471,B59) -> 6825 | R59: 45250 | S59: =C59=R59 -> TRUE | T59: =ABS(O59-LN(J59/SUMIFS('Futures Data'!$C$5:$C$3471,'Futures Data'!$A$5:$A$3471,A58,'Futures Data'!$B$5:$B$3471,B59)))<0.000000001 -> TRUE
... A789: 46290 | B789: =C788 -> 46311 | C789: =IF(OR(H788,D789<=$G$4),_xlfn.MINIFS('Futures Data'!$B$5:$B$3471,'Futures Data'!$A$5:$A$3471,A789,'Futures Data'!$B$5:$B$3471,">"&B789),B789) -> 46311 | D789: =COUNTIFS($A$47:$A$790,">"&A789,$A$47:$A$790,"<="&B789)+IF(B789>$G$5,NETWORKDAYS($G$5+1,B789),0) -> 15 | E789: =SUMIFS('Futures Data'!$E$5:$E$3471,'Futures Data'!$A$5:$A$3471,A789,'Futures Data'!$B$5:$B$3471,C789) -> 30740 | F789: =_xlfn.MINIFS('Futures Data'!$B$5:$B$3471,'Futures Data'!$A$5:$A$3471,A789,'Futures Data'!$B$5:$B$3471,">"&C789) -> 46346 | G789: =SUMIFS('Futures Data'!$E$5:$E$3471,'Futures Data'!$A$5:$A$3471,A789,'Futures Data'!$B$5:$B$3471,F789) -> 14250 | H789: =G789>E789 -> FALSE | I789: =C789<>B789 -> FALSE | J789: =SUMIFS('Futures Data'!$C$5:$C$3471,'Futures Data'!$A$5:$A$3471,A789,'Futures Data'!$B$5:$B$3471,B789) -> 7665 | K789: =SUMIFS('Futures Data'!$C$5:$C$3471,'Futures Data'!$A$5:$A$3471,A789,'Futures Data'!$B$5:$B$3471,C789) -> 7665 | L789: =K789-J789 -> 0 | M789: =M790+L789 -> 0 | N789: =J789+M789 -> 7665 | O789: =LN(J789/K788) -> -0.003906255 | P789: =LN(N789/N788) -> -0.003906255 | Q789: =SUMIFS('Futures Data'!$D$5:$D$3471,'Futures Data'!$A$5:$A$3471,A789,'Futures Data'!$B$5:$B$3471,B789) -> 6575 | R789: 46311 | S789: =C789=R789 -> TRUE | T789: =ABS(O789-LN(J789/SUMIFS('Futures Data'!$C$5:$C$3471,'Futures Data'!$A$5:$A$3471,A788,'Futures Data'!$B$5:$B$3471,B789)))<0.000000001 -> TRUE
A790: 46293 | B790: =C789 -> 46311 | C790: =IF(OR(H789,D790<=$G$4),_xlfn.MINIFS('Futures Data'!$B$5:$B$3471,'Futures Data'!$A$5:$A$3471,A790,'Futures Data'!$B$5:$B$3471,">"&B790),B790) -> 46311 | D790: =COUNTIFS($A$47:$A$790,">"&A790,$A$47:$A$790,"<="&B790)+IF(B790>$G$5,NETWORKDAYS($G$5+1,B790),0) -> 14 | E790: =SUMIFS('Futures Data'!$E$5:$E$3471,'Futures Data'!$A$5:$A$3471,A790,'Futures Data'!$B$5:$B$3471,C790) -> 29560 | F790: =_xlfn.MINIFS('Futures Data'!$B$5:$B$3471,'Futures Data'!$A$5:$A$3471,A790,'Futures Data'!$B$5:$B$3471,">"&C790) -> 46346 | G790: =SUMIFS('Futures Data'!$E$5:$E$3471,'Futures Data'!$A$5:$A$3471,A790,'Futures Data'!$B$5:$B$3471,F790) -> 15750 | H790: =G790>E790 -> FALSE | I790: =C790<>B790 -> FALSE | J790: =SUMIFS('Futures Data'!$C$5:$C$3471,'Futures Data'!$A$5:$A$3471,A790,'Futures Data'!$B$5:$B$3471,B790) -> 7661 | K790: =SUMIFS('Futures Data'!$C$5:$C$3471,'Futures Data'!$A$5:$A$3471,A790,'Futures Data'!$B$5:$B$3471,C790) -> 7661 | L790: =K790-J790 -> 0 | M790: =L790 -> 0 | N790: =J790+M790 -> 7661 | O790: =LN(J790/K789) -> -0.00052198879 | P790: =LN(N790/N789) -> -0.00052198879 | Q790: =SUMIFS('Futures Data'!$D$5:$D$3471,'Futures Data'!$A$5:$A$3471,A790,'Futures Data'!$B$5:$B$3471,B790) -> 4505 | R790: 46311 | S790: =C790=R790 -> TRUE | T790: =ABS(O790-LN(J790/SUMIFS('Futures Data'!$C$5:$C$3471,'Futures Data'!$A$5:$A$3471,A789,'Futures Data'!$B$5:$B$3471,B790)))<0.000000001 -> TRUE

Sheet Daily Analysis
A1: Daily Analysis: matched one-day returns (consecutive NCDEX trading days with an SEA quote on both days)
A2: rA = LN(meal_t / meal_t-1); rF = LN(F_t / F_t-1) using the SAME contract on both days (column E). Hedged return = rA - h x rF (Buyukkara et al. eq. 12). Nothing is interpolated or carried forward.
A4: Date t | B4: Previous NCDEX trading day | C4: Castor meal t-1 (Rs/MT) | D4: Castor meal t (Rs/MT) | E4: Contract held over (t-1,t] | F4: Futures close t-1 (Rs/qtl) | G4: Futures close t (Rs/qtl) | H4: rA castor meal return | I4: rF futures return | J4: Sample | K4: Hedged: OLS h* | L4: Hedged: naive h = 1 | M4: GARCH h_t (Python, one-step-ahead) | N4: Hedged: GARCH h_t | O4: OLS h* (for chart)
A5: ='Roll Schedule'!A48 -> 45195 | B5: ='Roll Schedule'!A47 -> 45194 | C5: =SUMIFS('Spot Data'!$E$5:$E$651,'Spot Data'!$A$5:$A$651,B5,'Spot Data'!$H$5:$H$651,"YES") -> 9575 | D5: =SUMIFS('Spot Data'!$E$5:$E$651,'Spot Data'!$A$5:$A$651,A5,'Spot Data'!$H$5:$H$651,"YES") -> 9500 | E5: ='Roll Schedule'!B48 -> 45219 | F5: =SUMIFS('Futures Data'!$C$5:$C$3471,'Futures Data'!$A$5:$A$3471,B5,'Futures Data'!$B$5:$B$3471,E5) -> 6176 | G5: =SUMIFS('Futures Data'!$C$5:$C$3471,'Futures Data'!$A$5:$A$3471,A5,'Futures Data'!$B$5:$B$3471,E5) -> 6155 | H5: =LN(D5/C5) -> -0.0078637365 | I5: =LN(G5/F5) -> -0.0034060531 | J5: =IF(A5<='Results & Charts'!$C$5,"In-sample","Out-of-sample") -> In-sample | K5: =H5-'Results & Charts'!$C$9*I5 -> -0.0057738934 | L5: =H5-I5 -> -0.0044576834 | M5: 0.61356738 | N5: =H5-M5*I5 -> -0.0057738934 | O5: ='Results & Charts'!$C$9 -> 0.61356738
A6: ='Roll Schedule'!A52 -> 45202 | B6: ='Roll Schedule'!A51 -> 45198 | C6: =SUMIFS('Spot Data'!$E$5:$E$651,'Spot Data'!$A$5:$A$651,B6,'Spot Data'!$H$5:$H$651,"YES") -> 9450 | D6: =SUMIFS('Spot Data'!$E$5:$E$651,'Spot Data'!$A$5:$A$651,A6,'Spot Data'!$H$5:$H$651,"YES") -> 9350 | E6: ='Roll Schedule'!B52 -> 45219 | F6: =SUMIFS('Futures Data'!$C$5:$C$3471,'Futures Data'!$A$5:$A$3471,B6,'Futures Data'!$B$5:$B$3471,E6) -> 6137 | G6: =SUMIFS('Futures Data'!$C$5:$C$3471,'Futures Data'!$A$5:$A$3471,A6,'Futures Data'!$B$5:$B$3471,E6) -> 6101 | H6: =LN(D6/C6) -> -0.010638398 | I6: =LN(G6/F6) -> -0.0058833312 | J6: =IF(A6<='Results & Charts'!$C$5,"In-sample","Out-of-sample") -> In-sample | K6: =H6-'Results & Charts'!$C$9*I6 -> -0.0070285781 | L6: =H6-I6 -> -0.004755067 | M6: 0.65175501 | N6: =H6-M6*I6 -> -0.0068039076 | O6: ='Results & Charts'!$C$9 -> 0.61356738
A7: ='Roll Schedule'!A53 -> 45203 | B7: ='Roll Schedule'!A52 -> 45202 | C7: =SUMIFS('Spot Data'!$E$5:$E$651,'Spot Data'!$A$5:$A$651,B7,'Spot Data'!$H$5:$H$651,"YES") -> 9350 | D7: =SUMIFS('Spot Data'!$E$5:$E$651,'Spot Data'!$A$5:$A$651,A7,'Spot Data'!$H$5:$H$651,"YES") -> 9150 | E7: ='Roll Schedule'!B53 -> 45219 | F7: =SUMIFS('Futures Data'!$C$5:$C$3471,'Futures Data'!$A$5:$A$3471,B7,'Futures Data'!$B$5:$B$3471,E7) -> 6101 | G7: =SUMIFS('Futures Data'!$C$5:$C$3471,'Futures Data'!$A$5:$A$3471,A7,'Futures Data'!$B$5:$B$3471,E7) -> 6135 | H7: =LN(D7/C7) -> -0.021622464 | I7: =LN(G7/F7) -> 0.005557386 | J7: =IF(A7<='Results & Charts'!$C$5,"In-sample","Out-of-sample") -> In-sample | K7: =H7-'Results & Charts'!$C$9*I7 -> -0.025032295 | L7: =H7-I7 -> -0.02717985 | M7: 0.67065402 | N7: =H7-M7*I7 -> -0.025349547 | O7: ='Results & Charts'!$C$9 -> 0.61356738
A8: ='Roll Schedule'!A54 -> 45204 | B8: ='Roll Schedule'!A53 -> 45203 | C8: =SUMIFS('Spot Data'!$E$5:$E$651,'Spot Data'!$A$5:$A$651,B8,'Spot Data'!$H$5:$H$651,"YES") -> 9150 | D8: =SUMIFS('Spot Data'!$E$5:$E$651,'Spot Data'!$A$5:$A$651,A8,'Spot Data'!$H$5:$H$651,"YES") -> 9000 | E8: ='Roll Schedule'!B54 -> 45250 | F8: =SUMIFS('Futures Data'!$C$5:$C$3471,'Futures Data'!$A$5:$A$3471,B8,'Futures Data'!$B$5:$B$3471,E8) -> 6193 | G8: =SUMIFS('Futures Data'!$C$5:$C$3471,'Futures Data'!$A$5:$A$3471,A8,'Futures Data'!$B$5:$B$3471,E8) -> 6175 | H8: =LN(D8/C8) -> -0.016529302 | I8: =LN(G8/F8) -> -0.0029107394 | J8: =IF(A8<='Results & Charts'!$C$5,"In-sample","Out-of-sample") -> In-sample | K8: =H8-'Results & Charts'!$C$9*I8 -> -0.014743367 | L8: =H8-I8 -> -0.013618563 | M8: 0.61635836 | N8: =H8-M8*I8 -> -0.014735243 | O8: ='Results & Charts'!$C$9 -> 0.61356738
A9: ='Roll Schedule'!A55 -> 45205 | B9: ='Roll Schedule'!A54 -> 45204 | C9: =SUMIFS('Spot Data'!$E$5:$E$651,'Spot Data'!$A$5:$A$651,B9,'Spot Data'!$H$5:$H$651,"YES") -> 9000 | D9: =SUMIFS('Spot Data'!$E$5:$E$651,'Spot Data'!$A$5:$A$651,A9,'Spot Data'!$H$5:$H$651,"YES") -> 8950 | E9: ='Roll Schedule'!B55 -> 45250 | F9: =SUMIFS('Futures Data'!$C$5:$C$3471,'Futures Data'!$A$5:$A$3471,B9,'Futures Data'!$B$5:$B$3471,E9) -> 6175 | G9: =SUMIFS('Futures Data'!$C$5:$C$3471,'Futures Data'!$A$5:$A$3471,A9,'Futures Data'!$B$5:$B$3471,E9) -> 6162 | H9: =LN(D9/C9) -> -0.005571045 | I9: =LN(G9/F9) -> -0.0021074823 | J9: =IF(A9<='Results & Charts'!$C$5,"In-sample","Out-of-sample") -> In-sample | K9: =H9-'Results & Charts'!$C$9*I9 -> -0.0042779626 | L9: =H9-I9 -> -0.0034635627 | M9: 0.65994759 | N9: =H9-M9*I9 -> -0.0041802172 | O9: ='Results & Charts'!$C$9 -> 0.61356738
A10: ='Roll Schedule'!A56 -> 45208 | B10: ='Roll Schedule'!A55 -> 45205 | C10: =SUMIFS('Spot Data'!$E$5:$E$651,'Spot Data'!$A$5:$A$651,B10,'Spot Data'!$H$5:$H$651,"YES") -> 8950 | D10: =SUMIFS('Spot Data'!$E$5:$E$651,'Spot Data'!$A$5:$A$651,A10,'Spot Data'!$H$5:$H$651,"YES") -> 8875 | E10: ='Roll Schedule'!B56 -> 45250 | F10: =SUMIFS('Futures Data'!$C$5:$C$3471,'Futures Data'!$A$5:$A$3471,B10,'Futures Data'!$B$5:$B$3471,E10) -> 6162 | G10: =SUMIFS('Futures Data'!$C$5:$C$3471,'Futures Data'!$A$5:$A$3471,A10,'Futures Data'!$B$5:$B$3471,E10) -> 6115 | H10: =LN(D10/C10) -> -0.0084151969 | I10: =LN(G10/F10) -> -0.007656631 | J10: =IF(A10<='Results & Charts'!$C$5,"In-sample","Out-of-sample") -> In-sample | K10: =H10-'Results & Charts'!$C$9*I10 -> -0.0037173379 | L10: =H10-I10 -> -0.00075856589 | M10: 0.69390476 | N10: =H10-M10*I10 -> -0.0031022242 | O10: ='Results & Charts'!$C$9 -> 0.61356738
A11: ='Roll Schedule'!A57 -> 45209 | B11: ='Roll Schedule'!A56 -> 45208 | C11: =SUMIFS('Spot Data'!$E$5:$E$651,'Spot Data'!$A$5:$A$651,B11,'Spot Data'!$H$5:$H$651,"YES") -> 8875 | D11: =SUMIFS('Spot Data'!$E$5:$E$651,'Spot Data'!$A$5:$A$651,A11,'Spot Data'!$H$5:$H$651,"YES") -> 8950 | E11: ='Roll Schedule'!B57 -> 45250 | F11: =SUMIFS('Futures Data'!$C$5:$C$3471,'Futures Data'!$A$5:$A$3471,B11,'Futures Data'!$B$5:$B$3471,E11) -> 6115 | G11: =SUMIFS('Futures Data'!$C$5:$C$3471,'Futures Data'!$A$5:$A$3471,A11,'Futures Data'!$B$5:$B$3471,E11) -> 6124 | H11: =LN(D11/C11) -> 0.0084151969 | I11: =LN(G11/F11) -> 0.0014707087 | J11: =IF(A11<='Results & Charts'!$C$5,"In-sample","Out-of-sample") -> In-sample | K11: =H11-'Results & Charts'!$C$9*I11 -> 0.0075128181 | L11: =H11-I11 -> 0.0069444883 | M11: 0.66582879 | N11: =H11-M11*I11 -> 0.0074359568 | O11: ='Results & Charts'!$C$9 -> 0.61356738
A12: ='Roll Schedule'!A58 -> 45210 | B12: ='Roll Schedule'!A57 -> 45209 | C12: =SUMIFS('Spot Data'!$E$5:$E$651,'Spot Data'!$A$5:$A$651,B12,'Spot Data'!$H$5:$H$651,"YES") -> 8950 | D12: =SUMIFS('Spot Data'!$E$5:$E$651,'Spot Data'!$A$5:$A$651,A12,'Spot Data'!$H$5:$H$651,"YES") -> 8800 | E12: ='Roll Schedule'!B58 -> 45250 | F12: =SUMIFS('Futures Data'!$C$5:$C$3471,'Futures Data'!$A$5:$A$3471,B12,'Futures Data'!$B$5:$B$3471,E12) -> 6124 | G12: =SUMIFS('Futures Data'!$C$5:$C$3471,'Futures Data'!$A$5:$A$3471,A12,'Futures Data'!$B$5:$B$3471,E12) -> 6072 | H12: =LN(D12/C12) -> -0.016901811 | I12: =LN(G12/F12) -> -0.0085274377 | J12: =IF(A12<='Results & Charts'!$C$5,"In-sample","Out-of-sample") -> In-sample | K12: =H12-'Results & Charts'!$C$9*I12 -> -0.011669653 | L12: =H12-I12 -> -0.0083743731 | M12: 0.70167923 | N12: =H12-M12*I12 -> -0.010918285 | O12: ='Results & Charts'!$C$9 -> 0.61356738
A13: ='Roll Schedule'!A59 -> 45211 | B13: ='Roll Schedule'!A58 -> 45210 | C13: =SUMIFS('Spot Data'!$E$5:$E$651,'Spot Data'!$A$5:$A$651,B13,'Spot Data'!$H$5:$H$651,"YES") -> 8800 | D13: =SUMIFS('Spot Data'!$E$5:$E$651,'Spot Data'!$A$5:$A$651,A13,'Spot Data'!$H$5:$H$651,"YES") -> 8700 | E13: ='Roll Schedule'!B59 -> 45250 | F13: =SUMIFS('Futures Data'!$C$5:$C$3471,'Futures Data'!$A$5:$A$3471,B13,'Futures Data'!$B$5:$B$3471,E13) -> 6072 | G13: =SUMIFS('Futures Data'!$C$5:$C$3471,'Futures Data'!$A$5:$A$3471,A13,'Futures Data'!$B$5:$B$3471,E13) -> 6034 | H13: =LN(D13/C13) -> -0.011428696 | I13: =LN(G13/F13) -> -0.0062778994 | J13: =IF(A13<='Results & Charts'!$C$5,"In-sample","Out-of-sample") -> In-sample | K13: =H13-'Results & Charts'!$C$9*I13 -> -0.0075767815 | L13: =H13-I13 -> -0.0051507965 | M13: 0.68142864 | N13: =H13-M13*I13 -> -0.0071507554 | O13: ='Results & Charts'!$C$9 -> 0.61356738
A14: ='Roll Schedule'!A60 -> 45212 | B14: ='Roll Schedule'!A59 -> 45211 | C14: =SUMIFS('Spot Data'!$E$5:$E$651,'Spot Data'!$A$5:$A$651,B14,'Spot Data'!$H$5:$H$651,"YES") -> 8700 | D14: =SUMIFS('Spot Data'!$E$5:$E$651,'Spot Data'!$A$5:$A$651,A14,'Spot Data'!$H$5:$H$651,"YES") -> 8700 | E14: ='Roll Schedule'!B60 -> 45250 | F14: =SUMIFS('Futures Data'!$C$5:$C$3471,'Futures Data'!$A$5:$A$3471,B14,'Futures Data'!$B$5:$B$3471,E14) -> 6034 | G14: =SUMIFS('Futures Data'!$C$5:$C$3471,'Futures Data'!$A$5:$A$3471,A14,'Futures Data'!$B$5:$B$3471,E14) -> 6035 | H14: =LN(D14/C14) -> 0 | I14: =LN(G14/F14) -> 0.00016571381 | J14: =IF(A14<='Results & Charts'!$C$5,"In-sample","Out-of-sample") -> In-sample | K14: =H14-'Results & Charts'!$C$9*I14 -> -0.00010167659 | L14: =H14-I14 -> -0.00016571381 | M14: 0.68945143 | N14: =H14-M14*I14 -> -0.00011425162 | O14: ='Results & Charts'!$C$9 -> 0.61356738
A15: ='Roll Schedule'!A61 -> 45215 | B15: ='Roll Schedule'!A60 -> 45212 | C15: =SUMIFS('Spot Data'!$E$5:$E$651,'Spot Data'!$A$5:$A$651,B15,'Spot Data'!$H$5:$H$651,"YES") -> 8700 | D15: =SUMIFS('Spot Data'!$E$5:$E$651,'Spot Data'!$A$5:$A$651,A15,'Spot Data'!$H$5:$H$651,"YES") -> 8650 | E15: ='Roll Schedule'!B61 -> 45250 | F15: =SUMIFS('Futures Data'!$C$5:$C$3471,'Futures Data'!$A$5:$A$3471,B15,'Futures Data'!$B$5:$B$3471,E15) -> 6035 | G15: =SUMIFS('Futures Data'!$C$5:$C$3471,'Futures Data'!$A$5:$A$3471,A15,'Futures Data'!$B$5:$B$3471,E15) -> 6079 | H15: =LN(D15/C15) -> -0.0057637047 | I15: =LN(G15/F15) -> 0.0072643542 | J15: =IF(A15<='Results & Charts'!$C$5,"In-sample","Out-of-sample") -> In-sample | K15: =H15-'Results & Charts'!$C$9*I15 -> -0.010220876 | L15: =H15-I15 -> -0.013028059 | M15: 0.72549104 | N15: =H15-M15*I15 -> -0.011033929 | O15: ='Results & Charts'!$C$9 -> 0.61356738
A16: ='Roll Schedule'!A64 -> 45218 | B16: ='Roll Schedule'!A63 -> 45217 | C16: =SUMIFS('Spot Data'!$E$5:$E$651,'Spot Data'!$A$5:$A$651,B16,'Spot Data'!$H$5:$H$651,"YES") -> 8600 | D16: =SUMIFS('Spot Data'!$E$5:$E$651,'Spot Data'!$A$5:$A$651,A16,'Spot Data'!$H$5:$H$651,"YES") -> 8550 | E16: ='Roll Schedule'!B64 -> 45250 | F16: =SUMIFS('Futures Data'!$C$5:$C$3471,'Futures Data'!$A$5:$A$3471,B16,'Futures Data'!$B$5:$B$3471,E16) -> 6009 | G16: =SUMIFS('Futures Data'!$C$5:$C$3471,'Futures Data'!$A$5:$A$3471,A16,'Futures Data'!$B$5:$B$3471,E16) -> 6006 | H16: =LN(D16/C16) -> -0.0058309203 | I16: =LN(G16/F16) -> -0.00049937579 | J16: =IF(A16<='Results & Charts'!$C$5,"In-sample","Out-of-sample") -> In-sample | K16: =H16-'Results & Charts'!$C$9*I16 -> -0.0055245196 | L16: =H16-I16 -> -0.0053315445 | M16: 0.64911584 | N16: =H16-M16*I16 -> -0.0055067676 | O16: ='Results & Charts'!$C$9 -> 0.61356738
A17: ='Roll Schedule'!A65 -> 45219 | B17: ='Roll Schedule'!A64 -> 45218 | C17: =SUMIFS('Spot Data'!$E$5:$E$651,'Spot Data'!$A$5:$A$651,B17,'Spot Data'!$H$5:$H$651,"YES") -> 8550 | D17: =SUMIFS('Spot Data'!$E$5:$E$651,'Spot Data'!$A$5:$A$651,A17,'Spot Data'!$H$5:$H$651,"YES") -> 8450 | E17: ='Roll Schedule'!B65 -> 45250 | F17: =SUMIFS('Futures Data'!$C$5:$C$3471,'Futures Data'!$A$5:$A$3471,B17,'Futures Data'!$B$5:$B$3471,E17) -> 6006 | G17: =SUMIFS('Futures Data'!$C$5:$C$3471,'Futures Data'!$A$5:$A$3471,A17,'Futures Data'!$B$5:$B$3471,E17) -> 6036 | H17: =LN(D17/C17) -> -0.011764842 | I17: =LN(G17/F17) -> 0.0049825713 | J17: =IF(A17<='Results & Charts'!$C$5,"In-sample","Out-of-sample") -> In-sample | K17: =H17-'Results & Charts'!$C$9*I17 -> -0.014821985 | L17: =H17-I17 -> -0.016747413 | M17: 0.68388585 | N17: =H17-M17*I17 -> -0.015172352 | O17: ='Results & Charts'!$C$9 -> 0.61356738
A18: ='Roll Schedule'!A66 -> 45222 | B18: ='Roll Schedule'!A65 -> 45219 | C18: =SUMIFS('Spot Data'!$E$5:$E$651,'Spot Data'!$A$5:$A$651,B18,'Spot Data'!$H$5:$H$651,"YES") -> 8450 | D18: =SUMIFS('Spot Data'!$E$5:$E$651,'Spot Data'!$A$5:$A$651,A18,'Spot Data'!$H$5:$H$651,"YES") -> 8450 | E18: ='Roll Schedule'!B66 -> 45250 | F18: =SUMIFS('Futures Data'!$C$5:$C$3471,'Futures Data'!$A$5:$A$3471,B18,'Futures Data'!$B$5:$B$3471,E18) -> 6036 | G18: =SUMIFS('Futures Data'!$C$5:$C$3471,'Futures Data'!$A$5:$A$3471,A18,'Futures Data'!$B$5:$B$3471,E18) -> 6036 | H18: =LN(D18/C18) -> 0 | I18: =LN(G18/F18) -> 0 | J18: =IF(A18<='Results & Charts'!$C$5,"In-sample","Out-of-sample") -> In-sample | K18: =H18-'Results & Charts'!$C$9*I18 -> 0 | L18: =H18-I18 -> 0 | M18: 0.64347098 | N18: =H18-M18*I18 -> 0 | O18: ='Results & Charts'!$C$9 -> 0.61356738
A19: ='Roll Schedule'!A67 -> 45224 | B19: ='Roll Schedule'!A66 -> 45222 | C19: =SUMIFS('Spot Data'!$E$5:$E$651,'Spot Data'!$A$5:$A$651,B19,'Spot Data'!$H$5:$H$651,"YES") -> 8450 | D19: =SUMIFS('Spot Data'!$E$5:$E$651,'Spot Data'!$A$5:$A$651,A19,'Spot Data'!$H$5:$H$651,"YES") -> 8400 | E19: ='Roll Schedule'!B67 -> 45250 | F19: =SUMIFS('Futures Data'!$C$5:$C$3471,'Futures Data'!$A$5:$A$3471,B19,'Futures Data'!$B$5:$B$3471,E19) -> 6036 | G19: =SUMIFS('Futures Data'!$C$5:$C$3471,'Futures Data'!$A$5:$A$3471,A19,'Futures Data'!$B$5:$B$3471,E19) -> 6055 | H19: =LN(D19/C19) -> -0.0059347355 | I19: =LN(G19/F19) -> 0.0031428361 | J19: =IF(A19<='Results & Charts'!$C$5,"In-sample","Out-of-sample") -> In-sample | K19: =H19-'Results & Charts'!$C$9*I19 -> -0.0078630772 | L19: =H19-I19 -> -0.0090775716 | M19: 0.67358418 | N19: =H19-M19*I19 -> -0.0080517002 | O19: ='Results & Charts'!$C$9 -> 0.61356738
A20: ='Roll Schedule'!A68 -> 45225 | B20: ='Roll Schedule'!A67 -> 45224 | C20: =SUMIFS('Spot Data'!$E$5:$E$651,'Spot Data'!$A$5:$A$651,B20,'Spot Data'!$H$5:$H$651,"YES") -> 8400 | D20: =SUMIFS('Spot Data'!$E$5:$E$651,'Spot Data'!$A$5:$A$651,A20,'Spot Data'!$H$5:$H$651,"YES") -> 8150 | E20: ='Roll Schedule'!B68 -> 45250 | F20: =SUMIFS('Futures Data'!$C$5:$C$3471,'Futures Data'!$A$5:$A$3471,B20,'Futures Data'!$B$5:$B$3471,E20) -> 6055 | G20: =SUMIFS('Futures Data'!$C$5:$C$3471,'Futures Data'!$A$5:$A$3471,A20,'Futures Data'!$B$5:$B$3471,E20) -> 6008 | H20: =LN(D20/C20) -> -0.030213779 | I20: =LN(G20/F20) -> -0.0077924625 | J20: =IF(A20<='Results & Charts'!$C$5,"In-sample","Out-of-sample") -> In-sample | K20: =H20-'Results & Charts'!$C$9*I20 -> -0.025432578 | L20: =H20-I20 -> -0.022421316 | M20: 0.67006005 | N20: =H20-M20*I20 -> -0.024992361 | O20: ='Results & Charts'!$C$9 -> 0.61356738
A21: ='Roll Schedule'!A69 -> 45226 | B21: ='Roll Schedule'!A68 -> 45225 | C21: =SUMIFS('Spot Data'!$E$5:$E$651,'Spot Data'!$A$5:$A$651,B21,'Spot Data'!$H$5:$H$651,"YES") -> 8150 | D21: =SUMIFS('Spot Data'!$E$5:$E$651,'Spot Data'!$A$5:$A$651,A21,'Spot Data'!$H$5:$H$651,"YES") -> 8050 | E21: ='Roll Schedule'!B69 -> 45250 | F21: =SUMIFS('Futures Data'!$C$5:$C$3471,'Futures Data'!$A$5:$A$3471,B21,'Futures Data'!$B$5:$B$3471,E21) -> 6008 | G21: =SUMIFS('Futures Data'!$C$5:$C$3471,'Futures Data'!$A$5:$A$3471,A21,'Futures Data'!$B$5:$B$3471,E21) -> 5980 | H21: =LN(D21/C21) -> -0.012345836 | I21: =LN(G21/F21) -> -0.0046713465 | J21: =IF(A21<='Results & Charts'!$C$5,"In-sample","Out-of-sample") -> In-sample | K21: =H21-'Results & Charts'!$C$9*I21 -> -0.00947965 | L21: =H21-I21 -> -0.0076744893 | M21: 0.69830319 | N21: =H21-M21*I21 -> -0.0090838197 | O21: ='Results & Charts'!$C$9 -> 0.61356738
A22: ='Roll Schedule'!A70 -> 45229 | B22: ='Roll Schedule'!A69 -> 45226 | C22: =SUMIFS('Spot Data'!$E$5:$E$651,'Spot Data'!$A$5:$A$651,B22,'Spot Data'!$H$5:$H$651,"YES") -> 8050 | D22: =SUMIFS('Spot Data'!$E$5:$E$651,'Spot Data'!$A$5:$A$651,A22,'Spot Data'!$H$5:$H$651,"YES") -> 7950 | E22: ='Roll Schedule'!B70 -> 45250 | F22: =SUMIFS('Futures Data'!$C$5:$C$3471,'Futures Data'!$A$5:$A$3471,B22,'Futures Data'!$B$5:$B$3471,E22) -> 5980 | G22: =SUMIFS('Futures Data'!$C$5:$C$3471,'Futures Data'!$A$5:$A$3471,A22,'Futures Data'!$B$5:$B$3471,E22) -> 5920 | H22: =LN(D22/C22) -> -0.012500163 | I22: =LN(G22/F22) -> -0.010084119 | J22: =IF(A22<='Results & Charts'!$C$5,"In-sample","Out-of-sample") -> In-sample | K22: =H22-'Results & Charts'!$C$9*I22 -> -0.0063128762 | L22: =H22-I22 -> -0.0024160437 | M22: 0.71892626 | N22: =H22-M22*I22 -> -0.0052504247 | O22: ='Results & Charts'!$C$9 -> 0.61356738
A23: ='Roll Schedule'!A71 -> 45230 | B23: ='Roll Schedule'!A70 -> 45229 | C23: =SUMIFS('Spot Data'!$E$5:$E$651,'Spot Data'!$A$5:$A$651,B23,'Spot Data'!$H$5:$H$651,"YES") -> 7950 | D23: =SUMIFS('Spot Data'!$E$5:$E$651,'Spot Data'!$A$5:$A$651,A23,'Spot Data'!$H$5:$H$651,"YES") -> 7850 | E23: ='Roll Schedule'!B71 -> 45250 | F23: =SUMIFS('Futures Data'!$C$5:$C$3471,'Futures Data'!$A$5:$A$3471,B23,'Futures Data'!$B$5:$B$3471,E23) -> 5920 | G23: =SUMIFS('Futures Data'!$C$5:$C$3471,'Futures Data'!$A$5:$A$3471,A23,'Futures Data'!$B$5:$B$3471,E23) -> 5924 | H23: =LN(D23/C23) -> -0.012658397 | I23: =LN(G23/F23) -> 0.00067544751 | J23: =IF(A23<='Results & Charts'!$C$5,"In-sample","Out-of-sample") -> In-sample | K23: =H23-'Results & Charts'!$C$9*I23 -> -0.013072829 | L23: =H23-I23 -> -0.013333844 | M23: 0.64825011 | N23: =H23-M23*I23 -> -0.013096256 | O23: ='Results & Charts'!$C$9 -> 0.61356738
A24: ='Roll Schedule'!A72 -> 45231 | B24: ='Roll Schedule'!A71 -> 45230 | C24: =SUMIFS('Spot Data'!$E$5:$E$651,'Spot Data'!$A$5:$A$651,B24,'Spot Data'!$H$5:$H$651,"YES") -> 7850 | D24: =SUMIFS('Spot Data'!$E$5:$E$651,'Spot Data'!$A$5:$A$651,A24,'Spot Data'!$H$5:$H$651,"YES") -> 7750 | E24: ='Roll Schedule'!B72 -> 45250 | F24: =SUMIFS('Futures Data'!$C$5:$C$3471,'Futures Data'!$A$5:$A$3471,B24,'Futures Data'!$B$5:$B$3471,E24) -> 5924 | G24: =SUMIFS('Futures Data'!$C$5:$C$3471,'Futures Data'!$A$5:$A$3471,A24,'Futures Data'!$B$5:$B$3471,E24) -> 5892 | H24: =LN(D24/C24) -> -0.012820688 | I24: =LN(G24/F24) -> -0.0054163978 | J24: =IF(A24<='Results & Charts'!$C$5,"In-sample","Out-of-sample") -> In-sample | K24: =H24-'Results & Charts'!$C$9*I24 -> -0.0094973634 | L24: =H24-I24 -> -0.0074042906 | M24: 0.678305 | N24: =H24-M24*I24 -> -0.0091467187 | O24: ='Results & Charts'!$C$9 -> 0.61356738
A25: ='Roll Schedule'!A73 -> 45232 | B25: ='Roll Schedule'!A72 -> 45231 | C25: =SUMIFS('Spot Data'!$E$5:$E$651,'Spot Data'!$A$5:$A$651,B25,'Spot Data'!$H$5:$H$651,"YES") -> 7750 | D25: =SUMIFS('Spot Data'!$E$5:$E$651,'Spot Data'!$A$5:$A$651,A25,'Spot Data'!$H$5:$H$651,"YES") -> 7800 | E25: ='Roll Schedule'!B73 -> 45250 | F25: =SUMIFS('Futures Data'!$C$5:$C$3471,'Futures Data'!$A$5:$A$3471,B25,'Futures Data'!$B$5:$B$3471,E25) -> 5892 | G25: =SUMIFS('Futures Data'!$C$5:$C$3471,'Futures Data'!$A$5:$A$3471,A25,'Futures Data'!$B$5:$B$3471,E25) -> 5818 | H25: =LN(D25/C25) -> 0.0064308903 | I25: =LN(G25/F25) -> -0.012638939 | J25: =IF(A25<='Results & Charts'!$C$5,"In-sample","Out-of-sample") -> In-sample | K25: =H25-'Results & Charts'!$C$9*I25 -> 0.014185731 | L25: =H25-I25 -> 0.019069829 | M25: 0.69652229 | N25: =H25-M25*I25 -> 0.015234193 | O25: ='Results & Charts'!$C$9 -> 0.61356738
A26: ='Roll Schedule'!A86 -> 45251 | B26: ='Roll Schedule'!A85 -> 45250 | C26: =SUMIFS('Spot Data'!$E$5:$E$651,'Spot Data'!$A$5:$A$651,B26,'Spot Data'!$H$5:$H$651,"YES") -> 7950 | D26: =SUMIFS('Spot Data'!$E$5:$E$651,'Spot Data'!$A$5:$A$651,A26,'Spot Data'!$H$5:$H$651,"YES") -> 8400 | E26: ='Roll Schedule'!B86 -> 45280 | F26: =SUMIFS('Futures Data'!$C$5:$C$3471,'Futures Data'!$A$5:$A$3471,B26,'Futures Data'!$B$5:$B$3471,E26) -> 5914 | G26: =SUMIFS('Futures Data'!$C$5:$C$3471,'Futures Data'!$A$5:$A$3471,A26,'Futures Data'!$B$5:$B$3471,E26) -> 5942 | H26: =LN(D26/C26) -> 0.055059777 | I26: =LN(G26/F26) -> 0.0047233556 | J26: =IF(A26<='Results & Charts'!$C$5,"In-sample","Out-of-sample") -> In-sample | K26: =H26-'Results & Charts'!$C$9*I26 -> 0.05216168 | L26: =H26-I26 -> 0.050336422 | M26: 0.51089219 | N26: =H26-M26*I26 -> 0.052646652 | O26: ='Results & Charts'!$C$9 -> 0.61356738
A27: ='Roll Schedule'!A87 -> 45252 | B27: ='Roll Schedule'!A86 -> 45251 | C27: =SUMIFS('Spot Data'!$E$5:$E$651,'Spot Data'!$A$5:$A$651,B27,'Spot Data'!$H$5:$H$651,"YES") -> 8400 | D27: =SUMIFS('Spot Data'!$E$5:$E$651,'Spot Data'!$A$5:$A$651,A27,'Spot Data'!$H$5:$H$651,"YES") -> 8700 | E27: ='Roll Schedule'!B87 -> 45280 | F27: =SUMIFS('Futures Data'!$C$5:$C$3471,'Futures Data'!$A$5:$A$3471,B27,'Futures Data'!$B$5:$B$3471,E27) -> 5942 | G27: =SUMIFS('Futures Data'!$C$5:$C$3471,'Futures Data'!$A$5:$A$3471,A27,'Futures Data'!$B$5:$B$3471,E27) -> 6021 | H27: =LN(D27/C27) -> 0.03509132 | I27: =LN(G27/F27) -> 0.013207581 | J27: =IF(A27<='Results & Charts'!$C$5,"In-sample","Out-of-sample") -> In-sample | K27: =H27-'Results & Charts'!$C$9*I27 -> 0.026987579 | L27: =H27-I27 -> 0.021883738 | M27: 0.61606998 | N27: =H27-M27*I27 -> 0.026954525 | O27: ='Results & Charts'!$C$9 -> 0.61356738
A28: ='Roll Schedule'!A88 -> 45253 | B28: ='Roll Schedule'!A87 -> 45252 | C28: =SUMIFS('Spot Data'!$E$5:$E$651,'Spot Data'!$A$5:$A$651,B28,'Spot Data'!$H$5:$H$651,"YES") -> 8700 | D28: =SUMIFS('Spot Data'!$E$5:$E$651,'Spot Data'!$A$5:$A$651,A28,'Spot Data'!$H$5:$H$651,"YES") -> 8950 | E28: ='Roll Schedule'!B88 -> 45280 | F28: =SUMIFS('Futures Data'!$C$5:$C$3471,'Futures Data'!$A$5:$A$3471,B28,'Futures Data'!$B$5:$B$3471,E28) -> 6021 | G28: =SUMIFS('Futures Data'!$C$5:$C$3471,'Futures Data'!$A$5:$A$3471,A28,'Futures Data'!$B$5:$B$3471,E28) -> 6204 | H28: =LN(D28/C28) -> 0.028330507 | I28: =LN(G28/F28) -> 0.029940887 | J28: =IF(A28<='Results & Charts'!$C$5,"In-sample","Out-of-sample") -> In-sample | K28: =H28-'Results & Charts'!$C$9*I28 -> 0.0099597551 | L28: =H28-I28 -> -0.0016103802 | M28: 0.60763278 | N28: =H28-M28*I28 -> 0.010137442 | O28: ='Results & Charts'!$C$9 -> 0.61356738
A29: ='Roll Schedule'!A89 -> 45254 | B29: ='Roll Schedule'!A88 -> 45253 | C29: =SUMIFS('Spot Data'!$E$5:$E$651,'Spot Data'!$A$5:$A$651,B29,'Spot Data'!$H$5:$H$651,"YES") -> 8950 | D29: =SUMIFS('Spot Data'!$E$5:$E$651,'Spot Data'!$A$5:$A$651,A29,'Spot Data'!$H$5:$H$651,"YES") -> 8900 | E29: ='Roll Schedule'!B89 -> 45280 | F29: =SUMIFS('Futures Data'!$C$5:$C$3471,'Futures Data'!$A$5:$A$3471,B29,'Futures Data'!$B$5:$B$3471,E29) -> 6204 | G29: =SUMIFS('Futures Data'!$C$5:$C$3471,'Futures Data'!$A$5:$A$3471,A29,'Futures Data'!$B$5:$B$3471,E29) -> 6120 | H29: =LN(D29/C29) -> -0.0056022555 | I29: =LN(G29/F29) -> -0.013632149 | J29: =IF(A29<='Results & Charts'!$C$5,"In-sample","Out-of-sample") -> In-sample | K29: =H29-'Results & Charts'!$C$9*I29 -> 0.0027619863 | L29: =H29-I29 -> 0.0080298932 | M29: 0.36728124 | N29: =H29-M29*I29 -> -0.000595423 | O29: ='Results & Charts'!$C$9 -> 0.61356738
A30: ='Roll Schedule'!A90 -> 45258 | B30: ='Roll Schedule'!A89 -> 45254 | C30: =SUMIFS('Spot Data'!$E$5:$E$651,'Spot Data'!$A$5:$A$651,B30,'Spot Data'!$H$5:$H$651,"YES") -> 8900 | D30: =SUMIFS('Spot Data'!$E$5:$E$651,'Spot Data'!$A$5:$A$651,A30,'Spot Data'!$H$5:$H$651,"YES") -> 9050 | E30: ='Roll Schedule'!B90 -> 45280 | F30: =SUMIFS('Futures Data'!$C$5:$C$3471,'Futures Data'!$A$5:$A$3471,B30,'Futures Data'!$B$5:$B$3471,E30) -> 6120 | G30: =SUMIFS('Futures Data'!$C$5:$C$3471,'Futures Data'!$A$5:$A$3471,A30,'Futures Data'!$B$5:$B$3471,E30) -> 6177 | H30: =LN(D30/C30) -> 0.016713481 | I30: =LN(G30/F30) -> 0.0092706202 | J30: =IF(A30<='Results & Charts'!$C$5,"In-sample","Out-of-sample") -> In-sample | K30: =H30-'Results & Charts'!$C$9*I30 -> 0.011025331 | L30: =H30-I30 -> 0.0074428608 | M30: 0.3723504 | N30: =H30-M30*I30 -> 0.013261562 | O30: ='Results & Charts'!$C$9 -> 0.61356738
A31: ='Roll Schedule'!A91 -> 45259 | B31: ='Roll Schedule'!A90 -> 45258 | C31: =SUMIFS('Spot Data'!$E$5:$E$651,'Spot Data'!$A$5:$A$651,B31,'Spot Data'!$H$5:$H$651,"YES") -> 9050 | D31: =SUMIFS('Spot Data'!$E$5:$E$651,'Spot Data'!$A$5:$A$651,A31,'Spot Data'!$H$5:$H$651,"YES") -> 9000 | E31: ='Roll Schedule'!B91 -> 45280 | F31: =SUMIFS('Futures Data'!$C$5:$C$3471,'Futures Data'!$A$5:$A$3471,B31,'Futures Data'!$B$5:$B$3471,E31) -> 6177 | G31: =SUMIFS('Futures Data'!$C$5:$C$3471,'Futures Data'!$A$5:$A$3471,A31,'Futures Data'!$B$5:$B$3471,E31) -> 6121 | H31: =LN(D31/C31) -> -0.0055401804 | I31: =LN(G31/F31) -> -0.0091072348 | J31: =IF(A31<='Results & Charts'!$C$5,"In-sample","Out-of-sample") -> In-sample | K31: =H31-'Results & Charts'!$C$9*I31 -> 4.7721869e-05 | L31: =H31-I31 -> 0.0035670545 | M31: 0.41168884 | N31: =H31-M31*I31 -> -0.0017908334 | O31: ='Results & Charts'!$C$9 -> 0.61356738
A32: ='Roll Schedule'!A92 -> 45260 | B32: ='Roll Schedule'!A91 -> 45259 | C32: =SUMIFS('Spot Data'!$E$5:$E$651,'Spot Data'!$A$5:$A$651,B32,'Spot Data'!$H$5:$H$651,"YES") -> 9000 | D32: =SUMIFS('Spot Data'!$E$5:$E$651,'Spot Data'!$A$5:$A$651,A32,'Spot Data'!$H$5:$H$651,"YES") -> 8900 | E32: ='Roll Schedule'!B92 -> 45280 | F32: =SUMIFS('Futures Data'!$C$5:$C$3471,'Futures Data'!$A$5:$A$3471,B32,'Futures Data'!$B$5:$B$3471,E32) -> 6121 | G32: =SUMIFS('Futures Data'!$C$5:$C$3471,'Futures Data'!$A$5:$A$3471,A32,'Futures Data'!$B$5:$B$3471,E32) -> 6066 | H32: =LN(D32/C32) -> -0.011173301 | I32: =LN(G32/F32) -> -0.0090260726 | J32: =IF(A32<='Results & Charts'!$C$5,"In-sample","Out-of-sample") -> In-sample | K32: =H32-'Results & Charts'!$C$9*I32 -> -0.0056351969 | L32: =H32-I32 -> -0.002147228 | M32: 0.43949224 | N32: =H32-M32*I32 -> -0.0072064117 | O32: ='Results & Charts'!$C$9 -> 0.61356738
A33: ='Roll Schedule'!A93 -> 45261 | B33: ='Roll Schedule'!A92 -> 45260 | C33: =SUMIFS('Spot Data'!$E$5:$E$651,'Spot Data'!$A$5:$A$651,B33,'Spot Data'!$H$5:$H$651,"YES") -> 8900 | D33: =SUMIFS('Spot Data'!$E$5:$E$651,'Spot Data'!$A$5:$A$651,A33,'Spot Data'!$H$5:$H$651,"YES") -> 8850 | E33: ='Roll Schedule'!B93 -> 45280 | F33: =SUMIFS('Futures Data'!$C$5:$C$3471,'Futures Data'!$A$5:$A$3471,B33,'Futures Data'!$B$5:$B$3471,E33) -> 6066 | G33: =SUMIFS('Futures Data'!$C$5:$C$3471,'Futures Data'!$A$5:$A$3471,A33,'Futures Data'!$B$5:$B$3471,E33) -> 5995 | H33: =LN(D33/C33) -> -0.0056338177 | I33: =LN(G33/F33) -> -0.011773621 | J33: =IF(A33<='Results & Charts'!$C$5,"In-sample","Out-of-sample") -> In-sample | K33: =H33-'Results & Charts'!$C$9*I33 -> 0.001590092 | L33: =H33-I33 -> 0.0061398031 | M33: 0.47347369 | N33: =H33-M33*I33 -> -5.9317989e-05 | O33: ='Results & Charts'!$C$9 -> 0.61356738
A34: ='Roll Schedule'!A94 -> 45264 | B34: ='Roll Schedule'!A93 -> 45261 | C34: =SUMIFS('Spot Data'!$E$5:$E$651,'Spot Data'!$A$5:$A$651,B34,'Spot Data'!$H$5:$H$651,"YES") -> 8850 | D34: =SUMIFS('Spot Data'!$E$5:$E$651,'Spot Data'!$A$5:$A$651,A34,'Spot Data'!$H$5:$H$651,"YES") -> 8750 | E34: ='Roll Schedule'!B94 -> 45280 | F34: =SUMIFS('Futures Data'!$C$5:$C$3471,'Futures Data'!$A$5:$A$3471,B34,'Futures Data'!$B$5:$B$3471,E34) -> 5995 | G34: =SUMIFS('Futures Data'!$C$5:$C$3471,'Futures Data'!$A$5:$A$3471,A34,'Futures Data'!$B$5:$B$3471,E34) -> 5843 | H34: =LN(D34/C34) -> -0.011363759 | I34: =LN(G34/F34) -> -0.025681425 | J34: =IF(A34<='Results & Charts'!$C$5,"In-sample","Out-of-sample") -> In-sample | K34: =H34-'Results & Charts'!$C$9*I34 -> 0.004393526 | L34: =H34-I34 -> 0.014317666 | M34: 0.47700689 | N34: =H34-M34*I34 -> 0.00088645792 | O34: ='Results & Charts'!$C$9 -> 0.61356738
A35: ='Roll Schedule'!A97 -> 45267 | B35: ='Roll Schedule'!A96 -> 45266 | C35: =SUMIFS('Spot Data'!$E$5:$E$651,'Spot Data'!$A$5:$A$651,B35,'Spot Data'!$H$5:$H$651,"YES") -> 8850 | D35: =SUMIFS('Spot Data'!$E$5:$E$651,'Spot Data'!$A$5:$A$651,A35,'Spot Data'!$H$5:$H$651,"YES") -> 8650 | E35: ='Roll Schedule'!B97 -> 45310 | F35: =SUMIFS('Futures Data'!$C$5:$C$3471,'Futures Data'!$A$5:$A$3471,B35,'Futures Data'!$B$5:$B$3471,E35) -> 5988 | G35: =SUMIFS('Futures Data'!$C$5:$C$3471,'Futures Data'!$A$5:$A$3471,A35,'Futures Data'!$B$5:$B$3471,E35) -> 5935 | H35: =LN(D35/C35) -> -0.022858138 | I35: =LN(G35/F35) -> -0.0088904385 | J35: =IF(A35<='Results & Charts'!$C$5,"In-sample","Out-of-sample") -> In-sample | K35: =H35-'Results & Charts'!$C$9*I35 -> -0.017403255 | L35: =H35-I35 -> -0.0139677 | M35: 0.35516611 | N35: =H35-M35*I35 -> -0.019700556 | O35: ='Results & Charts'!$C$9 -> 0.61356738
A36: ='Roll Schedule'!A100 -> 45272 | B36: ='Roll Schedule'!A99 -> 45271 | C36: =SUMIFS('Spot Data'!$E$5:$E$651,'Spot Data'!$A$5:$A$651,B36,'Spot Data'!$H$5:$H$651,"YES") -> 8650 | D36: =SUMIFS('Spot Data'!$E$5:$E$651,'Spot Data'!$A$5:$A$651,A36,'Spot Data'!$H$5:$H$651,"YES") -> 8650 | E36: ='Roll Schedule'!B100 -> 45310 | F36: =SUMIFS('Futures Data'!$C$5:$C$3471,'Futures Data'!$A$5:$A$3471,B36,'Futures Data'!$B$5:$B$3471,E36) -> 5913 | G36: =SUMIFS('Futures Data'!$C$5:$C$3471,'Futures Data'!$A$5:$A$3471,A36,'Futures Data'!$B$5:$B$3471,E36) -> 5870 | H36: =LN(D36/C36) -> 0 | I36: =LN(G36/F36) -> -0.007298683 | J36: =IF(A36<='Results & Charts'!$C$5,"In-sample","Out-of-sample") -> In-sample | K36: =H36-'Results & Charts'!$C$9*I36 -> 0.0044782338 | L36: =H36-I36 -> 0.007298683 | M36: 0.40320787 | N36: =H36-M36*I36 -> 0.0029428864 | O36: ='Results & Charts'!$C$9 -> 0.61356738
A37: ='Roll Schedule'!A103 -> 45275 | B37: ='Roll Schedule'!A102 -> 45274 | C37: =SUMIFS('Spot Data'!$E$5:$E$651,'Spot Data'!$A$5:$A$651,B37,'Spot Data'!$H$5:$H$651,"YES") -> 8650 | D37: =SUMIFS('Spot Data'!$E$5:$E$651,'Spot Data'!$A$5:$A$651,A37,'Spot Data'!$H$5:$H$651,"YES") -> 8450 | E37: ='Roll Schedule'!B103 -> 45310 | F37: =SUMIFS('Futures Data'!$C$5:$C$3471,'Futures Data'!$A$5:$A$3471,B37,'Futures Data'!$B$5:$B$3471,E37) -> 5880 | G37: =SUMIFS('Futures Data'!$C$5:$C$3471,'Futures Data'!$A$5:$A$3471,A37,'Futures Data'!$B$5:$B$3471,E37) -> 5785 | H37: =LN(D37/C37) -> -0.02339288 | I37: =LN(G37/F37) -> -0.016288401 | J37: =IF(A37<='Results & Charts'!$C$5,"In-sample","Out-of-sample") -> In-sample | K37: =H37-'Results & Charts'!$C$9*I37 -> -0.013398848 | L37: =H37-I37 -> -0.0071044783 | M37: 0.43558572 | N37: =H37-M37*I37 -> -0.016297885 | O37: ='Results & Charts'!$C$9 -> 0.61356738
A38: ='Roll Schedule'!A110 -> 45287 | B38: ='Roll Schedule'!A109 -> 45286 | C38: =SUMIFS('Spot Data'!$E$5:$E$651,'Spot Data'!$A$5:$A$651,B38,'Spot Data'!$H$5:$H$651,"YES") -> 7950 | D38: =SUMIFS('Spot Data'!$E$5:$E$651,'Spot Data'!$A$5:$A$651,A38,'Spot Data'!$H$5:$H$651,"YES") -> 7900 | E38: ='Roll Schedule'!B110 -> 45310 | F38: =SUMIFS('Futures Data'!$C$5:$C$3471,'Futures Data'!$A$5:$A$3471,B38,'Futures Data'!$B$5:$B$3471,E38) -> 5736 | G38: =SUMIFS('Futures Data'!$C$5:$C$3471,'Futures Data'!$A$5:$A$3471,A38,'Futures Data'!$B$5:$B$3471,E38) -> 5739 | H38: =LN(D38/C38) -> -0.0063091692 | I38: =LN(G38/F38) -> 0.00052287583 | J38: =IF(A38<='Results & Charts'!$C$5,"In-sample","Out-of-sample") -> In-sample | K38: =H38-'Results & Charts'!$C$9*I38 -> -0.0066299887 | L38: =H38-I38 -> -0.006832045 | M38: 0.44604741 | N38: =H38-M38*I38 -> -0.0065423966 | O38: ='Results & Charts'!$C$9 -> 0.61356738
A39: ='Roll Schedule'!A117 -> 45296 | B39: ='Roll Schedule'!A116 -> 45295 | C39: =SUMIFS('Spot Data'!$E$5:$E$651,'Spot Data'!$A$5:$A$651,B39,'Spot Data'!$H$5:$H$651,"YES") -> 7650 | D39: =SUMIFS('Spot Data'!$E$5:$E$651,'Spot Data'!$A$5:$A$651,A39,'Spot Data'!$H$5:$H$651,"YES") -> 7600 | E39: ='Roll Schedule'!B117 -> 45342 | F39: =SUMIFS('Futures Data'!$C$5:$C$3471,'Futures Data'!$A$5:$A$3471,B39,'Futures Data'!$B$5:$B$3471,E39) -> 5762 | G39: =SUMIFS('Futures Data'!$C$5:$C$3471,'Futures Data'!$A$5:$A$3471,A39,'Futures Data'!$B$5:$B$3471,E39) -> 5739 | H39: =LN(D39/C39) -> -0.0065574005 | I39: =LN(G39/F39) -> -0.0039996575 | J39: =IF(A39<='Results & Charts'!$C$5,"In-sample","Out-of-sample") -> In-sample | K39: =H39-'Results & Charts'!$C$9*I39 -> -0.0041033411 | L39: =H39-I39 -> -0.002557743 | M39: 0.49796122 | N39: =H39-M39*I39 -> -0.0045657262 | O39: ='Results & Charts'!$C$9 -> 0.61356738
A40: ='Roll Schedule'!A118 -> 45299 | B40: ='Roll Schedule'!A117 -> 45296 | C40: =SUMIFS('Spot Data'!$E$5:$E$651,'Spot Data'!$A$5:$A$651,B40,'Spot Data'!$H$5:$H$651,"YES") -> 7600 | D40: =SUMIFS('Spot Data'!$E$5:$E$651,'Spot Data'!$A$5:$A$651,A40,'Spot Data'!$H$5:$H$651,"YES") -> 7150 | E40: ='Roll Schedule'!B118 -> 45342 | F40: =SUMIFS('Futures Data'!$C$5:$C$3471,'Futures Data'!$A$5:$A$3471,B40,'Futures Data'!$B$5:$B$3471,E40) -> 5739 | G40: =SUMIFS('Futures Data'!$C$5:$C$3471,'Futures Data'!$A$5:$A$3471,A40,'Futures Data'!$B$5:$B$3471,E40) -> 5672 | H40: =LN(D40/C40) -> -0.061035891 | I40: =LN(G40/F40) -> -0.01174319 | J40: =IF(A40<='Results & Charts'!$C$5,"In-sample","Out-of-sample") -> In-sample | K40: =H40-'Results & Charts'!$C$9*I40 -> -0.053830652 | L40: =H40-I40 -> -0.049292701 | M40: 0.55113015 | N40: =H40-M40*I40 -> -0.054563865 | O40: ='Results & Charts'!$C$9 -> 0.61356738
A41: ='Roll Schedule'!A119 -> 45300 | B41: ='Roll Schedule'!A118 -> 45299 | C41: =SUMIFS('Spot Data'!$E$5:$E$651,'Spot Data'!$A$5:$A$651,B41,'Spot Data'!$H$5:$H$651,"YES") -> 7150 | D41: =SUMIFS('Spot Data'!$E$5:$E$651,'Spot Data'!$A$5:$A$651,A41,'Spot Data'!$H$5:$H$651,"YES") -> 7400 | E41: ='Roll Schedule'!B119 -> 45342 | F41: =SUMIFS('Futures Data'!$C$5:$C$3471,'Futures Data'!$A$5:$A$3471,B41,'Futures Data'!$B$5:$B$3471,E41) -> 5672 | G41: =SUMIFS('Futures Data'!$C$5:$C$3471,'Futures Data'!$A$5:$A$3471,A41,'Futures Data'!$B$5:$B$3471,E41) -> 5671 | H41: =LN(D41/C41) -> 0.034367644 | I41: =LN(G41/F41) -> -0.0001763202 | J41: =IF(A41<='Results & Charts'!$C$5,"In-sample","Out-of-sample") -> In-sample | K41: =H41-'Results & Charts'!$C$9*I41 -> 0.034475828 | L41: =H41-I41 -> 0.034543964 | M41: 0.65195973 | N41: =H41-M41*I41 -> 0.034482597 | O41: ='Results & Charts'!$C$9 -> 0.61356738
A42: ='Roll Schedule'!A120 -> 45301 | B42: ='Roll Schedule'!A119 -> 45300 | C42: =SUMIFS('Spot Data'!$E$5:$E$651,'Spot Data'!$A$5:$A$651,B42,'Spot Data'!$H$5:$H$651,"YES") -> 7400 | D42: =SUMIFS('Spot Data'!$E$5:$E$651,'Spot Data'!$A$5:$A$651,A42,'Spot Data'!$H$5:$H$651,"YES") -> 7200 | E42: ='Roll Schedule'!B120 -> 45342 | F42: =SUMIFS('Futures Data'!$C$5:$C$3471,'Futures Data'!$A$5:$A$3471,B42,'Futures Data'!$B$5:$B$3471,E42) -> 5671 | G42: =SUMIFS('Futures Data'!$C$5:$C$3471,'Futures Data'!$A$5:$A$3471,A42,'Futures Data'!$B$5:$B$3471,E42) -> 5614 | H42: =LN(D42/C42) -> -0.027398974 | I42: =LN(G42/F42) -> -0.010101991 | J42: =IF(A42<='Results & Charts'!$C$5,"In-sample","Out-of-sample") -> In-sample | K42: =H42-'Results & Charts'!$C$9*I42 -> -0.021200722 | L42: =H42-I42 -> -0.017296983 | M42: 0.721971 | N42: =H42-M42*I42 -> -0.02010563 | O42: ='Results & Charts'!$C$9 -> 0.61356738
A43: ='Roll Schedule'!A121 -> 45302 | B43: ='Roll Schedule'!A120 -> 45301 | C43: =SUMIFS('Spot Data'!$E$5:$E$651,'Spot Data'!$A$5:$A$651,B43,'Spot Data'!$H$5:$H$651,"YES") -> 7200 | D43: =SUMIFS('Spot Data'!$E$5:$E$651,'Spot Data'!$A$5:$A$651,A43,'Spot Data'!$H$5:$H$651,"YES") -> 7100 | E43: ='Roll Schedule'!B121 -> 45342 | F43: =SUMIFS('Futures Data'!$C$5:$C$3471,'Futures Data'!$A$5:$A$3471,B43,'Futures Data'!$B$5:$B$3471,E43) -> 5614 | G43: =SUMIFS('Futures Data'!$C$5:$C$3471,'Futures Data'!$A$5:$A$3471,A43,'Futures Data'!$B$5:$B$3471,E43) -> 5624 | H43: =LN(D43/C43) -> -0.013986242 | I43: =LN(G43/F43) -> 0.0017796766 | J43: =IF(A43<='Results & Charts'!$C$5,"In-sample","Out-of-sample") -> In-sample | K43: =H43-'Results & Charts'!$C$9*I43 -> -0.015078193 | L43: =H43-I43 -> -0.015765919 | M43: 0.76273162 | N43: =H43-M43*I43 -> -0.015343658 | O43: ='Results & Charts'!$C$9 -> 0.61356738
A44: ='Roll Schedule'!A125 -> 45308 | B44: ='Roll Schedule'!A124 -> 45307 | C44: =SUMIFS('Spot Data'!$E$5:$E$651,'Spot Data'!$A$5:$A$651,B44,'Spot Data'!$H$5:$H$651,"YES") -> 6950 | D44: =SUMIFS('Spot Data'!$E$5:$E$651,'Spot Data'!$A$5:$A$651,A44,'Spot Data'!$H$5:$H$651,"YES") -> 6950 | E44: ='Roll Schedule'!B125 -> 45342 | F44: =SUMIFS('Futures Data'!$C$5:$C$3471,'Futures Data'!$A$5:$A$3471,B44,'Futures Data'!$B$5:$B$3471,E44) -> 5649 | G44: =SUMIFS('Futures Data'!$C$5:$C$3471,'Futures Data'!$A$5:$A$3471,A44,'Futures Data'!$B$5:$B$3471,E44) -> 5647 | H44: =LN(D44/C44) -> 0 | I44: =LN(G44/F44) -> -0.00035410765 | J44: =IF(A44<='Results & Charts'!$C$5,"In-sample","Out-of-sample") -> In-sample | K44: =H44-'Results & Charts'!$C$9*I44 -> 0.00021726891 | L44: =H44-I44 -> 0.00035410765 | M44: 0.82522178 | N44: =H44-M44*I44 -> 0.00029221735 | O44: ='Results & Charts'!$C$9 -> 0.61356738
A45: ='Roll Schedule'!A126 -> 45309 | B45: ='Roll Schedule'!A125 -> 45308 | C45: =SUMIFS('Spot Data'!$E$5:$E$651,'Spot Data'!$A$5:$A$651,B45,'Spot Data'!$H$5:$H$651,"YES") -> 6950 | D45: =SUMIFS('Spot Data'!$E$5:$E$651,'Spot Data'!$A$5:$A$651,A45,'Spot Data'!$H$5:$H$651,"YES") -> 6850 | E45: ='Roll Schedule'!B126 -> 45342 | F45: =SUMIFS('Futures Data'!$C$5:$C$3471,'Futures Data'!$A$5:$A$3471,B45,'Futures Data'!$B$5:$B$3471,E45) -> 5647 | G45: =SUMIFS('Futures Data'!$C$5:$C$3471,'Futures Data'!$A$5:$A$3471,A45,'Futures Data'!$B$5:$B$3471,E45) -> 5683 | H45: =LN(D45/C45) -> -0.014493007 | I45: =LN(G45/F45) -> 0.0063548316 | J45: =IF(A45<='Results & Charts'!$C$5,"In-sample","Out-of-sample") -> In-sample | K45: =H45-'Results & Charts'!$C$9*I45 -> -0.018392125 | L45: =H45-I45 -> -0.020847839 | M45: 0.89906747 | N45: =H45-M45*I45 -> -0.02020643 | O45: ='Results & Charts'!$C$9 -> 0.61356738
A46: ='Roll Schedule'!A130 -> 45316 | B46: ='Roll Schedule'!A129 -> 45315 | C46: =SUMIFS('Spot Data'!$E$5:$E$651,'Spot Data'!$A$5:$A$651,B46,'Spot Data'!$H$5:$H$651,"YES") -> 6850 | D46: =SUMIFS('Spot Data'!$E$5:$E$651,'Spot Data'!$A$5:$A$651,A46,'Spot Data'!$H$5:$H$651,"YES") -> 6850 | E46: ='Roll Schedule'!B130 -> 45342 | F46: =SUMIFS('Futures Data'!$C$5:$C$3471,'Futures Data'!$A$5:$A$3471,B46,'Futures Data'!$B$5:$B$3471,E46) -> 5784 | G46: =SUMIFS('Futures Data'!$C$5:$C$3471,'Futures Data'!$A$5:$A$3471,A46,'Futures Data'!$B$5:$B$3471,E46) -> 5818 | H46: =LN(D46/C46) -> 0 | I46: =LN(G46/F46) -> 0.0058610752 | J46: =IF(A46<='Results & Charts'!$C$5,"In-sample","Out-of-sample") -> In-sample | K46: =H46-'Results & Charts'!$C$9*I46 -> -0.0035961646 | L46: =H46-I46 -> -0.0058610752 | M46: 0.88490421 | N46: =H46-M46*I46 -> -0.0051864901 | O46: ='Results & Charts'!$C$9 -> 0.61356738
A47: ='Roll Schedule'!A131 -> 45320 | B47: ='Roll Schedule'!A130 -> 45316 | C47: =SUMIFS('Spot Data'!$E$5:$E$651,'Spot Data'!$A$5:$A$651,B47,'Spot Data'!$H$5:$H$651,"YES") -> 6850 | D47: =SUMIFS('Spot Data'!$E$5:$E$651,'Spot Data'!$A$5:$A$651,A47,'Spot Data'!$H$5:$H$651,"YES") -> 6750 | E47: ='Roll Schedule'!B131 -> 45342 | F47: =SUMIFS('Futures Data'!$C$5:$C$3471,'Futures Data'!$A$5:$A$3471,B47,'Futures Data'!$B$5:$B$3471,E47) -> 5818 | G47: =SUMIFS('Futures Data'!$C$5:$C$3471,'Futures Data'!$A$5:$A$3471,A47,'Futures Data'!$B$5:$B$3471,E47) -> 5713 | H47: =LN(D47/C47) -> -0.014706147 | I47: =LN(G47/F47) -> -0.01821228 | J47: =IF(A47<='Results & Charts'!$C$5,"In-sample","Out-of-sample") -> In-sample | K47: =H47-'Results & Charts'!$C$9*I47 -> -0.0035316862 | L47: =H47-I47 -> 0.0035061329 | M47: 0.8998035 | N47: =H47-M47*I47 -> 0.0016813262 | O47: ='Results & Charts'!$C$9 -> 0.61356738
A48: ='Roll Schedule'!A132 -> 45321 | B48: ='Roll Schedule'!A131 -> 45320 | C48: =SUMIFS('Spot Data'!$E$5:$E$651,'Spot Data'!$A$5:$A$651,B48,'Spot Data'!$H$5:$H$651,"YES") -> 6750 | D48: =SUMIFS('Spot Data'!$E$5:$E$651,'Spot Data'!$A$5:$A$651,A48,'Spot Data'!$H$5:$H$651,"YES") -> 6700 | E48: ='Roll Schedule'!B132 -> 45342 | F48: =SUMIFS('Futures Data'!$C$5:$C$3471,'Futures Data'!$A$5:$A$3471,B48,'Futures Data'!$B$5:$B$3471,E48) -> 5713 | G48: =SUMIFS('Futures Data'!$C$5:$C$3471,'Futures Data'!$A$5:$A$3471,A48,'Futures Data'!$B$5:$B$3471,E48) -> 5763 | H48: =LN(D48/C48) -> -0.0074349785 | I48: =LN(G48/F48) -> 0.0087138927 | J48: =IF(A48<='Results & Charts'!$C$5,"In-sample","Out-of-sample") -> In-sample | K48: =H48-'Results & Charts'!$C$9*I48 -> -0.012781539 | L48: =H48-I48 -> -0.016148871 | M48: 0.68287637 | N48: =H48-M48*I48 -> -0.01338549 | O48: ='Results & Charts'!$C$9 -> 0.61356738
A49: ='Roll Schedule'!A133 -> 45322 | B49: ='Roll Schedule'!A132 -> 45321 | C49: =SUMIFS('Spot Data'!$E$5:$E$651,'Spot Data'!$A$5:$A$651,B49,'Spot Data'!$H$5:$H$651,"YES") -> 6700 | D49: =SUMIFS('Spot Data'!$E$5:$E$651,'Spot Data'!$A$5:$A$651,A49,'Spot Data'!$H$5:$H$651,"YES") -> 6650 | E49: ='Roll Schedule'!B133 -> 45342 | F49: =SUMIFS('Futures Data'!$C$5:$C$3471,'Futures Data'!$A$5:$A$3471,B49,'Futures Data'!$B$5:$B$3471,E49) -> 5763 | G49: =SUMIFS('Futures Data'!$C$5:$C$3471,'Futures Data'!$A$5:$A$3471,A49,'Futures Data'!$B$5:$B$3471,E49) -> 5739 | H49: =LN(D49/C49) -> -0.0074906717 | I49: =LN(G49/F49) -> -0.0041731933 | J49: =IF(A49<='Results & Charts'!$C$5,"In-sample","Out-of-sample") -> In-sample | K49: =H49-'Results & Charts'!$C$9*I49 -> -0.0049301364 | L49: =H49-I49 -> -0.0033174784 | M49: 0.66733858 | N49: =H49-M49*I49 -> -0.0047057388 | O49: ='Results & Charts'!$C$9 -> 0.61356738
A50: ='Roll Schedule'!A134 -> 45323 | B50: ='Roll Schedule'!A133 -> 45322 | C50: =SUMIFS('Spot Data'!$E$5:$E$651,'Spot Data'!$A$5:$A$651,B50,'Spot Data'!$H$5:$H$651,"YES") -> 6650 | D50: =SUMIFS('Spot Data'!$E$5:$E$651,'Spot Data'!$A$5:$A$651,A50,'Spot Data'!$H$5:$H$651,"YES") -> 6550 | E50: ='Roll Schedule'!B134 -> 45342 | F50: =SUMIFS('Futures Data'!$C$5:$C$3471,'Futures Data'!$A$5:$A$3471,B50,'Futures Data'!$B$5:$B$3471,E50) -> 5739 | G50: =SUMIFS('Futures Data'!$C$5:$C$3471,'Futures Data'!$A$5:$A$3471,A50,'Futures Data'!$B$5:$B$3471,E50) -> 5740 | H50: =LN(D50/C50) -> -0.015151805 | I50: =LN(G50/F50) -> 0.00017423121 | J50: =IF(A50<='Results & Charts'!$C$5,"In-sample","Out-of-sample") -> In-sample | K50: =H50-'Results & Charts'!$C$9*I50 -> -0.015258708 | L50: =H50-I50 -> -0.015326036 | M50: 0.72437083 | N50: =H50-M50*I50 -> -0.015278013 | O50: ='Results & Charts'!$C$9 -> 0.61356738
A51: ='Roll Schedule'!A135 -> 45324 | B51: ='Roll Schedule'!A134 -> 45323 | C51: =SUMIFS('Spot Data'!$E$5:$E$651,'Spot Data'!$A$5:$A$651,B51,'Spot Data'!$H$5:$H$651,"YES") -> 6550 | D51: =SUMIFS('Spot Data'!$E$5:$E$651,'Spot Data'!$A$5:$A$651,A51,'Spot Data'!$H$5:$H$651,"YES") -> 6350 | E51: ='Roll Schedule'!B135 -> 45342 | F51: =SUMIFS('Futures Data'!$C$5:$C$3471,'Futures Data'!$A$5:$A$3471,B51,'Futures Data'!$B$5:$B$3471,E51) -> 5740 | G51: =SUMIFS('Futures Data'!$C$5:$C$3471,'Futures Data'!$A$5:$A$3471,A51,'Futures Data'!$B$5:$B$3471,E51) -> 5739 | H51: =LN(D51/C51) -> -0.031010237 | I51: =LN(G51/F51) -> -0.00017423121 | J51: =IF(A51<='Results & Charts'!$C$5,"In-sample","Out-of-sample") -> In-sample | K51: =H51-'Results & Charts'!$C$9*I51 -> -0.030903334 | L51: =H51-I51 -> -0.030836006 | M51: 0.7868401 | N51: =H51-M51*I51 -> -0.030873145 | O51: ='Results & Charts'!$C$9 -> 0.61356738
A52: ='Roll Schedule'!A136 -> 45327 | B52: ='Roll Schedule'!A135 -> 45324 | C52: =SUMIFS('Spot Data'!$E$5:$E$651,'Spot Data'!$A$5:$A$651,B52,'Spot Data'!$H$5:$H$651,"YES") -> 6350 | D52: =SUMIFS('Spot Data'!$E$5:$E$651,'Spot Data'!$A$5:$A$651,A52,'Spot Data'!$H$5:$H$651,"YES") -> 6050 | E52: ='Roll Schedule'!B136 -> 45342 | F52: =SUMIFS('Futures Data'!$C$5:$C$3471,'Futures Data'!$A$5:$A$3471,B52,'Futures Data'!$B$5:$B$3471,E52) -> 5739 | G52: =SUMIFS('Futures Data'!$C$5:$C$3471,'Futures Data'!$A$5:$A$3471,A52,'Futures Data'!$B$5:$B$3471,E52) -> 5675 | H52: =LN(D52/C52) -> -0.048396541 | I52: =LN(G52/F52) -> -0.011214416 | J52: =IF(A52<='Results & Charts'!$C$5,"In-sample","Out-of-sample") -> In-sample | K52: =H52-'Results & Charts'!$C$9*I52 -> -0.041515741 | L52: =H52-I52 -> -0.037182125 | M52: 0.84913327 | N52: =H52-M52*I52 -> -0.038874007 | O52: ='Results & Charts'!$C$9 -> 0.61356738
A53: ='Roll Schedule'!A137 -> 45328 | B53: ='Roll Schedule'!A136 -> 45327 | C53: =SUMIFS('Spot Data'!$E$5:$E$651,'Spot Data'!$A$5:$A$651,B53,'Spot Data'!$H$5:$H$651,"YES") -> 6050 | D53: =SUMIFS('Spot Data'!$E$5:$E$651,'Spot Data'!$A$5:$A$651,A53,'Spot Data'!$H$5:$H$651,"YES") -> 6050 | E53: ='Roll Schedule'!B137 -> 45342 | F53: =SUMIFS('Futures Data'!$C$5:$C$3471,'Futures Data'!$A$5:$A$3471,B53,'Futures Data'!$B$5:$B$3471,E53) -> 5675 | G53: =SUMIFS('Futures Data'!$C$5:$C$3471,'Futures Data'!$A$5:$A$3471,A53,'Futures Data'!$B$5:$B$3471,E53) -> 5697 | H53: =LN(D53/C53) -> 0 | I53: =LN(G53/F53) -> 0.0038691571 | J53: =IF(A53<='Results & Charts'!$C$5,"In-sample","Out-of-sample") -> In-sample | K53: =H53-'Results & Charts'!$C$9*I53 -> -0.0023739886 | L53: =H53-I53 -> -0.0038691571 | M53: 0.89227008 | N53: =H53-M53*I53 -> -0.0034523332 | O53: ='Results & Charts'!$C$9 -> 0.61356738
A54: ='Roll Schedule'!A138 -> 45329 | B54: ='Roll Schedule'!A137 -> 45328 | C54: =SUMIFS('Spot Data'!$E$5:$E$651,'Spot Data'!$A$5:$A$651,B54,'Spot Data'!$H$5:$H$651,"YES") -> 6050 | D54: =SUMIFS('Spot Data'!$E$5:$E$651,'Spot Data'!$A$5:$A$651,A54,'Spot Data'!$H$5:$H$651,"YES") -> 6250 | E54: ='Roll Schedule'!B138 -> 45342 | F54: =SUMIFS('Futures Data'!$C$5:$C$3471,'Futures Data'!$A$5:$A$3471,B54,'Futures Data'!$B$5:$B$3471,E54) -> 5697 | G54: =SUMIFS('Futures Data'!$C$5:$C$3471,'Futures Data'!$A$5:$A$3471,A54,'Futures Data'!$B$5:$B$3471,E54) -> 5758 | H54: =LN(D54/C54) -> 0.032523192 | I54: =LN(G54/F54) -> 0.010650472 | J54: =IF(A54<='Results & Charts'!$C$5,"In-sample","Out-of-sample") -> In-sample | K54: =H54-'Results & Charts'!$C$9*I54 -> 0.02598841 | L54: =H54-I54 -> 0.02187272 | M54: 0.93604766 | N54: =H54-M54*I54 -> 0.022553843 | O54: ='Results & Charts'!$C$9 -> 0.61356738
A55: ='Roll Schedule'!A139 -> 45330 | B55: ='Roll Schedule'!A138 -> 45329 | C55: =SUMIFS('Spot Data'!$E$5:$E$651,'Spot Data'!$A$5:$A$651,B55,'Spot Data'!$H$5:$H$651,"YES") -> 6250 | D55: =SUMIFS('Spot Data'!$E$5:$E$651,'Spot Data'!$A$5:$A$651,A55,'Spot Data'!$H$5:$H$651,"YES") -> 6150 | E55: ='Roll Schedule'!B139 -> 45342 | F55: =SUMIFS('Futures Data'!$C$5:$C$3471,'Futures Data'!$A$5:$A$3471,B55,'Futures Data'!$B$5:$B$3471,E55) -> 5758 | G55: =SUMIFS('Futures Data'!$C$5:$C$3471,'Futures Data'!$A$5:$A$3471,A55,'Futures Data'!$B$5:$B$3471,E55) -> 5756 | H55: =LN(D55/C55) -> -0.016129382 | I55: =LN(G55/F55) -> -0.00034740316 | J55: =IF(A55<='Results & Charts'!$C$5,"In-sample","Out-of-sample") -> In-sample | K55: =H55-'Results & Charts'!$C$9*I55 -> -0.015916227 | L55: =H55-I55 -> -0.015781979 | M55: 0.92412003 | N55: =H55-M55*I55 -> -0.01580834 | O55: ='Results & Charts'!$C$9 -> 0.61356738
A56: ='Roll Schedule'!A140 -> 45331 | B56: ='Roll Schedule'!A139 -> 45330 | C56: =SUMIFS('Spot Data'!$E$5:$E$651,'Spot Data'!$A$5:$A$651,B56,'Spot Data'!$H$5:$H$651,"YES") -> 6150 | D56: =SUMIFS('Spot Data'!$E$5:$E$651,'Spot Data'!$A$5:$A$651,A56,'Spot Data'!$H$5:$H$651,"YES") -> 6150 | E56: ='Roll Schedule'!B140 -> 45342 | F56: =SUMIFS('Futures Data'!$C$5:$C$3471,'Futures Data'!$A$5:$A$3471,B56,'Futures Data'!$B$5:$B$3471,E56) -> 5756 | G56: =SUMIFS('Futures Data'!$C$5:$C$3471,'Futures Data'!$A$5:$A$3471,A56,'Futures Data'!$B$5:$B$3471,E56) -> 5773 | H56: =LN(D56/C56) -> 0 | I56: =LN(G56/F56) -> 0.0029490871 | J56: =IF(A56<='Results & Charts'!$C$5,"In-sample","Out-of-sample") -> In-sample | K56: =H56-'Results & Charts'!$C$9*I56 -> -0.0018094636 | L56: =H56-I56 -> -0.0029490871 | M56: 0.99684872 | N56: =H56-M56*I56 -> -0.0029397937 | O56: ='Results & Charts'!$C$9 -> 0.61356738
A57: ='Roll Schedule'!A141 -> 45334 | B57: ='Roll Schedule'!A140 -> 45331 | C57: =SUMIFS('Spot Data'!$E$5:$E$651,'Spot Data'!$A$5:$A$651,B57,'Spot Data'!$H$5:$H$651,"YES") -> 6150 | D57: =SUMIFS('Spot Data'!$E$5:$E$651,'Spot Data'!$A$5:$A$651,A57,'Spot Data'!$H$5:$H$651,"YES") -> 6150 | E57: ='Roll Schedule'!B141 -> 45371 | F57: =SUMIFS('Futures Data'!$C$5:$C$3471,'Futures Data'!$A$5:$A$3471,B57,'Futures Data'!$B$5:$B$3471,E57) -> 5610 | G57: =SUMIFS('Futures Data'!$C$5:$C$3471,'Futures Data'!$A$5:$A$3471,A57,'Futures Data'!$B$5:$B$3471,E57) -> 5605 | H57: =LN(D57/C57) -> 0 | I57: =LN(G57/F57) -> -0.00089166301 | J57: =IF(A57<='Results & Charts'!$C$5,"In-sample","Out-of-sample") -> In-sample | K57: =H57-'Results & Charts'!$C$9*I57 -> 0.00054709534 | L57: =H57-I57 -> 0.00089166301 | M57: 1.0475084 | N57: =H57-M57*I57 -> 0.00093402445 | O57: ='Results & Charts'!$C$9 -> 0.61356738
A58: ='Roll Schedule'!A144 -> 45337 | B58: ='Roll Schedule'!A143 -> 45336 | C58: =SUMIFS('Spot Data'!$E$5:$E$651,'Spot Data'!$A$5:$A$651,B58,'Spot Data'!$H$5:$H$651,"YES") -> 6050 | D58: =SUMIFS('Spot Data'!$E$5:$E$651,'Spot Data'!$A$5:$A$651,A58,'Spot Data'!$H$5:$H$651,"YES") -> 6150 | E58: ='Roll Schedule'!B144 -> 45371 | F58: =SUMIFS('Futures Data'!$C$5:$C$3471,'Futures Data'!$A$5:$A$3471,B58,'Futures Data'!$B$5:$B$3471,E58) -> 5638 | G58: =SUMIFS('Futures Data'!$C$5:$C$3471,'Futures Data'!$A$5:$A$3471,A58,'Futures Data'!$B$5:$B$3471,E58) -> 5639 | H58: =LN(D58/C58) -> 0.01639381 | I58: =LN(G58/F58) -> 0.00017735213 | J58: =IF(A58<='Results & Charts'!$C$5,"In-sample","Out-of-sample") -> In-sample | K58: =H58-'Results & Charts'!$C$9*I58 -> 0.016284992 | L58: =H58-I58 -> 0.016216458 | M58: 1.1139829 | N58: =H58-M58*I58 -> 0.016196243 | O58: ='Results & Charts'!$C$9 -> 0.61356738
A59: ='Roll Schedule'!A145 -> 45338 | B59: ='Roll Schedule'!A144 -> 45337 | C59: =SUMIFS('Spot Data'!$E$5:$E$651,'Spot Data'!$A$5:$A$651,B59,'Spot Data'!$H$5:$H$651,"YES") -> 6150 | D59: =SUMIFS('Spot Data'!$E$5:$E$651,'Spot Data'!$A$5:$A$651,A59,'Spot Data'!$H$5:$H$651,"YES") -> 6450 | E59: ='Roll Schedule'!B145 -> 45371 | F59: =SUMIFS('Futures Data'!$C$5:$C$3471,'Futures Data'!$A$5:$A$3471,B59,'Futures Data'!$B$5:$B$3471,E59) -> 5639 | G59: =SUMIFS('Futures Data'!$C$5:$C$3471,'Futures Data'!$A$5:$A$3471,A59,'Futures Data'!$B$5:$B$3471,E59) -> 5638 | H59: =LN(D59/C59) -> 0.047628049 | I59: =LN(G59/F59) -> -0.00017735213 | J59: =IF(A59<='Results & Charts'!$C$5,"In-sample","Out-of-sample") -> In-sample | K59: =H59-'Results & Charts'!$C$9*I59 -> 0.047736866 | L59: =H59-I59 -> 0.047805401 | M59: 1.1789245 | N59: =H59-M59*I59 -> 0.047837134 | O59: ='Results & Charts'!$C$9 -> 0.61356738
A60: ='Roll Schedule'!A146 -> 45341 | B60: ='Roll Schedule'!A145 -> 45338 | C60: =SUMIFS('Spot Data'!$E$5:$E$651,'Spot Data'!$A$5:$A$651,B60,'Spot Data'!$H$5:$H$651,"YES") -> 6450 | D60: =SUMIFS('Spot Data'!$E$5:$E$651,'Spot Data'!$A$5:$A$651,A60,'Spot Data'!$H$5:$H$651,"YES") -> 6450 | E60: ='Roll Schedule'!B146 -> 45371 | F60: =SUMIFS('Futures Data'!$C$5:$C$3471,'Futures Data'!$A$5:$A$3471,B60,'Futures Data'!$B$5:$B$3471,E60) -> 5638 | G60: =SUMIFS('Futures Data'!$C$5:$C$3471,'Futures Data'!$A$5:$A$3471,A60,'Futures Data'!$B$5:$B$3471,E60) -> 5698 | H60: =LN(D60/C60) -> 0 | I60: =LN(G60/F60) -> 0.010585843 | J60: =IF(A60<='Results & Charts'!$C$5,"In-sample","Out-of-sample") -> In-sample | K60: =H60-'Results & Charts'!$C$9*I60 -> -0.0064951282 | L60: =H60-I60 -> -0.010585843 | M60: 1.239215 | N60: =H60-M60*I60 -> -0.013118136 | O60: ='Results & Charts'!$C$9 -> 0.61356738
A61: ='Roll Schedule'!A147 -> 45342 | B61: ='Roll Schedule'!A146 -> 45341 | C61: =SUMIFS('Spot Data'!$E$5:$E$651,'Spot Data'!$A$5:$A$651,B61,'Spot Data'!$H$5:$H$651,"YES") -> 6450 | D61: =SUMIFS('Spot Data'!$E$5:$E$651,'Spot Data'!$A$5:$A$651,A61,'Spot Data'!$H$5:$H$651,"YES") -> 6500 | E61: ='Roll Schedule'!B147 -> 45371 | F61: =SUMIFS('Futures Data'!$C$5:$C$3471,'Futures Data'!$A$5:$A$3471,B61,'Futures Data'!$B$5:$B$3471,E61) -> 5698 | G61: =SUMIFS('Futures Data'!$C$5:$C$3471,'Futures Data'!$A$5:$A$3471,A61,'Futures Data'!$B$5:$B$3471,E61) -> 5708 | H61: =LN(D61/C61) -> 0.0077220461 | I61: =LN(G61/F61) -> 0.0017534635 | J61: =IF(A61<='Results & Charts'!$C$5,"In-sample","Out-of-sample") -> In-sample | K61: =H61-'Results & Charts'!$C$9*I61 -> 0.0066461781 | L61: =H61-I61 -> 0.0059685826 | M61: 1.0046586 | N61: =H61-M61*I61 -> 0.0059604138 | O61: ='Results & Charts'!$C$9 -> 0.61356738
A62: ='Roll Schedule'!A148 -> 45343 | B62: ='Roll Schedule'!A147 -> 45342 | C62: =SUMIFS('Spot Data'!$E$5:$E$651,'Spot Data'!$A$5:$A$651,B62,'Spot Data'!$H$5:$H$651,"YES") -> 6500 | D62: =SUMIFS('Spot Data'!$E$5:$E$651,'Spot Data'!$A$5:$A$651,A62,'Spot Data'!$H$5:$H$651,"YES") -> 6450 | E62: ='Roll Schedule'!B148 -> 45371 | F62: =SUMIFS('Futures Data'!$C$5:$C$3471,'Futures Data'!$A$5:$A$3471,B62,'Futures Data'!$B$5:$B$3471,E62) -> 5708 | G62: =SUMIFS('Futures Data'!$C$5:$C$3471,'Futures Data'!$A$5:$A$3471,A62,'Futures Data'!$B$5:$B$3471,E62) -> 5759 | H62: =LN(D62/C62) -> -0.0077220461 | I62: =LN(G62/F62) -> 0.0088951489 | J62: =IF(A62<='Results & Charts'!$C$5,"In-sample","Out-of-sample") -> In-sample | K62: =H62-'Results & Charts'!$C$9*I62 -> -0.013179819 | L62: =H62-I62 -> -0.016617195 | M62: 1.0601857 | N62: =H62-M62*I62 -> -0.017152555 | O62: ='Results & Charts'!$C$9 -> 0.61356738
A63: ='Roll Schedule'!A149 -> 45344 | B63: ='Roll Schedule'!A148 -> 45343 | C63: =SUMIFS('Spot Data'!$E$5:$E$651,'Spot Data'!$A$5:$A$651,B63,'Spot Data'!$H$5:$H$651,"YES") -> 6450 | D63: =SUMIFS('Spot Data'!$E$5:$E$651,'Spot Data'!$A$5:$A$651,A63,'Spot Data'!$H$5:$H$651,"YES") -> 6450 | E63: ='Roll Schedule'!B149 -> 45401 | F63: =SUMIFS('Futures Data'!$C$5:$C$3471,'Futures Data'!$A$5:$A$3471,B63,'Futures Data'!$B$5:$B$3471,E63) -> 5840 | G63: =SUMIFS('Futures Data'!$C$5:$C$3471,'Futures Data'!$A$5:$A$3471,A63,'Futures Data'!$B$5:$B$3471,E63) -> 5875 | H63: =LN(D63/C63) -> 0 | I63: =LN(G63/F63) -> 0.0059752632 | J63: =IF(A63<='Results & Charts'!$C$5,"In-sample","Out-of-sample") -> In-sample | K63: =H63-'Results & Charts'!$C$9*I63 -> -0.0036662266 | L63: =H63-I63 -> -0.0059752632 | M63: 0.91809698 | N63: =H63-M63*I63 -> -0.0054858711 | O63: ='Results & Charts'!$C$9 -> 0.61356738
A64: ='Roll Schedule'!A150 -> 45345 | B64: ='Roll Schedule'!A149 -> 45344 | C64: =SUMIFS('Spot Data'!$E$5:$E$651,'Spot Data'!$A$5:$A$651,B64,'Spot Data'!$H$5:$H$651,"YES") -> 6450 | D64: =SUMIFS('Spot Data'!$E$5:$E$651,'Spot Data'!$A$5:$A$651,A64,'Spot Data'!$H$5:$H$651,"YES") -> 6450 | E64: ='Roll Schedule'!B150 -> 45401 | F64: =SUMIFS('Futures Data'!$C$5:$C$3471,'Futures Data'!$A$5:$A$3471,B64,'Futures Data'!$B$5:$B$3471,E64) -> 5875 | G64: =SUMIFS('Futures Data'!$C$5:$C$3471,'Futures Data'!$A$5:$A$3471,A64,'Futures Data'!$B$5:$B$3471,E64) -> 5921 | H64: =LN(D64/C64) -> 0 | I64: =LN(G64/F64) -> 0.0077992935 | J64: =IF(A64<='Results & Charts'!$C$5,"In-sample","Out-of-sample") -> In-sample | K64: =H64-'Results & Charts'!$C$9*I64 -> -0.0047853921 | L64: =H64-I64 -> -0.0077992935 | M64: 0.90258494 | N64: =H64-M64*I64 -> -0.0070395248 | O64: ='Results & Charts'!$C$9 -> 0.61356738
A65: ='Roll Schedule'!A151 -> 45348 | B65: ='Roll Schedule'!A150 -> 45345 | C65: =SUMIFS('Spot Data'!$E$5:$E$651,'Spot Data'!$A$5:$A$651,B65,'Spot Data'!$H$5:$H$651,"YES") -> 6450 | D65: =SUMIFS('Spot Data'!$E$5:$E$651,'Spot Data'!$A$5:$A$651,A65,'Spot Data'!$H$5:$H$651,"YES") -> 6450 | E65: ='Roll Schedule'!B151 -> 45401 | F65: =SUMIFS('Futures Data'!$C$5:$C$3471,'Futures Data'!$A$5:$A$3471,B65,'Futures Data'!$B$5:$B$3471,E65) -> 5921 | G65: =SUMIFS('Futures Data'!$C$5:$C$3471,'Futures Data'!$A$5:$A$3471,A65,'Futures Data'!$B$5:$B$3471,E65) -> 5932 | H65: =LN(D65/C65) -> 0 | I65: =LN(G65/F65) -> 0.0018560707 | J65: =IF(A65<='Results & Charts'!$C$5,"In-sample","Out-of-sample") -> In-sample | K65: =H65-'Results & Charts'!$C$9*I65 -> -0.0011388245 | L65: =H65-I65 -> -0.0018560707 | M65: 0.84496863 | N65: =H65-M65*I65 -> -0.0015683215 | O65: ='Results & Charts'!$C$9 -> 0.61356738
A66: ='Roll Schedule'!A152 -> 45349 | B66: ='Roll Schedule'!A151 -> 45348 | C66: =SUMIFS('Spot Data'!$E$5:$E$651,'Spot Data'!$A$5:$A$651,B66,'Spot Data'!$H$5:$H$651,"YES") -> 6450 | D66: =SUMIFS('Spot Data'!$E$5:$E$651,'Spot Data'!$A$5:$A$651,A66,'Spot Data'!$H$5:$H$651,"YES") -> 6450 | E66: ='Roll Schedule'!B152 -> 45401 | F66: =SUMIFS('Futures Data'!$C$5:$C$3471,'Futures Data'!$A$5:$A$3471,B66,'Futures Data'!$B$5:$B$3471,E66) -> 5932 | G66: =SUMIFS('Futures Data'!$C$5:$C$3471,'Futures Data'!$A$5:$A$3471,A66,'Futures Data'!$B$5:$B$3471,E66) -> 5894 | H66: =LN(D66/C66) -> 0 | I66: =LN(G66/F66) -> -0.00642654 | J66: =IF(A66<='Results & Charts'!$C$5,"In-sample","Out-of-sample") -> In-sample | K66: =H66-'Results & Charts'!$C$9*I66 -> 0.0039431153 | L66: =H66-I66 -> 0.00642654 | M66: 0.89084326 | N66: =H66-M66*I66 -> 0.0057250398 | O66: ='Results & Charts'!$C$9 -> 0.61356738
A67: ='Roll Schedule'!A153 -> 45350 | B67: ='Roll Schedule'!A152 -> 45349 | C67: =SUMIFS('Spot Data'!$E$5:$E$651,'Spot Data'!$A$5:$A$651,B67,'Spot Data'!$H$5:$H$651,"YES") -> 6450 | D67: =SUMIFS('Spot Data'!$E$5:$E$651,'Spot Data'!$A$5:$A$651,A67,'Spot Data'!$H$5:$H$651,"YES") -> 6450 | E67: ='Roll Schedule'!B153 -> 45401 | F67: =SUMIFS('Futures Data'!$C$5:$C$3471,'Futures Data'!$A$5:$A$3471,B67,'Futures Data'!$B$5:$B$3471,E67) -> 5894 | G67: =SUMIFS('Futures Data'!$C$5:$C$3471,'Futures Data'!$A$5:$A$3471,A67,'Futures Data'!$B$5:$B$3471,E67) -> 5878 | H67: =LN(D67/C67) -> 0 | I67: =LN(G67/F67) -> -0.0027183163 | J67: =IF(A67<='Results & Charts'!$C$5,"In-sample","Out-of-sample") -> In-sample | K67: =H67-'Results & Charts'!$C$9*I67 -> 0.0016678702 | L67: =H67-I67 -> 0.0027183163 | M67: 0.8738371 | N67: =H67-M67*I67 -> 0.0023753656 | O67: ='Results & Charts'!$C$9 -> 0.61356738
A68: ='Roll Schedule'!A157 -> 45356 | B68: ='Roll Schedule'!A156 -> 45355 | C68: =SUMIFS('Spot Data'!$E$5:$E$651,'Spot Data'!$A$5:$A$651,B68,'Spot Data'!$H$5:$H$651,"YES") -> 6550 | D68: =SUMIFS('Spot Data'!$E$5:$E$651,'Spot Data'!$A$5:$A$651,A68,'Spot Data'!$H$5:$H$651,"YES") -> 6650 | E68: ='Roll Schedule'!B157 -> 45401 | F68: =SUMIFS('Futures Data'!$C$5:$C$3471,'Futures Data'!$A$5:$A$3471,B68,'Futures Data'!$B$5:$B$3471,E68) -> 5820 | G68: =SUMIFS('Futures Data'!$C$5:$C$3471,'Futures Data'!$A$5:$A$3471,A68,'Futures Data'!$B$5:$B$3471,E68) -> 5845 | H68: =LN(D68/C68) -> 0.015151805 | I68: =LN(G68/F68) -> 0.0042863332 | J68: =IF(A68<='Results & Charts'!$C$5,"In-sample","Out-of-sample") -> In-sample | K68: =H68-'Results & Charts'!$C$9*I68 -> 0.012521851 | L68: =H68-I68 -> 0.010865472 | M68: 0.91196159 | N68: =H68-M68*I68 -> 0.011242834 | O68: ='Results & Charts'!$C$9 -> 0.61356738
A69: ='Roll Schedule'!A160 -> 45362 | B69: ='Roll Schedule'!A159 -> 45358 | C69: =SUMIFS('Spot Data'!$E$5:$E$651,'Spot Data'!$A$5:$A$651,B69,'Spot Data'!$H$5:$H$651,"YES") -> 6600 | D69: =SUMIFS('Spot Data'!$E$5:$E$651,'Spot Data'!$A$5:$A$651,A69,'Spot Data'!$H$5:$H$651,"YES") -> 6650 | E69: ='Roll Schedule'!B160 -> 45401 | F69: =SUMIFS('Futures Data'!$C$5:$C$3471,'Futures Data'!$A$5:$A$3471,B69,'Futures Data'!$B$5:$B$3471,E69) -> 5847 | G69: =SUMIFS('Futures Data'!$C$5:$C$3471,'Futures Data'!$A$5:$A$3471,A69,'Futures Data'!$B$5:$B$3471,E69) -> 5857 | H69: =LN(D69/C69) -> 0.0075472056 | I69: =LN(G69/F69) -> 0.0017088179 | J69: =IF(A69<='Results & Charts'!$C$5,"In-sample","Out-of-sample") -> In-sample | K69: =H69-'Results & Charts'!$C$9*I69 -> 0.0064987307 | L69: =H69-I69 -> 0.0058383877 | M69: 0.94052981 | N69: =H69-M69*I69 -> 0.0059400115 | O69: ='Results & Charts'!$C$9 -> 0.61356738
A70: ='Roll Schedule'!A161 -> 45363 | B70: ='Roll Schedule'!A160 -> 45362 | C70: =SUMIFS('Spot Data'!$E$5:$E$651,'Spot Data'!$A$5:$A$651,B70,'Spot Data'!$H$5:$H$651,"YES") -> 6650 | D70: =SUMIFS('Spot Data'!$E$5:$E$651,'Spot Data'!$A$5:$A$651,A70,'Spot Data'!$H$5:$H$651,"YES") -> 6600 | E70: ='Roll Schedule'!B161 -> 45401 | F70: =SUMIFS('Futures Data'!$C$5:$C$3471,'Futures Data'!$A$5:$A$3471,B70,'Futures Data'!$B$5:$B$3471,E70) -> 5857 | G70: =SUMIFS('Futures Data'!$C$5:$C$3471,'Futures Data'!$A$5:$A$3471,A70,'Futures Data'!$B$5:$B$3471,E70) -> 5860 | H70: =LN(D70/C70) -> -0.0075472056 | I70: =LN(G70/F70) -> 0.00051207648 | J70: =IF(A70<='Results & Charts'!$C$5,"In-sample","Out-of-sample") -> In-sample | K70: =H70-'Results & Charts'!$C$9*I70 -> -0.0078613991 | L70: =H70-I70 -> -0.0080592821 | M70: 0.98117991 | N70: =H70-M70*I70 -> -0.0080496448 | O70: ='Results & Charts'!$C$9 -> 0.61356738
A71: ='Roll Schedule'!A162 -> 45364 | B71: ='Roll Schedule'!A161 -> 45363 | C71: =SUMIFS('Spot Data'!$E$5:$E$651,'Spot Data'!$A$5:$A$651,B71,'Spot Data'!$H$5:$H$651,"YES") -> 6600 | D71: =SUMIFS('Spot Data'!$E$5:$E$651,'Spot Data'!$A$5:$A$651,A71,'Spot Data'!$H$5:$H$651,"YES") -> 6650 | E71: ='Roll Schedule'!B162 -> 45401 | F71: =SUMIFS('Futures Data'!$C$5:$C$3471,'Futures Data'!$A$5:$A$3471,B71,'Futures Data'!$B$5:$B$3471,E71) -> 5860 | G71: =SUMIFS('Futures Data'!$C$5:$C$3471,'Futures Data'!$A$5:$A$3471,A71,'Futures Data'!$B$5:$B$3471,E71) -> 5907 | H71: =LN(D71/C71) -> 0.0075472056 | I71: =LN(G71/F71) -> 0.0079884847 | J71: =IF(A71<='Results & Charts'!$C$5,"In-sample","Out-of-sample") -> In-sample | K71: =H71-'Results & Charts'!$C$9*I71 -> 0.002645732 | L71: =H71-I71 -> -0.0004412791 | M71: 1.0152664 | N71: =H71-M71*I71 -> -0.00056323468 | O71: ='Results & Charts'!$C$9 -> 0.61356738
A72: ='Roll Schedule'!A163 -> 45365 | B72: ='Roll Schedule'!A162 -> 45364 | C72: =SUMIFS('Spot Data'!$E$5:$E$651,'Spot Data'!$A$5:$A$651,B72,'Spot Data'!$H$5:$H$651,"YES") -> 6650 | D72: =SUMIFS('Spot Data'!$E$5:$E$651,'Spot Data'!$A$5:$A$651,A72,'Spot Data'!$H$5:$H$651,"YES") -> 6600 | E72: ='Roll Schedule'!B163 -> 45401 | F72: =SUMIFS('Futures Data'!$C$5:$C$3471,'Futures Data'!$A$5:$A$3471,B72,'Futures Data'!$B$5:$B$3471,E72) -> 5907 | G72: =SUMIFS('Futures Data'!$C$5:$C$3471,'Futures Data'!$A$5:$A$3471,A72,'Futures Data'!$B$5:$B$3471,E72) -> 5926 | H72: =LN(D72/C72) -> -0.0075472056 | I72: =LN(G72/F72) -> 0.0032113608 | J72: =IF(A72<='Results & Charts'!$C$5,"In-sample","Out-of-sample") -> In-sample | K72: =H72-'Results & Charts'!$C$9*I72 -> -0.0095175919 | L72: =H72-I72 -> -0.010758566 | M72: 0.91483566 | N72: =H72-M72*I72 -> -0.010485073 | O72: ='Results & Charts'!$C$9 -> 0.61356738
A73: ='Roll Schedule'!A164 -> 45366 | B73: ='Roll Schedule'!A163 -> 45365 | C73: =SUMIFS('Spot Data'!$E$5:$E$651,'Spot Data'!$A$5:$A$651,B73,'Spot Data'!$H$5:$H$651,"YES") -> 6600 | D73: =SUMIFS('Spot Data'!$E$5:$E$651,'Spot Data'!$A$5:$A$651,A73,'Spot Data'!$H$5:$H$651,"YES") -> 6350 | E73: ='Roll Schedule'!B164 -> 45401 | F73: =SUMIFS('Futures Data'!$C$5:$C$3471,'Futures Data'!$A$5:$A$3471,B73,'Futures Data'!$B$5:$B$3471,E73) -> 5926 | G73: =SUMIFS('Futures Data'!$C$5:$C$3471,'Futures Data'!$A$5:$A$3471,A73,'Futures Data'!$B$5:$B$3471,E73) -> 5892 | H73: =LN(D73/C73) -> -0.038614836 | I73: =LN(G73/F73) -> -0.0057539506 | J73: =IF(A73<='Results & Charts'!$C$5,"In-sample","Out-of-sample") -> In-sample | K73: =H73-'Results & Charts'!$C$9*I73 -> -0.0350844 | L73: =H73-I73 -> -0.032860886 | M73: 0.91737488 | N73: =H73-M73*I73 -> -0.033336306 | O73: ='Results & Charts'!$C$9 -> 0.61356738
A74: ='Roll Schedule'!A165 -> 45369 | B74: ='Roll Schedule'!A164 -> 45366 | C74: =SUMIFS('Spot Data'!$E$5:$E$651,'Spot Data'!$A$5:$A$651,B74,'Spot Data'!$H$5:$H$651,"YES") -> 6350 | D74: =SUMIFS('Spot Data'!$E$5:$E$651,'Spot Data'!$A$5:$A$651,A74,'Spot Data'!$H$5:$H$651,"YES") -> 6250 | E74: ='Roll Schedule'!B165 -> 45401 | F74: =SUMIFS('Futures Data'!$C$5:$C$3471,'Futures Data'!$A$5:$A$3471,B74,'Futures Data'!$B$5:$B$3471,E74) -> 5892 | G74: =SUMIFS('Futures Data'!$C$5:$C$3471,'Futures Data'!$A$5:$A$3471,A74,'Futures Data'!$B$5:$B$3471,E74) -> 5897 | H74: =LN(D74/C74) -> -0.015873349 | I74: =LN(G74/F74) -> 0.00084824842 | J74: =IF(A74<='Results & Charts'!$C$5,"In-sample","Out-of-sample") -> In-sample | K74: =H74-'Results & Charts'!$C$9*I74 -> -0.016393807 | L74: =H74-I74 -> -0.016721598 | M74: 0.97590473 | N74: =H74-M74*I74 -> -0.016701159 | O74: ='Results & Charts'!$C$9 -> 0.61356738
A75: ='Roll Schedule'!A166 -> 45370 | B75: ='Roll Schedule'!A165 -> 45369 | C75: =SUMIFS('Spot Data'!$E$5:$E$651,'Spot Data'!$A$5:$A$651,B75,'Spot Data'!$H$5:$H$651,"YES") -> 6250 | D75: =SUMIFS('Spot Data'!$E$5:$E$651,'Spot Data'!$A$5:$A$651,A75,'Spot Data'!$H$5:$H$651,"YES") -> 6350 | E75: ='Roll Schedule'!B166 -> 45401 | F75: =SUMIFS('Futures Data'!$C$5:$C$3471,'Futures Data'!$A$5:$A$3471,B75,'Futures Data'!$B$5:$B$3471,E75) -> 5897 | G75: =SUMIFS('Futures Data'!$C$5:$C$3471,'Futures Data'!$A$5:$A$3471,A75,'Futures Data'!$B$5:$B$3471,E75) -> 5991 | H75: =LN(D75/C75) -> 0.015873349 | I75: =LN(G75/F75) -> 0.015814596 | J75: =IF(A75<='Results & Charts'!$C$5,"In-sample","Out-of-sample") -> In-sample | K75: =H75-'Results & Charts'!$C$9*I75 -> 0.0061700288 | L75: =H75-I75 -> 5.8753073e-05 | M75: 1.002873 | N75: =H75-M75*I75 -> 1.3318373e-05 | O75: ='Results & Charts'!$C$9 -> 0.61356738
A76: ='Roll Schedule'!A169 -> 45373 | B76: ='Roll Schedule'!A168 -> 45372 | C76: =SUMIFS('Spot Data'!$E$5:$E$651,'Spot Data'!$A$5:$A$651,B76,'Spot Data'!$H$5:$H$651,"YES") -> 6350 | D76: =SUMIFS('Spot Data'!$E$5:$E$651,'Spot Data'!$A$5:$A$651,A76,'Spot Data'!$H$5:$H$651,"YES") -> 6450 | E76: ='Roll Schedule'!B169 -> 45401 | F76: =SUMIFS('Futures Data'!$C$5:$C$3471,'Futures Data'!$A$5:$A$3471,B76,'Futures Data'!$B$5:$B$3471,E76) -> 6100 | G76: =SUMIFS('Futures Data'!$C$5:$C$3471,'Futures Data'!$A$5:$A$3471,A76,'Futures Data'!$B$5:$B$3471,E76) -> 6138 | H76: =LN(D76/C76) -> 0.015625318 | I76: =LN(G76/F76) -> 0.006210185 | J76: =IF(A76<='Results & Charts'!$C$5,"In-sample","Out-of-sample") -> In-sample | K76: =H76-'Results & Charts'!$C$9*I76 -> 0.011814951 | L76: =H76-I76 -> 0.0094151329 | M76: 0.69333537 | N76: =H76-M76*I76 -> 0.011319577 | O76: ='Results & Charts'!$C$9 -> 0.61356738
A77: ='Roll Schedule'!A172 -> 45379 | B77: ='Roll Schedule'!A171 -> 45378 | C77: =SUMIFS('Spot Data'!$E$5:$E$651,'Spot Data'!$A$5:$A$651,B77,'Spot Data'!$H$5:$H$651,"YES") -> 6350 | D77: =SUMIFS('Spot Data'!$E$5:$E$651,'Spot Data'!$A$5:$A$651,A77,'Spot Data'!$H$5:$H$651,"YES") -> 6350 | E77: ='Roll Schedule'!B172 -> 45401 | F77: =SUMIFS('Futures Data'!$C$5:$C$3471,'Futures Data'!$A$5:$A$3471,B77,'Futures Data'!$B$5:$B$3471,E77) -> 6072 | G77: =SUMIFS('Futures Data'!$C$5:$C$3471,'Futures Data'!$A$5:$A$3471,A77,'Futures Data'!$B$5:$B$3471,E77) -> 6050 | H77: =LN(D77/C77) -> 0 | I77: =LN(G77/F77) -> -0.0036297681 | J77: =IF(A77<='Results & Charts'!$C$5,"In-sample","Out-of-sample") -> In-sample | K77: =H77-'Results & Charts'!$C$9*I77 -> 0.0022271073 | L77: =H77-I77 -> 0.0036297681 | M77: 0.72599013 | N77: =H77-M77*I77 -> 0.0026351758 | O77: ='Results & Charts'!$C$9 -> 0.61356738
A78: ='Roll Schedule'!A173 -> 45383 | B78: ='Roll Schedule'!A172 -> 45379 | C78: =SUMIFS('Spot Data'!$E$5:$E$651,'Spot Data'!$A$5:$A$651,B78,'Spot Data'!$H$5:$H$651,"YES") -> 6350 | D78: =SUMIFS('Spot Data'!$E$5:$E$651,'Spot Data'!$A$5:$A$651,A78,'Spot Data'!$H$5:$H$651,"YES") -> 6250 | E78: ='Roll Schedule'!B173 -> 45401 | F78: =SUMIFS('Futures Data'!$C$5:$C$3471,'Futures Data'!$A$5:$A$3471,B78,'Futures Data'!$B$5:$B$3471,E78) -> 6050 | G78: =SUMIFS('Futures Data'!$C$5:$C$3471,'Futures Data'!$A$5:$A$3471,A78,'Futures Data'!$B$5:$B$3471,E78) -> 6009 | H78: =LN(D78/C78) -> -0.015873349 | I78: =LN(G78/F78) -> -0.0067999267 | J78: =IF(A78<='Results & Charts'!$C$5,"In-sample","Out-of-sample") -> In-sample | K78: =H78-'Results & Charts'!$C$9*I78 -> -0.011701136 | L78: =H78-I78 -> -0.0090734225 | M78: 0.76539437 | N78: =H78-M78*I78 -> -0.010668724 | O78: ='Results & Charts'!$C$9 -> 0.61356738
A79: ='Roll Schedule'!A174 -> 45384 | B79: ='Roll Schedule'!A173 -> 45383 | C79: =SUMIFS('Spot Data'!$E$5:$E$651,'Spot Data'!$A$5:$A$651,B79,'Spot Data'!$H$5:$H$651,"YES") -> 6250 | D79: =SUMIFS('Spot Data'!$E$5:$E$651,'Spot Data'!$A$5:$A$651,A79,'Spot Data'!$H$5:$H$651,"YES") -> 6250 | E79: ='Roll Schedule'!B174 -> 45401 | F79: =SUMIFS('Futures Data'!$C$5:$C$3471,'Futures Data'!$A$5:$A$3471,B79,'Futures Data'!$B$5:$B$3471,E79) -> 6009 | G79: =SUMIFS('Futures Data'!$C$5:$C$3471,'Futures Data'!$A$5:$A$3471,A79,'Futures Data'!$B$5:$B$3471,E79) -> 5979 | H79: =LN(D79/C79) -> 0 | I79: =LN(G79/F79) -> -0.0050050155 | J79: =IF(A79<='Results & Charts'!$C$5,"In-sample","Out-of-sample") -> In-sample | K79: =H79-'Results & Charts'!$C$9*I79 -> 0.0030709142 | L79: =H79-I79 -> 0.0050050155 | M79: 0.7894302 | N79: =H79-M79*I79 -> 0.0039511104 | O79: ='Results & Charts'!$C$9 -> 0.61356738
A80: ='Roll Schedule'!A175 -> 45385 | B80: ='Roll Schedule'!A174 -> 45384 | C80: =SUMIFS('Spot Data'!$E$5:$E$651,'Spot Data'!$A$5:$A$651,B80,'Spot Data'!$H$5:$H$651,"YES") -> 6250 | D80: =SUMIFS('Spot Data'!$E$5:$E$651,'Spot Data'!$A$5:$A$651,A80,'Spot Data'!$H$5:$H$651,"YES") -> 6250 | E80: ='Roll Schedule'!B175 -> 45401 | F80: =SUMIFS('Futures Data'!$C$5:$C$3471,'Futures Data'!$A$5:$A$3471,B80,'Futures Data'!$B$5:$B$3471,E80) -> 5979 | G80: =SUMIFS('Futures Data'!$C$5:$C$3471,'Futures Data'!$A$5:$A$3471,A80,'Futures Data'!$B$5:$B$3471,E80) -> 6026 | H80: =LN(D80/C80) -> 0 | I80: =LN(G80/F80) -> 0.0078301108 | J80: =IF(A80<='Results & Charts'!$C$5,"In-sample","Out-of-sample") -> In-sample | K80: =H80-'Results & Charts'!$C$9*I80 -> -0.0048043006 | L80: =H80-I80 -> -0.0078301108 | M80: 0.80755374 | N80: =H80-M80*I80 -> -0.0063232353 | O80: ='Results & Charts'!$C$9 -> 0.61356738
A81: ='Roll Schedule'!A176 -> 45386 | B81: ='Roll Schedule'!A175 -> 45385 | C81: =SUMIFS('Spot Data'!$E$5:$E$651,'Spot Data'!$A$5:$A$651,B81,'Spot Data'!$H$5:$H$651,"YES") -> 6250 | D81: =SUMIFS('Spot Data'!$E$5:$E$651,'Spot Data'!$A$5:$A$651,A81,'Spot Data'!$H$5:$H$651,"YES") -> 6350 | E81: ='Roll Schedule'!B176 -> 45401 | F81: =SUMIFS('Futures Data'!$C$5:$C$3471,'Futures Data'!$A$5:$A$3471,B81,'Futures Data'!$B$5:$B$3471,E81) -> 6026 | G81: =SUMIFS('Futures Data'!$C$5:$C$3471,'Futures Data'!$A$5:$A$3471,A81,'Futures Data'!$B$5:$B$3471,E81) -> 6081 | H81: =LN(D81/C81) -> 0.015873349 | I81: =LN(G81/F81) -> 0.0090857154 | J81: =IF(A81<='Results & Charts'!$C$5,"In-sample","Out-of-sample") -> In-sample | K81: =H81-'Results & Charts'!$C$9*I81 -> 0.010298651 | L81: =H81-I81 -> 0.0067876337 | M81: 0.75632122 | N81: =H81-M81*I81 -> 0.0090016298 | O81: ='Results & Charts'!$C$9 -> 0.61356738
A82: ='Roll Schedule'!A177 -> 45387 | B82: ='Roll Schedule'!A176 -> 45386 | C82: =SUMIFS('Spot Data'!$E$5:$E$651,'Spot Data'!$A$5:$A$651,B82,'Spot Data'!$H$5:$H$651,"YES") -> 6350 | D82: =SUMIFS('Spot Data'!$E$5:$E$651,'Spot Data'!$A$5:$A$651,A82,'Spot Data'!$H$5:$H$651,"YES") -> 6350 | E82: ='Roll Schedule'!B177 -> 45401 | F82: =SUMIFS('Futures Data'!$C$5:$C$3471,'Futures Data'!$A$5:$A$3471,B82,'Futures Data'!$B$5:$B$3471,E82) -> 6081 | G82: =SUMIFS('Futures Data'!$C$5:$C$3471,'Futures Data'!$A$5:$A$3471,A82,'Futures Data'!$B$5:$B$3471,E82) -> 6028 | H82: =LN(D82/C82) -> 0 | I82: =LN(G82/F82) -> -0.0087538754 | J82: =IF(A82<='Results & Charts'!$C$5,"In-sample","Out-of-sample") -> In-sample | K82: =H82-'Results & Charts'!$C$9*I82 -> 0.0053710924 | L82: =H82-I82 -> 0.0087538754 | M82: 0.73306522 | N82: =H82-M82*I82 -> 0.0064171616 | O82: ='Results & Charts'!$C$9 -> 0.61356738
A83: ='Roll Schedule'!A178 -> 45390 | B83: ='Roll Schedule'!A177 -> 45387 | C83: =SUMIFS('Spot Data'!$E$5:$E$651,'Spot Data'!$A$5:$A$651,B83,'Spot Data'!$H$5:$H$651,"YES") -> 6350 | D83: =SUMIFS('Spot Data'!$E$5:$E$651,'Spot Data'!$A$5:$A$651,A83,'Spot Data'!$H$5:$H$651,"YES") -> 6250 | E83: ='Roll Schedule'!B178 -> 45401 | F83: =SUMIFS('Futures Data'!$C$5:$C$3471,'Futures Data'!$A$5:$A$3471,B83,'Futures Data'!$B$5:$B$3471,E83) -> 6028 | G83: =SUMIFS('Futures Data'!$C$5:$C$3471,'Futures Data'!$A$5:$A$3471,A83,'Futures Data'!$B$5:$B$3471,E83) -> 5931 | H83: =LN(D83/C83) -> -0.015873349 | I83: =LN(G83/F83) -> -0.016222448 | J83: =IF(A83<='Results & Charts'!$C$5,"In-sample","Out-of-sample") -> In-sample | K83: =H83-'Results & Charts'!$C$9*I83 -> -0.0059197843 | L83: =H83-I83 -> 0.00034909875 | M83: 0.69539895 | N83: =H83-M83*I83 -> -0.0045922759 | O83: ='Results & Charts'!$C$9 -> 0.61356738
A84: ='Roll Schedule'!A182 -> 45397 | B84: ='Roll Schedule'!A181 -> 45394 | C84: =SUMIFS('Spot Data'!$E$5:$E$651,'Spot Data'!$A$5:$A$651,B84,'Spot Data'!$H$5:$H$651,"YES") -> 6250 | D84: =SUMIFS('Spot Data'!$E$5:$E$651,'Spot Data'!$A$5:$A$651,A84,'Spot Data'!$H$5:$H$651,"YES") -> 6250 | E84: ='Roll Schedule'!B182 -> 45432 | F84: =SUMIFS('Futures Data'!$C$5:$C$3471,'Futures Data'!$A$5:$A$3471,B84,'Futures Data'!$B$5:$B$3471,E84) -> 5902 | G84: =SUMIFS('Futures Data'!$C$5:$C$3471,'Futures Data'!$A$5:$A$3471,A84,'Futures Data'!$B$5:$B$3471,E84) -> 5823 | H84: =LN(D84/C84) -> 0 | I84: =LN(G84/F84) -> -0.013475684 | J84: =IF(A84<='Results & Charts'!$C$5,"In-sample","Out-of-sample") -> In-sample | K84: =H84-'Results & Charts'!$C$9*I84 -> 0.00826824 | L84: =H84-I84 -> 0.013475684 | M84: 0.57011576 | N84: =H84-M84*I84 -> 0.0076826996 | O84: ='Results & Charts'!$C$9 -> 0.61356738
A85: ='Roll Schedule'!A183 -> 45398 | B85: ='Roll Schedule'!A182 -> 45397 | C85: =SUMIFS('Spot Data'!$E$5:$E$651,'Spot Data'!$A$5:$A$651,B85,'Spot Data'!$H$5:$H$651,"YES") -> 6250 | D85: =SUMIFS('Spot Data'!$E$5:$E$651,'Spot Data'!$A$5:$A$651,A85,'Spot Data'!$H$5:$H$651,"YES") -> 6150 | E85: ='Roll Schedule'!B183 -> 45432 | F85: =SUMIFS('Futures Data'!$C$5:$C$3471,'Futures Data'!$A$5:$A$3471,B85,'Futures Data'!$B$5:$B$3471,E85) -> 5823 | G85: =SUMIFS('Futures Data'!$C$5:$C$3471,'Futures Data'!$A$5:$A$3471,A85,'Futures Data'!$B$5:$B$3471,E85) -> 5802 | H85: =LN(D85/C85) -> -0.016129382 | I85: =LN(G85/F85) -> -0.0036129072 | J85: =IF(A85<='Results & Charts'!$C$5,"In-sample","Out-of-sample") -> In-sample | K85: =H85-'Results & Charts'!$C$9*I85 -> -0.01391262 | L85: =H85-I85 -> -0.012516475 | M85: 0.50226083 | N85: =H85-M85*I85 -> -0.01431476 | O85: ='Results & Charts'!$C$9 -> 0.61356738
A86: ='Roll Schedule'!A184 -> 45400 | B86: ='Roll Schedule'!A183 -> 45398 | C86: =SUMIFS('Spot Data'!$E$5:$E$651,'Spot Data'!$A$5:$A$651,B86,'Spot Data'!$H$5:$H$651,"YES") -> 6150 | D86: =SUMIFS('Spot Data'!$E$5:$E$651,'Spot Data'!$A$5:$A$651,A86,'Spot Data'!$H$5:$H$651,"YES") -> 6150 | E86: ='Roll Schedule'!B184 -> 45432 | F86: =SUMIFS('Futures Data'!$C$5:$C$3471,'Futures Data'!$A$5:$A$3471,B86,'Futures Data'!$B$5:$B$3471,E86) -> 5802 | G86: =SUMIFS('Futures Data'!$C$5:$C$3471,'Futures Data'!$A$5:$A$3471,A86,'Futures Data'!$B$5:$B$3471,E86) -> 5806 | H86: =LN(D86/C86) -> 0 | I86: =LN(G86/F86) -> 0.0006891799 | J86: =IF(A86<='Results & Charts'!$C$5,"In-sample","Out-of-sample") -> In-sample | K86: =H86-'Results & Charts'!$C$9*I86 -> -0.00042285831 | L86: =H86-I86 -> -0.0006891799 | M86: 0.55638995 | N86: =H86-M86*I86 -> -0.00038345277 | O86: ='Results & Charts'!$C$9 -> 0.61356738
A87: ='Roll Schedule'!A187 -> 45405 | B87: ='Roll Schedule'!A186 -> 45404 | C87: =SUMIFS('Spot Data'!$E$5:$E$651,'Spot Data'!$A$5:$A$651,B87,'Spot Data'!$H$5:$H$651,"YES") -> 6150 | D87: =SUMIFS('Spot Data'!$E$5:$E$651,'Spot Data'!$A$5:$A$651,A87,'Spot Data'!$H$5:$H$651,"YES") -> 6150 | E87: ='Roll Schedule'!B187 -> 45432 | F87: =SUMIFS('Futures Data'!$C$5:$C$3471,'Futures Data'!$A$5:$A$3471,B87,'Futures Data'!$B$5:$B$3471,E87) -> 5806 | G87: =SUMIFS('Futures Data'!$C$5:$C$3471,'Futures Data'!$A$5:$A$3471,A87,'Futures Data'!$B$5:$B$3471,E87) -> 5810 | H87: =LN(D87/C87) -> 0 | I87: =LN(G87/F87) -> 0.00068870526 | J87: =IF(A87<='Results & Charts'!$C$5,"In-sample","Out-of-sample") -> In-sample | K87: =H87-'Results & Charts'!$C$9*I87 -> -0.00042256708 | L87: =H87-I87 -> -0.00068870526 | M87: 0.60709218 | N87: =H87-M87*I87 -> -0.00041810758 | O87: ='Results & Charts'!$C$9 -> 0.61356738
A88: ='Roll Schedule'!A188 -> 45406 | B88: ='Roll Schedule'!A187 -> 45405 | C88: =SUMIFS('Spot Data'!$E$5:$E$651,'Spot Data'!$A$5:$A$651,B88,'Spot Data'!$H$5:$H$651,"YES") -> 6150 | D88: =SUMIFS('Spot Data'!$E$5:$E$651,'Spot Data'!$A$5:$A$651,A88,'Spot Data'!$H$5:$H$651,"YES") -> 6050 | E88: ='Roll Schedule'!B188 -> 45432 | F88: =SUMIFS('Futures Data'!$C$5:$C$3471,'Futures Data'!$A$5:$A$3471,B88,'Futures Data'!$B$5:$B$3471,E88) -> 5810 | G88: =SUMIFS('Futures Data'!$C$5:$C$3471,'Futures Data'!$A$5:$A$3471,A88,'Futures Data'!$B$5:$B$3471,E88) -> 5780 | H88: =LN(D88/C88) -> -0.01639381 | I88: =LN(G88/F88) -> -0.0051768882 | J88: =IF(A88<='Results & Charts'!$C$5,"In-sample","Out-of-sample") -> In-sample | K88: =H88-'Results & Charts'!$C$9*I88 -> -0.01321744 | L88: =H88-I88 -> -0.011216922 | M88: 0.65753783 | N88: =H88-M88*I88 -> -0.01298981 | O88: ='Results & Charts'!$C$9 -> 0.61356738
A89: ='Roll Schedule'!A189 -> 45407 | B89: ='Roll Schedule'!A188 -> 45406 | C89: =SUMIFS('Spot Data'!$E$5:$E$651,'Spot Data'!$A$5:$A$651,B89,'Spot Data'!$H$5:$H$651,"YES") -> 6050 | D89: =SUMIFS('Spot Data'!$E$5:$E$651,'Spot Data'!$A$5:$A$651,A89,'Spot Data'!$H$5:$H$651,"YES") -> 6050 | E89: ='Roll Schedule'!B189 -> 45432 | F89: =SUMIFS('Futures Data'!$C$5:$C$3471,'Futures Data'!$A$5:$A$3471,B89,'Futures Data'!$B$5:$B$3471,E89) -> 5780 | G89: =SUMIFS('Futures Data'!$C$5:$C$3471,'Futures Data'!$A$5:$A$3471,A89,'Futures Data'!$B$5:$B$3471,E89) -> 5787 | H89: =LN(D89/C89) -> 0 | I89: =LN(G89/F89) -> 0.0012103399 | J89: =IF(A89<='Results & Charts'!$C$5,"In-sample","Out-of-sample") -> In-sample | K89: =H89-'Results & Charts'!$C$9*I89 -> -0.00074262509 | L89: =H89-I89 -> -0.0012103399 | M89: 0.70365984 | N89: =H89-M89*I89 -> -0.00085166758 | O89: ='Results & Charts'!$C$9 -> 0.61356738
A90: ='Roll Schedule'!A190 -> 45408 | B90: ='Roll Schedule'!A189 -> 45407 | C90: =SUMIFS('Spot Data'!$E$5:$E$651,'Spot Data'!$A$5:$A$651,B90,'Spot Data'!$H$5:$H$651,"YES") -> 6050 | D90: =SUMIFS('Spot Data'!$E$5:$E$651,'Spot Data'!$A$5:$A$651,A90,'Spot Data'!$H$5:$H$651,"YES") -> 6050 | E90: ='Roll Schedule'!B190 -> 45432 | F90: =SUMIFS('Futures Data'!$C$5:$C$3471,'Futures Data'!$A$5:$A$3471,B90,'Futures Data'!$B$5:$B$3471,E90) -> 5787 | G90: =SUMIFS('Futures Data'!$C$5:$C$3471,'Futures Data'!$A$5:$A$3471,A90,'Futures Data'!$B$5:$B$3471,E90) -> 5754 | H90: =LN(D90/C90) -> 0 | I90: =LN(G90/F90) -> -0.0057187575 | J90: =IF(A90<='Results & Charts'!$C$5,"In-sample","Out-of-sample") -> In-sample | K90: =H90-'Results & Charts'!$C$9*I90 -> 0.003508843 | L90: =H90-I90 -> 0.0057187575 | M90: 0.75064321 | N90: =H90-M90*I90 -> 0.0042927465 | O90: ='Results & Charts'!$C$9 -> 0.61356738
A91: ='Roll Schedule'!A341 -> 45631 | B91: ='Roll Schedule'!A340 -> 45630 | C91: =SUMIFS('Spot Data'!$E$5:$E$651,'Spot Data'!$A$5:$A$651,B91,'Spot Data'!$H$5:$H$651,"YES") -> 6800 | D91: =SUMIFS('Spot Data'!$E$5:$E$651,'Spot Data'!$A$5:$A$651,A91,'Spot Data'!$H$5:$H$651,"YES") -> 6750 | E91: ='Roll Schedule'!B341 -> 45646 | F91: =SUMIFS('Futures Data'!$C$5:$C$3471,'Futures Data'!$A$5:$A$3471,B91,'Futures Data'!$B$5:$B$3471,E91) -> 6479 | G91: =SUMIFS('Futures Data'!$C$5:$C$3471,'Futures Data'!$A$5:$A$3471,A91,'Futures Data'!$B$5:$B$3471,E91) -> 6390 | H91: =LN(D91/C91) -> -0.0073801073 | I91: =LN(G91/F91) -> -0.013831909 | J91: =IF(A91<='Results & Charts'!$C$5,"In-sample","Out-of-sample") -> In-sample | K91: =H91-'Results & Charts'!$C$9*I91 -> 0.0011067009 | L91: =H91-I91 -> 0.0064518018 | M91: 0.7546388 | N91: =H91-M91*I91 -> 0.003057988 | O91: ='Results & Charts'!$C$9 -> 0.61356738
A92: ='Roll Schedule'!A342 -> 45632 | B92: ='Roll Schedule'!A341 -> 45631 | C92: =SUMIFS('Spot Data'!$E$5:$E$651,'Spot Data'!$A$5:$A$651,B92,'Spot Data'!$H$5:$H$651,"YES") -> 6750 | D92: =SUMIFS('Spot Data'!$E$5:$E$651,'Spot Data'!$A$5:$A$651,A92,'Spot Data'!$H$5:$H$651,"YES") -> 6650 | E92: ='Roll Schedule'!B342 -> 45646 | F92: =SUMIFS('Futures Data'!$C$5:$C$3471,'Futures Data'!$A$5:$A$3471,B92,'Futures Data'!$B$5:$B$3471,E92) -> 6390 | G92: =SUMIFS('Futures Data'!$C$5:$C$3471,'Futures Data'!$A$5:$A$3471,A92,'Futures Data'!$B$5:$B$3471,E92) -> 6417 | H92: =LN(D92/C92) -> -0.01492565 | I92: =LN(G92/F92) -> 0.0042164504 | J92: =IF(A92<='Results & Charts'!$C$5,"In-sample","Out-of-sample") -> In-sample | K92: =H92-'Results & Charts'!$C$9*I92 -> -0.017512727 | L92: =H92-I92 -> -0.019142101 | M92: 0.60894859 | N92: =H92-M92*I92 -> -0.017493252 | O92: ='Results & Charts'!$C$9 -> 0.61356738
A93: ='Roll Schedule'!A343 -> 45635 | B93: ='Roll Schedule'!A342 -> 45632 | C93: =SUMIFS('Spot Data'!$E$5:$E$651,'Spot Data'!$A$5:$A$651,B93,'Spot Data'!$H$5:$H$651,"YES") -> 6650 | D93: =SUMIFS('Spot Data'!$E$5:$E$651,'Spot Data'!$A$5:$A$651,A93,'Spot Data'!$H$5:$H$651,"YES") -> 6650 | E93: ='Roll Schedule'!B343 -> 45646 | F93: =SUMIFS('Futures Data'!$C$5:$C$3471,'Futures Data'!$A$5:$A$3471,B93,'Futures Data'!$B$5:$B$3471,E93) -> 6417 | G93: =SUMIFS('Futures Data'!$C$5:$C$3471,'Futures Data'!$A$5:$A$3471,A93,'Futures Data'!$B$5:$B$3471,E93) -> 6383 | H93: =LN(D93/C93) -> 0 | I93: =LN(G93/F93) -> -0.0053125125 | J93: =IF(A93<='Results & Charts'!$C$5,"In-sample","Out-of-sample") -> In-sample | K93: =H93-'Results & Charts'!$C$9*I93 -> 0.0032595844 | L93: =H93-I93 -> 0.0053125125 | M93: 0.61655463 | N93: =H93-M93*I93 -> 0.0032754542 | O93: ='Results & Charts'!$C$9 -> 0.61356738
A94: ='Roll Schedule'!A344 -> 45636 | B94: ='Roll Schedule'!A343 -> 45635 | C94: =SUMIFS('Spot Data'!$E$5:$E$651,'Spot Data'!$A$5:$A$651,B94,'Spot Data'!$H$5:$H$651,"YES") -> 6650 | D94: =SUMIFS('Spot Data'!$E$5:$E$651,'Spot Data'!$A$5:$A$651,A94,'Spot Data'!$H$5:$H$651,"YES") -> 6650 | E94: ='Roll Schedule'!B344 -> 45646 | F94: =SUMIFS('Futures Data'!$C$5:$C$3471,'Futures Data'!$A$5:$A$3471,B94,'Futures Data'!$B$5:$B$3471,E94) -> 6383 | G94: =SUMIFS('Futures Data'!$C$5:$C$3471,'Futures Data'!$A$5:$A$3471,A94,'Futures Data'!$B$5:$B$3471,E94) -> 6294 | H94: =LN(D94/C94) -> 0 | I94: =LN(G94/F94) -> -0.014041408 | J94: =IF(A94<='Results & Charts'!$C$5,"In-sample","Out-of-sample") -> In-sample | K94: =H94-'Results & Charts'!$C$9*I94 -> 0.0086153497 | L94: =H94-I94 -> 0.014041408 | M94: 0.63515234 | N94: =H94-M94*I94 -> 0.0089184329 | O94: ='Results & Charts'!$C$9 -> 0.61356738
A95: ='Roll Schedule'!A345 -> 45637 | B95: ='Roll Schedule'!A344 -> 45636 | C95: =SUMIFS('Spot Data'!$E$5:$E$651,'Spot Data'!$A$5:$A$651,B95,'Spot Data'!$H$5:$H$651,"YES") -> 6650 | D95: =SUMIFS('Spot Data'!$E$5:$E$651,'Spot Data'!$A$5:$A$651,A95,'Spot Data'!$H$5:$H$651,"YES") -> 6750 | E95: ='Roll Schedule'!B345 -> 45677 | F95: =SUMIFS('Futures Data'!$C$5:$C$3471,'Futures Data'!$A$5:$A$3471,B95,'Futures Data'!$B$5:$B$3471,E95) -> 6368 | G95: =SUMIFS('Futures Data'!$C$5:$C$3471,'Futures Data'!$A$5:$A$3471,A95,'Futures Data'!$B$5:$B$3471,E95) -> 6346 | H95: =LN(D95/C95) -> 0.01492565 | I95: =LN(G95/F95) -> -0.0034607554 | J95: =IF(A95<='Results & Charts'!$C$5,"In-sample","Out-of-sample") -> In-sample | K95: =H95-'Results & Charts'!$C$9*I95 -> 0.017049057 | L95: =H95-I95 -> 0.018386406 | M95: 0.50300893 | N95: =H95-M95*I95 -> 0.016666441 | O95: ='Results & Charts'!$C$9 -> 0.61356738
A96: ='Roll Schedule'!A346 -> 45638 | B96: ='Roll Schedule'!A345 -> 45637 | C96: =SUMIFS('Spot Data'!$E$5:$E$651,'Spot Data'!$A$5:$A$651,B96,'Spot Data'!$H$5:$H$651,"YES") -> 6750 | D96: =SUMIFS('Spot Data'!$E$5:$E$651,'Spot Data'!$A$5:$A$651,A96,'Spot Data'!$H$5:$H$651,"YES") -> 6700 | E96: ='Roll Schedule'!B346 -> 45677 | F96: =SUMIFS('Futures Data'!$C$5:$C$3471,'Futures Data'!$A$5:$A$3471,B96,'Futures Data'!$B$5:$B$3471,E96) -> 6346 | G96: =SUMIFS('Futures Data'!$C$5:$C$3471,'Futures Data'!$A$5:$A$3471,A96,'Futures Data'!$B$5:$B$3471,E96) -> 6372 | H96: =LN(D96/C96) -> -0.0074349785 | I96: =LN(G96/F96) -> 0.0040886989 | J96: =IF(A96<='Results & Charts'!$C$5,"In-sample","Out-of-sample") -> In-sample | K96: =H96-'Results & Charts'!$C$9*I96 -> -0.0099436708 | L96: =H96-I96 -> -0.011523677 | M96: 0.52659788 | N96: =H96-M96*I96 -> -0.0095880787 | O96: ='Results & Charts'!$C$9 -> 0.61356738
A97: ='Roll Schedule'!A347 -> 45639 | B97: ='Roll Schedule'!A346 -> 45638 | C97: =SUMIFS('Spot Data'!$E$5:$E$651,'Spot Data'!$A$5:$A$651,B97,'Spot Data'!$H$5:$H$651,"YES") -> 6700 | D97: =SUMIFS('Spot Data'!$E$5:$E$651,'Spot Data'!$A$5:$A$651,A97,'Spot Data'!$H$5:$H$651,"YES") -> 6700 | E97: ='Roll Schedule'!B347 -> 45677 | F97: =SUMIFS('Futures Data'!$C$5:$C$3471,'Futures Data'!$A$5:$A$3471,B97,'Futures Data'!$B$5:$B$3471,E97) -> 6372 | G97: =SUMIFS('Futures Data'!$C$5:$C$3471,'Futures Data'!$A$5:$A$3471,A97,'Futures Data'!$B$5:$B$3471,E97) -> 6347 | H97: =LN(D97/C97) -> 0 | I97: =LN(G97/F97) -> -0.0039311317 | J97: =IF(A97<='Results & Charts'!$C$5,"In-sample","Out-of-sample") -> In-sample | K97: =H97-'Results & Charts'!$C$9*I97 -> 0.0024120142 | L97: =H97-I97 -> 0.0039311317 | M97: 0.54206035 | N97: =H97-M97*I97 -> 0.0021309106 | O97: ='Results & Charts'!$C$9 -> 0.61356738
A98: ='Roll Schedule'!A348 -> 45642 | B98: ='Roll Schedule'!A347 -> 45639 | C98: =SUMIFS('Spot Data'!$E$5:$E$651,'Spot Data'!$A$5:$A$651,B98,'Spot Data'!$H$5:$H$651,"YES") -> 6700 | D98: =SUMIFS('Spot Data'!$E$5:$E$651,'Spot Data'!$A$5:$A$651,A98,'Spot Data'!$H$5:$H$651,"YES") -> 6650 | E98: ='Roll Schedule'!B348 -> 45677 | F98: =SUMIFS('Futures Data'!$C$5:$C$3471,'Futures Data'!$A$5:$A$3471,B98,'Futures Data'!$B$5:$B$3471,E98) -> 6347 | G98: =SUMIFS('Futures Data'!$C$5:$C$3471,'Futures Data'!$A$5:$A$3471,A98,'Futures Data'!$B$5:$B$3471,E98) -> 6265 | H98: =LN(D98/C98) -> -0.0074906717 | I98: =LN(G98/F98) -> -0.013003672 | J98: =IF(A98<='Results & Charts'!$C$5,"In-sample","Out-of-sample") -> In-sample | K98: =H98-'Results & Charts'!$C$9*I98 -> 0.00048795725 | L98: =H98-I98 -> 0.0055130002 | M98: 0.57015874 | N98: =H98-M98*I98 -> -7.651445e-05 | O98: ='Results & Charts'!$C$9 -> 0.61356738
A99: ='Roll Schedule'!A349 -> 45643 | B99: ='Roll Schedule'!A348 -> 45642 | C99: =SUMIFS('Spot Data'!$E$5:$E$651,'Spot Data'!$A$5:$A$651,B99,'Spot Data'!$H$5:$H$651,"YES") -> 6650 | D99: =SUMIFS('Spot Data'!$E$5:$E$651,'Spot Data'!$A$5:$A$651,A99,'Spot Data'!$H$5:$H$651,"YES") -> 6600 | E99: ='Roll Schedule'!B349 -> 45677 | F99: =SUMIFS('Futures Data'!$C$5:$C$3471,'Futures Data'!$A$5:$A$3471,B99,'Futures Data'!$B$5:$B$3471,E99) -> 6265 | G99: =SUMIFS('Futures Data'!$C$5:$C$3471,'Futures Data'!$A$5:$A$3471,A99,'Futures Data'!$B$5:$B$3471,E99) -> 6246 | H99: =LN(D99/C99) -> -0.0075472056 | I99: =LN(G99/F99) -> -0.0030373295 | J99: =IF(A99<='Results & Charts'!$C$5,"In-sample","Out-of-sample") -> In-sample | K99: =H99-'Results & Charts'!$C$9*I99 -> -0.0056835993 | L99: =H99-I99 -> -0.0045098761 | M99: 0.49030312 | N99: =H99-M99*I99 -> -0.0060579935 | O99: ='Results & Charts'!$C$9 -> 0.61356738
A100: ='Roll Schedule'!A350 -> 45644 | B100: ='Roll Schedule'!A349 -> 45643 | C100: =SUMIFS('Spot Data'!$E$5:$E$651,'Spot Data'!$A$5:$A$651,B100,'Spot Data'!$H$5:$H$651,"YES") -> 6600 | D100: =SUMIFS('Spot Data'!$E$5:$E$651,'Spot Data'!$A$5:$A$651,A100,'Spot Data'!$H$5:$H$651,"YES") -> 6600 | E100: ='Roll Schedule'!B350 -> 45677 | F100: =SUMIFS('Futures Data'!$C$5:$C$3471,'Futures Data'!$A$5:$A$3471,B100,'Futures Data'!$B$5:$B$3471,E100) -> 6246 | G100: =SUMIFS('Futures Data'!$C$5:$C$3471,'Futures Data'!$A$5:$A$3471,A100,'Futures Data'!$B$5:$B$3471,E100) -> 6313 | H100: =LN(D100/C100) -> 0 | I100: =LN(G100/F100) -> 0.010669741 | J100: =IF(A100<='Results & Charts'!$C$5,"In-sample","Out-of-sample") -> In-sample | K100: =H100-'Results & Charts'!$C$9*I100 -> -0.0065466048 | L100: =H100-I100 -> -0.010669741 | M100: 0.53135773 | N100: =H100-M100*I100 -> -0.0056694491 | O100: ='Results & Charts'!$C$9 -> 0.61356738
A101: ='Roll Schedule'!A351 -> 45645 | B101: ='Roll Schedule'!A350 -> 45644 | C101: =SUMIFS('Spot Data'!$E$5:$E$651,'Spot Data'!$A$5:$A$651,B101,'Spot Data'!$H$5:$H$651,"YES") -> 6600 | D101: =SUMIFS('Spot Data'!$E$5:$E$651,'Spot Data'!$A$5:$A$651,A101,'Spot Data'!$H$5:$H$651,"YES") -> 6650 | E101: ='Roll Schedule'!B351 -> 45677 | F101: =SUMIFS('Futures Data'!$C$5:$C$3471,'Futures Data'!$A$5:$A$3471,B101,'Futures Data'!$B$5:$B$3471,E101) -> 6313 | G101: =SUMIFS('Futures Data'!$C$5:$C$3471,'Futures Data'!$A$5:$A$3471,A101,'Futures Data'!$B$5:$B$3471,E101) -> 6328 | H101: =LN(D101/C101) -> 0.0075472056 | I101: =LN(G101/F101) -> 0.0023732311 | J101: =IF(A101<='Results & Charts'!$C$5,"In-sample","Out-of-sample") -> In-sample | K101: =H101-'Results & Charts'!$C$9*I101 -> 0.0060910685 | L101: =H101-I101 -> 0.0051739746 | M101: 0.47176048 | N101: =H101-M101*I101 -> 0.006427609 | O101: ='Results & Charts'!$C$9 -> 0.61356738
...

Sheet Results & Charts
A1: Results & Charts: castor meal (SEA) hedged with NCDEX castor seed futures
K2: Charts: spot and futures are on separate charts because units differ (Rs/MT vs Rs/quintal) and levels are not comparable. Spot dots are the dates used in returns; SEA published no castor meal quote from 27 Apr to 3 Dec 2024. Futures steps at rolls are contract changes, not market moves.
A3: SAMPLE SPLIT (chronological, fixed before estimation)
A5: In-sample: returns up to and including | C5: 45930
A6: Check: formulas below use the rows that match this split | C6: =AND(COUNTIF('Daily Analysis'!J5:J279,"In-sample")=275,COUNTIF('Daily Analysis'!J280:J500,"Out-of-sample")=221) -> TRUE
A8: TABLE 1. OLS hedge, eq. (3): rA = a + h* rF + e (in-sample rows only)
A9: Hedge ratio h* = SLOPE(rA, rF) | C9: =SLOPE('Daily Analysis'!H5:H279,'Daily Analysis'!I5:I279) -> 0.61356738
A10: Intercept a | C10: =INTERCEPT('Daily Analysis'!H5:H279,'Daily Analysis'!I5:I279) -> -0.00032635527
A11: Standard error of h* | C11: =INDEX(LINEST('Daily Analysis'!H5:H279,'Daily Analysis'!I5:I279,TRUE(),TRUE()),2,1) -> 0.13755548
A12: t-statistic | C12: =C9/C11 -> 4.4605083
A13: R-squared | C13: =RSQ('Daily Analysis'!H5:H279,'Daily Analysis'!I5:I279) -> 0.067928977
A14: Correlation rA, rF | C14: =CORREL('Daily Analysis'!H5:H279,'Daily Analysis'!I5:I279) -> 0.26063188
A16: TABLE 2. Hedge effectiveness, eq. (13): HE = 1 - Var(hedged) / Var(unhedged); sample variances
A17: Model | B17: Hedge ratio | C17: Sample | D17: First return date | E17: Last return date | F17: Obs | G17: Var unhedged | H17: Var hedged | I17: HE
A18: OLS (h* fixed from in-sample) | B18: =C9 -> 0.61356738 | C18: In-sample | D18: =MIN('Daily Analysis'!A5:A279) -> 45195 | E18: =MAX('Daily Analysis'!A5:A279) -> 45926 | F18: =COUNT('Daily Analysis'!H5:H279) -> 275 | G18: =VAR('Daily Analysis'!H5:H279) -> 0.00025856373 | H18: =VAR('Daily Analysis'!K5:K279) -> 0.00024099976 | I18: =1-H18/G18 -> 0.067928977
A19: OLS (h* fixed from in-sample) | B19: =C9 -> 0.61356738 | C19: Out-of-sample | D19: =MIN('Daily Analysis'!A280:A500) -> 45931 | E19: =MAX('Daily Analysis'!A280:A500) -> 46293 | F19: =COUNT('Daily Analysis'!H280:H500) -> 221 | G19: =VAR('Daily Analysis'!H280:H500) -> 0.00025065151 | H19: =VAR('Daily Analysis'!K280:K500) -> 0.00023413894 | I19: =1-H19/G19 -> 0.065878581
A20: Naive (h = 1) | B20: 1 | C20: In-sample | D20: =MIN('Daily Analysis'!A5:A279) -> 45195 | E20: =MAX('Daily Analysis'!A5:A279) -> 45926 | F20: =COUNT('Daily Analysis'!H5:H279) -> 275 | G20: =VAR('Daily Analysis'!H5:H279) -> 0.00025856373 | H20: =VAR('Daily Analysis'!L5:L279) -> 0.00024796675 | I20: =1-H20/G20 -> 0.040983982
A21: Naive (h = 1) | B21: 1 | C21: Out-of-sample | D21: =MIN('Daily Analysis'!A280:A500) -> 45931 | E21: =MAX('Daily Analysis'!A280:A500) -> 46293 | F21: =COUNT('Daily Analysis'!H280:H500) -> 221 | G21: =VAR('Daily Analysis'!H280:H500) -> 0.00025065151 | H21: =VAR('Daily Analysis'!L280:L500) -> 0.00023997424 | I21: =1-H21/G21 -> 0.042598056
A22: Diagonal VECH GARCH (time-varying h_t) | B22: h_t | C22: In-sample | D22: =MIN('Daily Analysis'!A5:A279) -> 45195 | E22: =MAX('Daily Analysis'!A5:A279) -> 45926 | F22: =COUNT('Daily Analysis'!H5:H279) -> 275 | G22: =VAR('Daily Analysis'!H5:H279) -> 0.00025856373 | H22: =VAR('Daily Analysis'!N5:N279) -> 0.00024048914 | I22: =1-H22/G22 -> 0.069903783
A23: Diagonal VECH GARCH (time-varying h_t) | B23: h_t | C23: Out-of-sample | D23: =MIN('Daily Analysis'!A280:A500) -> 45931 | E23: =MAX('Daily Analysis'!A280:A500) -> 46293 | F23: =COUNT('Daily Analysis'!H280:H500) -> 221 | G23: =VAR('Daily Analysis'!H280:H500) -> 0.00025065151 | H23: =VAR('Daily Analysis'!N280:N500) -> 0.0002330506 | I23: =1-H23/G23 -> 0.070220655
A25: Chart data: HE by model | B25: In-sample | C25: Out-of-sample
A26: OLS | B26: =I18 -> 0.067928977 | C26: =I19 -> 0.065878581
A27: Naive | B27: =I20 -> 0.040983982 | C27: =I21 -> 0.042598056
A28: GARCH | B28: =I22 -> 0.069903783 | C28: =I23 -> 0.070220655
A30: TABLE 3. Risk-adjusted return = mean / SD (paper Table 5)
A31: Portfolio | C31: Mean/SD in-sample | D31: Mean/SD out-of-sample
A32: Unhedged | C32: =AVERAGE('Daily Analysis'!H5:H279)/STDEV('Daily Analysis'!H5:H279) -> -0.043761188 | D32: =AVERAGE('Daily Analysis'!H280:H500)/STDEV('Daily Analysis'!H280:H500) -> 0.058779334
A33: OLS hedged | C33: =AVERAGE('Daily Analysis'!K5:K279)/STDEV('Daily Analysis'!K5:K279) -> -0.021022402 | D33: =AVERAGE('Daily Analysis'!K280:K500)/STDEV('Daily Analysis'!K280:K500) -> 0.057260751
A34: Naive hedged | C34: =AVERAGE('Daily Analysis'!L5:L279)/STDEV('Daily Analysis'!L5:L279) -> -0.0056337005 | D34: =AVERAGE('Daily Analysis'!L280:L500)/STDEV('Daily Analysis'!L280:L500) -> 0.054348083
A35: GARCH hedged | C35: =AVERAGE('Daily Analysis'!N5:N279)/STDEV('Daily Analysis'!N5:N279) -> -0.029653956 | D35: =AVERAGE('Daily Analysis'!N280:N500)/STDEV('Daily Analysis'!N280:N500) -> 0.064742614
A37: TABLE 4. Diagonal VECH GARCH(1,1), eq. (4)-(8): Python maximum likelihood on in-sample returns only (values)
A38: H11 = C1 + A11 e1^2 + B11 H11(-1); H12 = C2 + A22 e1 e2 + B22 H12(-1); H22 = C3 + A33 e2^2 + B33 H22(-1); h_t = H12/H22. Constant means; no error-correction term (Table 5).
A39: Parameter | C39: Estimate | D39: Std. error
A40: mu_meal | C40: -0.067242996 | D40: 0.094378305
A41: mu_fut | C41: -0.04008154 | D41: 0.039792468
A42: C1 | C42: 0.31625254 | D42: 0.20047405
A43: C2 | C43: 0.0046760104 | D43: 0.0068593261
A44: C3 | C44: 0.036953935 | D44: 0.041300368
A45: A11 | C45: 0.085589838 | D45: 0.041482115
A46: A22 | C46: 0.014941638 | D46: 0.012562314
A47: A33 | C47: 0.082798545 | D47: 0.047255712
A48: B11 | C48: 0.7955952 | D48: 0.093046399
A49: B22 | C49: 0.95997041 | D49: 0.032273718
A50: B33 | C50: 0.83448611 | D50: 0.12328952
A51: Estimation: in-sample pairs only, then parameters fixed; 5/5 starting values converged; best log-likelihood -784.24; H_t positive definite at every date; out-of-sample h_t uses data up to t-1 only (tested). Not re-estimated during the out-of-sample period.
A53: TABLE 5. Diagnostics (paper Tables 2-3)
A54: Statistic | C54: rA castor meal | D54: rF CASTOR | E54: Source
A55: Observations | C55: =COUNT('Daily Analysis'!H5:H500) -> 496 | D55: =COUNT('Daily Analysis'!I5:I500) -> 496 | E55: Excel formula
A56: Standard deviation | C56: =STDEV('Daily Analysis'!H5:H500) -> 0.015974541 | D56: =STDEV('Daily Analysis'!I5:I500) -> 0.0066798288 | E56: Excel formula
A57: Skewness | C57: =SKEW('Daily Analysis'!H5:H500) -> 0.31790579 | D57: =SKEW('Daily Analysis'!I5:I500) -> 0.014753869 | E57: Excel formula
A58: Excess kurtosis | C58: =KURT('Daily Analysis'!H5:H500) -> 4.8820912 | D58: =KURT('Daily Analysis'!I5:I500) -> 1.237077 | E58: Excel formula
A59: Share of zero returns | C59: =COUNTIF('Daily Analysis'!H5:H500,0)/COUNT('Daily Analysis'!H5:H500) -> 0.32459677 | D59: =COUNTIF('Daily Analysis'!I5:I500,0)/COUNT('Daily Analysis'!I5:I500) -> 0.012096774 | E59: Excel formula
A60: Jarque-Bera = n/6 (S^2 + K^2/4) | C60: =C55/6*(C57^2+C58^2/4) -> 500.94079 | D60: =D55/6*(D57^2+D58^2/4) -> 31.645425
A61: Jarque-Bera p-value | C61: =CHIDIST(C60,2) -> 1.66759e-109 | D61: =CHIDIST(D60,2) -> 1.3436414e-07
A62: Ljung-Box Q(36) p-value | C62: 0.045454278 | D62: 0.24776154 | E62: Python
A63: ADF p-value, returns | C63: 1.1933938e-12 | D63: 0 | E63: Python
A64: ADF p-value, log price levels | C64: 0.61467995 | D64: 0.1353801 | E64: Python
A65: Engle-Granger cointegration p-value (levels) | C65: 0.81199223 | E65: Python: > 0.05, so no error-correction term
A67: TABLE 6. Roll-method comparison (same 496 return dates and split; Python, values). Not used to choose the rule.
A68: Roll rule | B68: Rolls | C68: h* | D68: HE in | E68: HE out | F68: Days held in tender period
A69: FINAL: OI signal, 1-day lag, 7-day backstop | B69: 36 | C69: 0.61356738 | D69: 0.067928977 | E69: 0.065878581 | F69: 0
A70: Fixed: 10 trading days before expiry (earlier version) | B70: 36 | C70: 0.61592979 | D70: 0.065378194 | E70: 0.065614745 | F70: 0
A71: OI signal, 1-day lag, no backstop | B71: 36 | C71: 0.55477801 | D71: 0.060218918 | E71: 0.0651187 | F71: 1
A72: Volume signal, 1-day lag, 7-day backstop | B72: 36 | C72: 0.60606675 | D72: 0.064165132 | E72: 0.065249299 | F72: 0
A73: Spot-month: hold until expiry (paper p.1) | B73: 36 | C73: 0.39733372 | D73: 0.040258947 | E73: 0.0302417 | F73: 108
A75: TABLE 7. Key audit checks
A76: Check | C76: Result | D76: Expected | E76: Pass?
A77: SEA quotes used (status OK) | C77: =COUNTIF('Spot Data'!$H$5:$H$651,"YES") -> 546 | D77: 546 | E77: =IF(C77=D77,"PASS",IF(ISNUMBER(C77),IF(ABS(C77-D77)<0.000000001,"PASS","FAIL"),"FAIL")) -> PASS
A78: SEA values confirmed on the live page (rows) | C78: =COUNTIF('Spot Data'!$J$5:$J$651,"matches*")+COUNTIF('Spot Data'!$J$5:$J$651,"fetched*") -> 647 | D78: 647 | E78: =IF(C78=D78,"PASS",IF(ISNUMBER(C78),IF(ABS(C78-D78)<0.000000001,"PASS","FAIL"),"FAIL")) -> PASS
A79: NCDEX trading days in the data | C79: =COUNT('Roll Schedule'!A47:A790) -> 744 | D79: 744 | E79: =IF(C79=D79,"PASS",IF(ISNUMBER(C79),IF(ABS(C79-D79)<0.000000001,"PASS","FAIL"),"FAIL")) -> PASS
A80: Contract chosen by Excel = contract chosen by Python (mismatching days) | C80: =COUNTIF('Roll Schedule'!S47:S790,FALSE()) -> 0 | D80: 0 | E80: =IF(C80=D80,"PASS",IF(ISNUMBER(C80),IF(ABS(C80-D80)<0.000000001,"PASS","FAIL"),"FAIL")) -> PASS
A81: Rolls | C81: =COUNTIF('Roll Schedule'!I47:I790,TRUE()) -> 36 | D81: 36 | E81: =IF(C81=D81,"PASS",IF(ISNUMBER(C81),IF(ABS(C81-D81)<0.000000001,"PASS","FAIL"),"FAIL")) -> PASS
A82: Futures returns that mix two contracts | C82: =COUNTIF('Roll Schedule'!T48:T790,FALSE()) -> 0 | D82: 0 | E82: =IF(C82=D82,"PASS",IF(ISNUMBER(C82),IF(ABS(C82-D82)<0.000000001,"PASS","FAIL"),"FAIL")) -> PASS
A83: Return days holding a contract in its tender period (last 3 days) | C83: =COUNTIF('Roll Schedule'!D48:D790,"<=2") -> 0 | D83: 0 | E83: =IF(C83=D83,"PASS",IF(ISNUMBER(C83),IF(ABS(C83-D83)<0.000000001,"PASS","FAIL"),"FAIL")) -> PASS
A84: Return days where the held contract did not trade | C84: =COUNTIF('Roll Schedule'!Q48:Q790,0) -> 0 | D84: 0 | E84: =IF(C84=D84,"PASS",IF(ISNUMBER(C84),IF(ABS(C84-D84)<0.000000001,"PASS","FAIL"),"FAIL")) -> PASS
A85: Matched return pairs | C85: =COUNT('Daily Analysis'!H5:H500) -> 496 | D85: 496 | E85: =IF(C85=D85,"PASS",IF(ISNUMBER(C85),IF(ABS(C85-D85)<0.000000001,"PASS","FAIL"),"FAIL")) -> PASS
A86: Missing spot lookups in Daily Analysis (zeros) | C86: =COUNTIF('Daily Analysis'!C5:D500,0) -> 0 | D86: 0 | E86: =IF(C86=D86,"PASS",IF(ISNUMBER(C86),IF(ABS(C86-D86)<0.000000001,"PASS","FAIL"),"FAIL")) -> PASS
A87: Days where LN change of additive back-adjusted series differs from held-contract return | C87: =SUMPRODUCT(--(ABS('Roll Schedule'!P48:P790-'Roll Schedule'!O48:O790)>0.000001)) -> 715 | D87: 715 | E87: =IF(C87=D87,"PASS",IF(ISNUMBER(C87),IF(ABS(C87-D87)<0.000000001,"PASS","FAIL"),"FAIL")) -> PASS
A88: OLS h*: Excel minus independent Python | C88: =C9-0.613567382430444 -> 0 | D88: 0 | E88: =IF(C88=D88,"PASS",IF(ISNUMBER(C88),IF(ABS(C88-D88)<0.000000001,"PASS","FAIL"),"FAIL")) -> PASS
A89: HE OLS in-sample: Excel minus Python | C89: =I18-0.0679289767629433 -> -1.9984014e-15 | D89: 0 | E89: =IF(C89=D89,"PASS",IF(ISNUMBER(C89),IF(ABS(C89-D89)<0.000000001,"PASS","FAIL"),"FAIL")) -> PASS
A90: HE OLS out-of-sample: Excel minus Python | C90: =I19-0.0658785807042258 -> 3.3306691e-16 | D90: 0 | E90: =IF(C90=D90,"PASS",IF(ISNUMBER(C90),IF(ABS(C90-D90)<0.000000001,"PASS","FAIL"),"FAIL")) -> PASS
A91: HE GARCH out-of-sample: Excel minus Python | C91: =I23-0.0702206550520033 -> 7.7715612e-16 | D91: 0 | E91: =IF(C91=D91,"PASS",IF(ISNUMBER(C91),IF(ABS(C91-D91)<0.000000001,"PASS","FAIL"),"FAIL")) -> PASS
A92: Sample split check | C92: =C6 -> TRUE | D92: =TRUE() -> TRUE | E92: =IF(C92=D92,"PASS",IF(ISNUMBER(C92),IF(ABS(C92-D92)<0.000000001,"PASS","FAIL"),"FAIL")) -> PASS
A93: All checks pass? | C93: =IF(COUNTIF(E77:E92,"FAIL")=0,"YES","NO") -> YES
A95: KEY LIMITATIONS
A96: - Seven-month spot gap: SEA published no castor meal quote from 27 Apr 2024 to 3 Dec 2024, so the 496 returns cover three calendar years with a hole; the gap is not filled.
A97: - Castor meal prices are SEA registered association quotes (not traded prices) and are unchanged on about one day in three, which weakens the measured correlation.
A98: - No castor meal futures exist; castor seed futures are a cross-hedge, so basis risk remains large (about 93% of variance is not hedged).
A99: - GARCH is estimated once on in-sample data and treats return pairs separated by missing quotes as consecutive; several parameters have large standard errors.
A100: - Ederington HE judges a conditional (GARCH) hedge on unconditional variance, which Buyukkara et al. (p.94) note is imperfect.
A101: - Roll backstop uses NCDEX's tender period (current specification) and a 2022 pre-expiry-margin circular that was not re-verified for 2023-26.
